Workbook

Sheet Raw Platform Nov 4-6 2025
A1: OrderDate | B1: Hour | C1: OrderID | D1: Alternate_Id | E1: Restaurant | F1: Location | G1: Platform | H1: TotalSales
A2: Nov 6, 2025 | B2: 13.0 | C2: E3753 | D2: d311e99e-8294-4ea3-8a62-c7860c4e3753 | E2: Siam - Thai Kitchen | F2: NSK NRB | G2: Uber KE | H2: 1890.0
A3: Nov 6, 2025 | B3: 17.0 | C3: 66951 | D3: a1db4ea7-4976-49d8-aaba-6fbc0b766951 | E3: Siam - Thai Kitchen | F3: Village Market NRB | G3: Uber KE | H3: 2390.0
A4: Nov 6, 2025 | B4: 13.0 | C4: C851C | D4: 510b3a2f-1439-431f-a743-5196b35c851c | E4: Khan's - Pakistani Kitchen | F4: Westlands NRB | G4: Uber KE | H4: 1500.0
A5: Nov 6, 2025 | B5: 12.0 | C5: 17A3F | D5: 88bf6653-8268-4004-a679-5f5a19617a3f | E5: Little Italy | F5: Kilimani NRB | G5: Uber KE | H5: 2250.0
A6: Nov 6, 2025 | B6: 21.0 | C6: 360EA | D6: f23ed8a5-0965-4c75-a146-a9a71cd360ea | E6: DILLI! - Curries & Grill | F6: Kilimani NRB | G6: Uber KE | H6: 1140.0
A7: Nov 6, 2025 | B7: 18.0 | C7: 0D2F0 | D7: 4b934bbd-7fdf-4bf8-b220-0f587270d2f0 | E7: Kai Sushi Bar | F7: Village Market NRB | G7: Uber KE | H7: 7040.0
A8: Nov 6, 2025 | B8: 19.0 | C8: DD3D4 | D8: d390f304-1588-4c00-9af2-ea35084dd3d4 | E8: Marty's Famous Burgers | F8: Kilimani NRB | G8: Uber KE | H8: 2080.0
A9: Nov 6, 2025 | B9: 8.0 | C9: 088F9 | D9: b203c4ca-6fc4-4636-84a1-6c36dcb088f9 | E9: SuperWings | F9: null | G9: Uber KE | H9: 10260.0
A10: Nov 6, 2025 | B10: 9.0 | C10: 139333 | D10: 11986 | E10: Khan's - Pakistani Kitchen | F10: Westlands NRB | G10: ANDO App | H10: 920.0
A11: Nov 6, 2025 | B11: 18.0 | C11: 676E0 | D11: 0ee617a6-4279-489a-bab1-02e454f676e0 | E11: Pasta Della Nonna | F11: NSK NRB | G11: Uber KE | H11: 2200.0
A12: Nov 6, 2025 | B12: 12.0 | C12: 101477071505 | D12: 101477071505 | E12: Siam - Thai Kitchen | F12: NSK NRB | G12: Glovo | H12: 2780.0
... A1561: Nov 4, 2025 | B1561: 18.0 | C1561: 4E153 | D1561: d481e341-9515-4433-a42a-39386384e153 | E1561: Little Italy | F1561: Cape Town SA | G1561: Uber SA | H1561: 280.0

Sheet Glovo Raw Nov 4-6 2025
A1: Restaurant name | B1: Order ID | C1: Restaurant ID | D1: Delivery Type | E1: Payment type | F1: Payment method | G1: Is Pro Order | H1: Restaurant Address | I1: Order status | J1: Order received at | K1: Accepted at | L1: Estimated ready to pick up time | M1: Ready to pick up at | N1: Rider near pickup at | O1: In delivery at | P1: Estimated delivery time | Q1: Delivered at | R1: Has Complaint? | S1: Complaint Reason | T1: Cancelled at | U1: Cancellation reason | V1: Cancellation owner | W1: Subtotal | X1: Service fee | Y1: Packaging charges | Z1: Minimum order value fee | AA1: Rider Tip | AB1: Delivery Fee | AC1: Vendor Refunds | AD1: Tax Charge | AE1: Online Payment Fee | AF1: Discount Funded by Vendor | AG1: Voucher Funded by Vendor | AH1: Commission | AI1: Vendor Charges | AJ1: Ads Fee | AK1: Wait time fee | AL1: Marketing Fees | AM1: Is Payable | AN1: Is Paid | AO1: Estimated earnings | AP1: Cash amount already collected by vendor | AQ1: Amount owed back to platform | AR1: Payout Amount | AS1: Platform-Funded Discount | AT1: Platform-Funded Voucher | AU1: Total Discount | AV1: Total Voucher | AW1: Tax Amount | AX1: Order Items
A2: Little Italy (PQ5Q+2W Nairobi) [NBO] | B2: 1.01475401774E11 | C2: 212504.0 | D2: Vendor delivery | E2: Online | G2: N | H2: PQ5Q+2W Nairobi, Kenya | I2: Delivered | J2: 45965.47777777778 | K2: 45965.478472222225 | O2: 45965.50625 | P2: 45965.51597222222 | Q2: 45965.561111111114 | R2: N | W2: 1210.0 | X2: 0.0 | Y2: 0.0 | Z2: 0.0 | AA2: 0.0 | AB2: 200.0 | AC2: 0.0 | AD2: 0.0 | AE2: 0.0 | AF2: 0.0 | AG2: 0.0 | AH2: 0.0 | AI2: 0.0 | AJ2: 0.0 | AK2: 0.0 | AO2: 1410.0 | AP2: 0.0 | AQ2: 0.0 | AR2: 1410.0 | AS2: 0.0 | AT2: 0.0 | AU2: 0.0 | AV2: 0.0 | AW2: 0.0 | AX2: 1 Mother’s Lasagna [1 No Cutlery]
A3: Little Italy (PQ5Q+2W Nairobi) [NBO] | B3: 1.01475497632E11 | C3: 212504.0 | D3: Vendor delivery | E3: Online | G3: N | H3: PQ5Q+2W Nairobi, Kenya | I3: Delivered | J3: 45965.592361111114 | K3: 45965.592361111114 | O3: 45965.620833333334 | P3: 45965.63055555556 | Q3: 45965.67569444444 | R3: N | W3: 1350.0 | X3: 0.0 | Y3: 0.0 | Z3: 0.0 | AA3: 0.0 | AB3: 200.0 | AC3: 0.0 | AD3: 0.0 | AE3: 0.0 | AF3: 0.0 | AG3: 0.0 | AH3: 0.0 | AI3: 0.0 | AJ3: 0.0 | AK3: 0.0 | AO3: 1550.0 | AP3: 0.0 | AQ3: 0.0 | AR3: 1550.0 | AS3: 0.0 | AT3: 0.0 | AU3: 0.0 | AV3: 0.0 | AW3: 0.0 | AX3: 1 Tagliatelle w/ Mushroom Cream Sauce - Single Portion [1 Grilled Chicken, 1 No Cutlery]
A4: Little Italy (PQ5Q+2W Nairobi) [NBO] | B4: 1.01475749857E11 | C4: 212504.0 | D4: Vendor delivery | E4: Online | G4: Y | H4: PQ5Q+2W Nairobi, Kenya | I4: Delivered | J4: 45965.77638888889 | K4: 45965.77638888889 | O4: 45965.791666666664 | P4: 45965.813888888886 | Q4: 45965.85972222222 | R4: N | W4: 4190.0 | X4: 0.0 | Y4: 0.0 | Z4: 0.0 | AA4: 0.0 | AB4: 0.0 | AC4: 0.0 | AD4: 0.0 | AE4: 0.0 | AF4: 0.0 | AG4: 0.0 | AH4: 0.0 | AI4: 0.0 | AJ4: 0.0 | AK4: 0.0 | AO4: 4190.0 | AP4: 0.0 | AQ4: 0.0 | AR4: 4190.0 | AS4: 0.0 | AT4: 0.0 | AU4: 0.0 | AV4: 0.0 | AW4: 0.0 | AX4: 1 Penne Arrabbiata - Single Portion [1 No Cutlery], 1 Tagliatelle w/ Mushroom Cream Sauce - Single Portion [1 Grilled Chicken], 1 Creamy Chicken & Mushroom Macaroni - Single Portion [1 No Cutlery], 3 Pepsi Cola 300ml
A5: Little Italy (PQ5Q+2W Nairobi) [NBO] | B5: 1.01475768452E11 | C5: 212504.0 | D5: Vendor delivery | E5: Online | G5: N | H5: PQ5Q+2W Nairobi, Kenya | I5: Delivered | J5: 45965.790972222225 | K5: 45965.791666666664 | O5: 45965.80625 | P5: 45965.82916666667 | Q5: 45965.87708333333 | R5: N | W5: 1150.0 | X5: 0.0 | Y5: 0.0 | Z5: 0.0 | AA5: 0.0 | AB5: 200.0 | AC5: 0.0 | AD5: 0.0 | AE5: 0.0 | AF5: 0.0 | AG5: 0.0 | AH5: 0.0 | AI5: 0.0 | AJ5: 0.0 | AK5: 0.0 | AO5: 1350.0 | AP5: 0.0 | AQ5: 0.0 | AR5: 1350.0 | AS5: 0.0 | AT5: 0.0 | AU5: 0.0 | AV5: 0.0 | AW5: 0.0 | AX5: 1 Penne Arrabbiata - Single Portion [1 Grilled Chicken]
A6: Little Italy (PQ5Q+2W Nairobi) [NBO] | B6: 1.01475788395E11 | C6: 212504.0 | D6: Vendor delivery | E6: Online | G6: Y | H6: PQ5Q+2W Nairobi, Kenya | I6: Delivered | J6: 45965.80694444444 | K6: 45965.80763888889 | O6: 45965.84652777778 | P6: 45965.845138888886 | Q6: 45965.89097222222 | R6: N | W6: 4000.0 | X6: 0.0 | Y6: 0.0 | Z6: 0.0 | AA6: 0.0 | AB6: 0.0 | AC6: 0.0 | AD6: 0.0 | AE6: 0.0 | AF6: 0.0 | AG6: 0.0 | AH6: 0.0 | AI6: 0.0 | AJ6: 0.0 | AK6: 0.0 | AO6: 4000.0 | AP6: 0.0 | AQ6: 0.0 | AR6: 4000.0 | AS6: 0.0 | AT6: 0.0 | AU6: 0.0 | AV6: 0.0 | AW6: 0.0 | AX6: 2 Spaghetti Bolognese - Double Portion [1 No Cutlery]
A7: Little Italy (PQ5Q+2W Nairobi) [NBO] | B7: 1.01475830948E11 | C7: 212504.0 | D7: Vendor delivery | E7: Online | G7: Y | H7: PQ5Q+2W Nairobi, Kenya | I7: Delivered | J7: 45965.839583333334 | K7: 45965.84027777778 | O7: 45965.87777777778 | P7: 45965.87777777778 | Q7: 45965.92569444444 | R7: N | W7: 3180.0 | X7: 0.0 | Y7: 0.0 | Z7: 0.0 | AA7: 0.0 | AB7: 0.0 | AC7: 0.0 | AD7: 0.0 | AE7: 0.0 | AF7: 0.0 | AG7: 0.0 | AH7: 0.0 | AI7: 0.0 | AJ7: 0.0 | AK7: 0.0 | AO7: 3180.0 | AP7: 0.0 | AQ7: 0.0 | AR7: 3180.0 | AS7: 0.0 | AT7: 0.0 | AU7: 0.0 | AV7: 0.0 | AW7: 0.0 | AX7: 1 Tagliatelle w/ Mushroom Cream Sauce - Single Portion [1 No Cutlery], 1 Mac & Cheese - Kids' Portion [1 No Cutlery], 1 Kale Caesar Salad w/ Grilled Chicken
A8: Little Italy (PQ5Q+2W Nairobi) [NBO] | B8: 1.01475872386E11 | C8: 212504.0 | D8: Vendor delivery | E8: Online | G8: Y | H8: PQ5Q+2W Nairobi, Kenya | I8: Delivered | J8: 45965.86875 | K8: 45965.86944444444 | O8: 45965.88333333333 | P8: 45965.90694444445 | Q8: 45965.95347222222 | R8: N | W8: 2100.0 | X8: 0.0 | Y8: 0.0 | Z8: 0.0 | AA8: 0.0 | AB8: 0.0 | AC8: 0.0 | AD8: 0.0 | AE8: 0.0 | AF8: 0.0 | AG8: 0.0 | AH8: 0.0 | AI8: 0.0 | AJ8: 0.0 | AK8: 0.0 | AO8: 2100.0 | AP8: 0.0 | AQ8: 0.0 | AR8: 2100.0 | AS8: 0.0 | AT8: 0.0 | AU8: 0.0 | AV8: 0.0 | AW8: 0.0 | AX8: 1 Creamy Chicken & Mushroom Macaroni - Double Portion [1 No Cutlery]
A9: Little Italy (PQ5Q+2W Nairobi) [NBO] | B9: 1.01476291902E11 | C9: 212504.0 | D9: Vendor delivery | E9: Online | G9: N | H9: PQ5Q+2W Nairobi, Kenya | I9: Delivered | J9: 45966.58194444444 | K9: 45966.58194444444 | O9: 45966.60277777778 | P9: 45966.62013888889 | Q9: 45966.66527777778 | R9: N | W9: 5770.0 | X9: 0.0 | Y9: 0.0 | Z9: 0.0 | AA9: 0.0 | AB9: 200.0 | AC9: 0.0 | AD9: 0.0 | AE9: 0.0 | AF9: 0.0 | AG9: 0.0 | AH9: 0.0 | AI9: 0.0 | AJ9: 0.0 | AK9: 0.0 | AO9: 5970.0 | AP9: 0.0 | AQ9: 0.0 | AR9: 5970.0 | AS9: 0.0 | AT9: 0.0 | AU9: 0.0 | AV9: 0.0 | AW9: 0.0 | AX9: 1 Mother’s Lasagna [1 BPA-Free Cutlery], 2 Penne Alfredo - Double Portion [1 Grilled Chicken, 1 BPA-Free Cutlery]
A10: Little Italy (PQ5Q+2W Nairobi) [NBO] | B10: 1.01476440702E11 | C10: 212504.0 | D10: Vendor delivery | E10: Online | G10: N | H10: PQ5Q+2W Nairobi, Kenya | I10: Delivered | J10: 45966.67916666667 | K10: 45966.67986111111 | O10: 45966.728472222225 | P10: 45966.717361111114 | Q10: 45966.76597222222 | R10: N | W10: 2250.0 | X10: 0.0 | Y10: 0.0 | Z10: 0.0 | AA10: 0.0 | AB10: 200.0 | AC10: 0.0 | AD10: 0.0 | AE10: 0.0 | AF10: 0.0 | AG10: 0.0 | AH10: 0.0 | AI10: 0.0 | AJ10: 0.0 | AK10: 0.0 | AO10: 2450.0 | AP10: 0.0 | AQ10: 0.0 | AR10: 2450.0 | AS10: 0.0 | AT10: 0.0 | AU10: 0.0 | AV10: 0.0 | AW10: 0.0 | AX10: 1 Penne Alfredo - Double Portion [1 Grilled Chicken]
A11: Little Italy (PQ5Q+2W Nairobi) [NBO] | B11: 1.01476440949E11 | C11: 212504.0 | D11: Vendor delivery | E11: Cash | G11: N | H11: PQ5Q+2W Nairobi, Kenya | I11: Delivered | J11: 45966.67986111111 | K11: 45966.67986111111 | O11: 45966.728472222225 | P11: 45966.717361111114 | Q11: 45966.76597222222 | R11: N | W11: 1210.0 | X11: 0.0 | Y11: 0.0 | Z11: 0.0 | AA11: 0.0 | AB11: 200.0 | AC11: 0.0 | AD11: 0.0 | AE11: 0.0 | AF11: 0.0 | AG11: 0.0 | AH11: 0.0 | AI11: 0.0 | AJ11: 0.0 | AK11: 0.0 | AO11: 1458.4 | AP11: 1210.0 | AQ11: 0.0 | AR11: 248.4 | AS11: 0.0 | AT11: 0.0 | AU11: 0.0 | AV11: 0.0 | AW11: 0.0 | AX11: 1 Mother’s Lasagna
A12: Little Italy (PQ5Q+2W Nairobi) [NBO] | B12: 1.01476626016E11 | C12: 212504.0 | D12: Vendor delivery | E12: Online | G12: Y | H12: PQ5Q+2W Nairobi, Kenya | I12: Delivered | J12: 45966.82152777778 | K12: 45966.82152777778 | O12: 45966.856944444444 | P12: 45966.85972222222 | Q12: 45966.90555555555 | R12: N | W12: 2730.0 | X12: 0.0 | Y12: 0.0 | Z12: 0.0 | AA12: 0.0 | AB12: 0.0 | AC12: 0.0 | AD12: 0.0 | AE12: 0.0 | AF12: 0.0 | AG12: 0.0 | AH12: 0.0 | AI12: 0.0 | AJ12: 0.0 | AK12: 0.0 | AO12: 2730.0 | AP12: 0.0 | AQ12: 0.0 | AR12: 2730.0 | AS12: 0.0 | AT12: 0.0 | AU12: 0.0 | AV12: 0.0 | AW12: 0.0 | AX12: 1 Mac & Cheese Regular, 1 Kale Caesar Salad w/ Grilled Chicken
A13: Little Italy (PQ5Q+2W Nairobi) [NBO] | B13: 1.01476638371E11 | C13: 212504.0 | D13: Vendor delivery | E13: Online | G13: N | H13: PQ5Q+2W Nairobi, Kenya | I13: Delivered | J13: 45966.830555555556 | K13: 45966.830555555556 | O13: 45966.856944444444 | P13: 45966.86875 | Q13: 45966.91527777778 | R13: N | W13: 2280.0 | X13: 0.0 | Y13: 0.0 | Z13: 0.0 | AA13: 0.0 | AB13: 200.0 | AC13: 0.0 | AD13: 0.0 | AE13: 0.0 | AF13: 0.0 | AG13: 0.0 | AH13: 0.0 | AI13: 0.0 | AJ13: 0.0 | AK13: 0.0 | AO13: 2480.0 | AP13: 0.0 | AQ13: 0.0 | AR13: 2480.0 | AS13: 0.0 | AT13: 0.0 | AU13: 0.0 | AV13: 0.0 | AW13: 0.0 | AX13: 1 Classic Tiramisu, 1 Penne Arrabbiata - Single Portion [1 Grilled Chicken], 1 Creamy Chicken and Mushroom Soup
... A19: Little Italy (PQ5Q+2W Nairobi) [NBO] | B19: 1.01477432217E11 | C19: 212504.0 | D19: Vendor delivery | E19: Online | G19: Y | H19: PQ5Q+2W Nairobi, Kenya | I19: Delivered | J19: 45967.78611111111 | K19: 45967.78611111111 | O19: 45967.84444444445 | P19: 45967.82430555556 | Q19: 45967.87013888889 | R19: N | W19: 1700.0 | X19: 0.0 | Y19: 0.0 | Z19: 0.0 | AA19: 0.0 | AB19: 0.0 | AC19: 0.0 | AD19: 0.0 | AE19: 0.0 | AF19: 0.0 | AG19: 0.0 | AH19: 0.0 | AI19: 0.0 | AJ19: 0.0 | AK19: 0.0 | AO19: 1700.0 | AP19: 0.0 | AQ19: 0.0 | AR19: 1700.0 | AS19: 0.0 | AT19: 0.0 | AU19: 0.0 | AV19: 0.0 | AW19: 0.0 | AX19: 1 Chef's Special Tomato Soup, 1 Lasagna Vegetariana
A20: Khan's - Pakistani Kitchen (Mpaka Rd) [NBO] | B20: 1.01475688322E11 | C20: 265592.0 | D20: Vendor delivery | E20: Online | G20: Y | H20: Mpaka Rd, Nairobi, Kenya | I20: Cancelled | J20: 45965.72430555556 | K20: 45965.72430555556 | P20: 45965.7625 | R20: N | T20: 45965.76875 | U20: Incorrect address | V20: Customer | W20: 2220.0 | X20: 0.0 | Y20: 0.0 | Z20: 0.0 | AA20: 0.0 | AB20: 0.0 | AC20: 2220.0 | AD20: 0.0 | AE20: 0.0 | AF20: 0.0 | AG20: 0.0 | AH20: 0.0 | AI20: 0.0 | AJ20: 0.0 | AK20: 0.0 | AM20: yes | AO20: 2220.0 | AP20: 0.0 | AQ20: 0.0 | AR20: 2220.0 | AS20: 0.0 | AT20: 0.0 | AU20: 0.0 | AV20: 0.0 | AW20: 0.0 | AX20: 1 Chicken Tikka Roll, 1 Tandoori Garlic Naan, 1 Paneer Tikka Roll, 1 Lahori Halwa
A21: Khan's - Pakistani Kitchen (Mpaka Rd) [NBO] | B21: 1.01475753619E11 | C21: 265592.0 | D21: Vendor delivery | E21: Online | G21: Y | H21: Mpaka Rd, Nairobi, Kenya | I21: Delivered | J21: 45965.77916666667 | K21: 45965.77916666667 | O21: 45965.82013888889 | P21: 45965.81736111111 | Q21: 45965.86319444444 | R21: N | W21: 2220.0 | X21: 0.0 | Y21: 0.0 | Z21: 0.0 | AA21: 0.0 | AB21: 0.0 | AC21: 0.0 | AD21: 0.0 | AE21: 0.0 | AF21: 0.0 | AG21: 0.0 | AH21: 0.0 | AI21: 0.0 | AJ21: 0.0 | AK21: 0.0 | AO21: 2220.0 | AP21: 0.0 | AQ21: 0.0 | AR21: 2220.0 | AS21: 0.0 | AT21: 0.0 | AU21: 0.0 | AV21: 0.0 | AW21: 0.0 | AX21: 1 Chicken Tikka Roll, 1 Tandoori Garlic Naan, 1 Paneer Tikka Roll, 1 Lahori Halwa
A22: Khan's - Pakistani Kitchen (Mpaka Rd) [NBO] | B22: 1.01475915025E11 | C22: 265592.0 | D22: Vendor delivery | E22: Online | G22: Y | H22: Mpaka Rd, Nairobi, Kenya | I22: Delivered | J22: 45965.89444444444 | K22: 45965.89513888889 | O22: 45965.90416666667 | P22: 45965.93263888889 | Q22: 45965.978472222225 | R22: N | W22: 990.0 | X22: 0.0 | Y22: 0.0 | Z22: 0.0 | AA22: 0.0 | AB22: 0.0 | AC22: 0.0 | AD22: 0.0 | AE22: 0.0 | AF22: 0.0 | AG22: 0.0 | AH22: 0.0 | AI22: 0.0 | AJ22: 0.0 | AK22: 0.0 | AO22: 990.0 | AP22: 0.0 | AQ22: 0.0 | AR22: 990.0 | AS22: 0.0 | AT22: 0.0 | AU22: 0.0 | AV22: 0.0 | AW22: 0.0 | AX22: 1 Chicken Tikka Biryani [1 BPA-Free Cutlery, 2 Single Portion - Serves 1 Person]
A23: Khan's - Pakistani Kitchen (Mpaka Rd) [NBO] | B23: 1.01476217037E11 | C23: 265592.0 | D23: Vendor delivery | E23: Online | G23: N | H23: Mpaka Rd, Nairobi, Kenya | I23: Delivered | J23: 45966.495833333334 | K23: 45966.495833333334 | O23: 45966.51944444444 | P23: 45966.53402777778 | Q23: 45966.58194444444 | R23: N | W23: 970.0 | X23: 0.0 | Y23: 0.0 | Z23: 0.0 | AA23: 0.0 | AB23: 200.0 | AC23: 0.0 | AD23: 0.0 | AE23: 0.0 | AF23: 0.0 | AG23: 0.0 | AH23: 0.0 | AI23: 0.0 | AJ23: 0.0 | AK23: 0.0 | AO23: 1170.0 | AP23: 0.0 | AQ23: 0.0 | AR23: 1170.0 | AS23: 0.0 | AT23: 0.0 | AU23: 0.0 | AV23: 0.0 | AW23: 0.0 | AX23: 1 Sindhi Boneless Chicken Biryani [1 Mild, 1 Single Portion - Serves 1 Person]
A24: Khan's - Pakistani Kitchen (Mpaka Rd) [NBO] | B24: 1.01476244412E11 | C24: 265592.0 | D24: Vendor delivery | E24: Online | G24: N | H24: Mpaka Rd, Nairobi, Kenya | I24: Delivered | J24: 45966.53333333333 | K24: 45966.53402777778 | O24: 45966.55069444444 | P24: 45966.57152777778 | Q24: 45966.62013888889 | R24: N | W24: 920.0 | X24: 0.0 | Y24: 0.0 | Z24: 0.0 | AA24: 0.0 | AB24: 200.0 | AC24: 0.0 | AD24: 0.0 | AE24: 0.0 | AF24: 0.0 | AG24: 0.0 | AH24: 0.0 | AI24: 0.0 | AJ24: 0.0 | AK24: 0.0 | AO24: 1120.0 | AP24: 0.0 | AQ24: 0.0 | AR24: 1120.0 | AS24: 0.0 | AT24: 0.0 | AU24: 0.0 | AV24: 0.0 | AW24: 0.0 | AX24: 1 Sindhi Chicken Biryani [1 Single Portion - Serves 1 Person, 1 Mild]
A25: Khan's - Pakistani Kitchen (Mpaka Rd) [NBO] | B25: 1.0147635894E11 | C25: 265592.0 | D25: Vendor delivery | E25: Online | G25: N | H25: Mpaka Rd, Nairobi, Kenya | I25: Picked up | J25: 45966.629166666666 | K25: 45966.629166666666 | O25: 45966.72152777778 | P25: 45966.66736111111 | Q25: 45966.71388888889 | R25: N | W25: 2320.0 | X25: 0.0 | Y25: 0.0 | Z25: 0.0 | AA25: 0.0 | AB25: 200.0 | AC25: 0.0 | AD25: 0.0 | AE25: 0.0 | AF25: 0.0 | AG25: 0.0 | AH25: 0.0 | AI25: 0.0 | AJ25: 0.0 | AK25: 0.0 | AO25: 2520.0 | AP25: 0.0 | AQ25: 0.0 | AR25: 2520.0 | AS25: 0.0 | AT25: 0.0 | AU25: 0.0 | AV25: 0.0 | AW25: 0.0 | AX25: 1 Paneer Tikka Biryani [1 No Cutlery, 1 Single Portion - Serves 1 Person], 1 Lahori Chicken Karahi - Single Portion [1 Tandoori Garlic Naan]
A26: Khan's - Pakistani Kitchen (Mpaka Rd) [NBO] | B26: 1.01476595353E11 | C26: 265592.0 | D26: Vendor delivery | E26: Cash | G26: N | H26: Mpaka Rd, Nairobi, Kenya | I26: Delivered | J26: 45966.79791666667 | K26: 45966.79861111111 | O26: 45966.81319444445 | P26: 45966.83611111111 | Q26: 45966.88402777778 | R26: N | W26: 2910.0 | X26: 0.0 | Y26: 0.0 | Z26: 0.0 | AA26: 0.0 | AB26: 200.0 | AC26: 0.0 | AD26: 0.0 | AE26: 0.0 | AF26: 0.0 | AG26: 0.0 | AH26: 0.0 | AI26: 0.0 | AJ26: 0.0 | AK26: 0.0 | AO26: 3219.0 | AP26: 0.0 | AQ26: 0.0 | AR26: 3219.0 | AS26: 0.0 | AT26: 0.0 | AU26: 0.0 | AV26: 0.0 | AW26: 0.0 | AX26: 1 Sindhi Boneless Chicken Biryani [1 Mild, 1 Single Portion - Serves 1 Person], 2 Chicken Tikka Biryani [1 No Cutlery, 2 Single Portion - Serves 1 Person]
A27: Khan's - Pakistani Kitchen (Mpaka Rd) [NBO] | B27: 1.01476630542E11 | C27: 265592.0 | D27: Vendor delivery | E27: Online | G27: N | H27: Mpaka Rd, Nairobi, Kenya | I27: Delivered | J27: 45966.82430555556 | K27: 45966.825 | O27: 45966.84652777778 | P27: 45966.8625 | Q27: 45966.90833333333 | R27: N | W27: 1250.0 | X27: 0.0 | Y27: 0.0 | Z27: 0.0 | AA27: 0.0 | AB27: 200.0 | AC27: 0.0 | AD27: 0.0 | AE27: 0.0 | AF27: 0.0 | AG27: 0.0 | AH27: 0.0 | AI27: 0.0 | AJ27: 0.0 | AK27: 0.0 | AO27: 1450.0 | AP27: 0.0 | AQ27: 0.0 | AR27: 1450.0 | AS27: 0.0 | AT27: 0.0 | AU27: 0.0 | AV27: 0.0 | AW27: 0.0 | AX27: 1 Chicken Tikka Roll, 1 Gulab Jamun
A28: Khan's - Pakistani Kitchen (Mpaka Rd) [NBO] | B28: 1.01476636956E11 | C28: 265592.0 | D28: Vendor delivery | E28: Online | G28: Y | H28: Mpaka Rd, Nairobi, Kenya | I28: Delivered | J28: 45966.82916666667 | K28: 45966.82916666667 | O28: 45966.84652777778 | P28: 45966.86736111111 | Q28: 45966.91527777778 | R28: N | W28: 1940.0 | X28: 0.0 | Y28: 0.0 | Z28: 0.0 | AA28: 0.0 | AB28: 0.0 | AC28: 0.0 | AD28: 0.0 | AE28: 0.0 | AF28: 0.0 | AG28: 0.0 | AH28: 0.0 | AI28: 0.0 | AJ28: 0.0 | AK28: 0.0 | AO28: 1940.0 | AP28: 0.0 | AQ28: 0.0 | AR28: 1940.0 | AS28: 0.0 | AT28: 0.0 | AU28: 0.0 | AV28: 0.0 | AW28: 0.0 | AX28: 2 Chicken Tikka Biryani [1 No Cutlery, 1 Single Portion - Serves 1 Person]
A29: Khan's - Pakistani Kitchen (Mpaka Rd) [NBO] | B29: 1.01477091498E11 | C29: 265592.0 | D29: Vendor delivery | E29: Online | G29: N | H29: Mpaka Rd, Nairobi, Kenya | I29: Delivered | J29: 45967.53888888889 | K29: 45967.53888888889 | O29: 45967.544444444444 | P29: 45967.57708333333 | Q29: 45967.623611111114 | R29: N | W29: 970.0 | X29: 0.0 | Y29: 0.0 | Z29: 0.0 | AA29: 0.0 | AB29: 200.0 | AC29: 0.0 | AD29: 0.0 | AE29: 0.0 | AF29: 0.0 | AG29: 0.0 | AH29: 0.0 | AI29: 0.0 | AJ29: 0.0 | AK29: 0.0 | AO29: 1170.0 | AP29: 0.0 | AQ29: 0.0 | AR29: 1170.0 | AS29: 0.0 | AT29: 0.0 | AU29: 0.0 | AV29: 0.0 | AW29: 0.0 | AX29: 1 Chicken Tikka Biryani [1 No Cutlery, 1 Single Portion - Serves 1 Person]
A30: Khan's - Pakistani Kitchen (Mpaka Rd) [NBO] | B30: 1.01477093687E11 | C30: 265592.0 | D30: Vendor delivery | E30: Online | G30: N | H30: Mpaka Rd, Nairobi, Kenya | I30: Delivered | J30: 45967.541666666664 | K30: 45967.541666666664 | O30: 45967.544444444444 | P30: 45967.57986111111 | Q30: 45967.62708333333 | R30: N | W30: 1410.0 | X30: 0.0 | Y30: 0.0 | Z30: 0.0 | AA30: 0.0 | AB30: 200.0 | AC30: 0.0 | AD30: 0.0 | AE30: 0.0 | AF30: 0.0 | AG30: 0.0 | AH30: 0.0 | AI30: 0.0 | AJ30: 0.0 | AK30: 0.0 | AO30: 1610.0 | AP30: 0.0 | AQ30: 0.0 | AR30: 1610.0 | AS30: 0.0 | AT30: 0.0 | AU30: 0.0 | AV30: 0.0 | AW30: 0.0 | AX30: 1 Mutton Karahi - Single Portion [1 Tandoori Butter Naan]
A31: Khan's - Pakistani Kitchen (Mpaka Rd) [NBO] | B31: 1.01477454686E11 | C31: 265592.0 | D31: Vendor delivery | E31: Online | G31: Y | H31: Mpaka Rd, Nairobi, Kenya | I31: Delivered | J31: 45967.802777777775 | K31: 45967.80347222222 | O31: 45967.83541666667 | P31: 45967.84097222222 | Q31: 45967.8875 | R31: N | W31: 970.0 | X31: 0.0 | Y31: 0.0 | Z31: 0.0 | AA31: 0.0 | AB31: 0.0 | AC31: 0.0 | AD31: 0.0 | AE31: 0.0 | AF31: 0.0 | AG31: 0.0 | AH31: 0.0 | AI31: 0.0 | AJ31: 0.0 | AK31: 0.0 | AO31: 970.0 | AP31: 0.0 | AQ31: 0.0 | AR31: 970.0 | AS31: 0.0 | AT31: 0.0 | AU31: 0.0 | AV31: 0.0 | AW31: 0.0 | AX31: 1 Chicken Tikka Biryani [1 No Cutlery, 1 Single Portion - Serves 1 Person]
A32: Khan's - Pakistani Kitchen (Mpaka Rd) [NBO] | B32: 1.01477463665E11 | C32: 265592.0 | D32: Vendor delivery | E32: Online | G32: N | H32: Mpaka Rd, Nairobi, Kenya | I32: Delivered | J32: 45967.80902777778 | K32: 45967.80972222222 | O32: 45967.85277777778 | P32: 45967.84722222222 | Q32: 45967.89444444444 | R32: N | W32: 860.0 | X32: 0.0 | Y32: 0.0 | Z32: 0.0 | AA32: 0.0 | AB32: 200.0 | AC32: 0.0 | AD32: 0.0 | AE32: 0.0 | AF32: 0.0 | AG32: 0.0 | AH32: 0.0 | AI32: 0.0 | AJ32: 0.0 | AK32: 0.0 | AO32: 1060.0 | AP32: 0.0 | AQ32: 0.0 | AR32: 1060.0 | AS32: 0.0 | AT32: 0.0 | AU32: 0.0 | AV32: 0.0 | AW32: 0.0 | AX32: 2 Gulab Jamun
... A42: Khan's - Pakistani Kitchen (Village Market) [NBO] | B42: 1.01475877409E11 | C42: 378030.0 | D42: Vendor delivery | E42: Cash | G42: N | H42: Village Market, Nairobi, Kenya | I42: Delivered | J42: 45965.87222222222 | K42: 45965.87222222222 | O42: 45965.90347222222 | P42: 45965.910416666666 | Q42: 45965.95694444444 | R42: N | W42: 970.0 | X42: 0.0 | Y42: 0.0 | Z42: 0.0 | AA42: 0.0 | AB42: 0.0 | AC42: 0.0 | AD42: 0.0 | AE42: 0.0 | AF42: 0.0 | AG42: 0.0 | AH42: 0.0 | AI42: 0.0 | AJ42: 0.0 | AK42: 0.0 | AO42: 989.4 | AP42: 0.0 | AQ42: 0.0 | AR42: 989.4 | AS42: 0.0 | AT42: 0.0 | AU42: 0.0 | AV42: 0.0 | AW42: 0.0 | AX42: 1 Sindhi Boneless Chicken Biryani [1 Spicy (hot), 1 Single Portion - Serves 1 Person]
A43: DILLI! - Curries and Grill (Village Market) [NBO] | B43: 1.01475781046E11 | C43: 378071.0 | D43: Platform delivery | E43: Online | G43: N | H43: Village Market, Nairobi, Kenya | I43: Delivered | J43: 45965.80138888889 | K43: 45965.80138888889 | L43: 45965.81319444445 | M43: 45965.81319444445 | N43: 45965.80763888889 | O43: 45965.81319444445 | P43: 45965.83263888889 | Q43: 45965.82777777778 | R43: N | W43: 1270.0 | X43: 0.0 | Y43: 0.0 | Z43: 0.0 | AA43: 0.0 | AB43: 0.0 | AC43: 0.0 | AD43: 0.0 | AE43: 0.0 | AF43: 0.0 | AG43: 0.0 | AH43: 0.0 | AI43: 0.0 | AJ43: 0.0 | AK43: 0.0 | AO43: 1270.0 | AP43: 0.0 | AQ43: 0.0 | AR43: 1270.0 | AS43: 0.0 | AT43: 0.0 | AU43: 0.0 | AV43: 0.0 | AW43: 0.0 | AX43: 1 Tandoori Garlic Naan, 1 Dilliwala Butter Chicken [1 Tandoori Garlic Naan, 1 Single Portion - Serves 1, 1 Hot, 1 BPA-Free Cutlery]
A44: DILLI! - Curries and Grill (Village Market) [NBO] | B44: 1.01477434883E11 | C44: 378071.0 | D44: Platform delivery | E44: Online | G44: N | H44: Village Market, Nairobi, Kenya | I44: Delivered | J44: 45967.794444444444 | K44: 45967.794444444444 | L44: 45967.80486111111 | N44: 45967.80138888889 | O44: 45967.80625 | P44: 45967.82986111111 | Q44: 45967.82013888889 | R44: N | W44: 990.0 | X44: 0.0 | Y44: 0.0 | Z44: 0.0 | AA44: 0.0 | AB44: 0.0 | AC44: 0.0 | AD44: 0.0 | AE44: 0.0 | AF44: 0.0 | AG44: 0.0 | AH44: 0.0 | AI44: 0.0 | AJ44: 0.0 | AK44: 0.0 | AO44: 990.0 | AP44: 0.0 | AQ44: 0.0 | AR44: 990.0 | AS44: 0.0 | AT44: 0.0 | AU44: 0.0 | AV44: 0.0 | AW44: 0.0 | AX44: 1 Dilliwala Butter Chicken - Single Portion [1 Tandoori Garlic Naan, 1 Mild, 1 No Cutlery]
A45: DILLI! - Curries and Grill (Village Market) [NBO] | B45: 1.0147747393E11 | C45: 378071.0 | D45: Platform delivery | E45: Online | G45: N | H45: Village Market, Nairobi, Kenya | I45: Delivered | J45: 45967.81805555556 | K45: 45967.81805555556 | L45: 45967.82986111111 | N45: 45967.82638888889 | O45: 45967.82986111111 | P45: 45967.847916666666 | Q45: 45967.84652777778 | R45: N | W45: 1270.0 | X45: 0.0 | Y45: 0.0 | Z45: 0.0 | AA45: 0.0 | AB45: 0.0 | AC45: 0.0 | AD45: 0.0 | AE45: 0.0 | AF45: 0.0 | AG45: 0.0 | AH45: 0.0 | AI45: 0.0 | AJ45: 0.0 | AK45: 0.0 | AO45: 1270.0 | AP45: 0.0 | AQ45: 0.0 | AR45: 1270.0 | AS45: 0.0 | AT45: 0.0 | AU45: 0.0 | AV45: 0.0 | AW45: 0.0 | AX45: 1 Tandoori Garlic Naan, 1 Chicken Tikka Masala - Single Portion [1 Tandoori Garlic Naan, 1 Medium, 1 BPA-Free Cutlery]
A46: SuperWings (PQ5Q+2J8) [NBO] | B46: 1.01475412871E11 | C46: 475401.0 | D46: Vendor delivery | E46: Online | G46: N | H46: PQ5Q+2J8, Timau Road, Nairobi, Kenya | I46: Delivered | J46: 45965.49722222222 | K46: 45965.49791666667 | O46: 45965.52777777778 | P46: 45965.535416666666 | Q46: 45965.58194444444 | R46: N | W46: 850.0 | X46: 0.0 | Y46: 0.0 | Z46: 0.0 | AA46: 0.0 | AB46: 200.0 | AC46: 0.0 | AD46: 0.0 | AE46: 0.0 | AF46: 0.0 | AG46: 0.0 | AH46: 0.0 | AI46: 0.0 | AJ46: 0.0 | AK46: 0.0 | AO46: 1050.0 | AP46: 0.0 | AQ46: 0.0 | AR46: 1050.0 | AS46: 0.0 | AT46: 0.0 | AU46: 0.0 | AV46: 0.0 | AW46: 0.0 | AX46: 1 Traditional Buffalo Wings (Bone-in) [1 6pcs]
A47: SuperWings (PQ5Q+2J8) [NBO] | B47: 1.01475537113E11 | C47: 475401.0 | D47: Vendor delivery | E47: Online | G47: N | H47: PQ5Q+2J8, Timau Road, Nairobi, Kenya | I47: Delivered | J47: 45965.620833333334 | K47: 45965.620833333334 | O47: 45965.63958333333 | P47: 45965.65833333333 | Q47: 45965.70347222222 | R47: N | W47: 2400.0 | X47: 0.0 | Y47: 0.0 | Z47: 0.0 | AA47: 0.0 | AB47: 200.0 | AC47: 0.0 | AD47: 0.0 | AE47: 0.0 | AF47: 0.0 | AG47: 0.0 | AH47: 0.0 | AI47: 0.0 | AJ47: 0.0 | AK47: 0.0 | AO47: 2600.0 | AP47: 0.0 | AQ47: 0.0 | AR47: 2600.0 | AS47: 0.0 | AT47: 0.0 | AU47: 0.0 | AV47: 0.0 | AW47: 0.0 | AX47: 1 Teriyaki Wings (Boneless) [1 24pc]
A48: SuperWings (PQ5Q+2J8) [NBO] | B48: 1.01476318076E11 | C48: 475401.0 | D48: Vendor delivery | E48: Cash | G48: N | H48: PQ5Q+2J8, Timau Road, Nairobi, Kenya | I48: Delivered | J48: 45966.60208333333 | K48: 45966.60208333333 | O48: 45966.64375 | P48: 45966.64027777778 | Q48: 45966.686111111114 | R48: N | W48: 1750.0 | X48: 0.0 | Y48: 0.0 | Z48: 0.0 | AA48: 0.0 | AB48: 200.0 | AC48: 0.0 | AD48: 0.0 | AE48: 0.0 | AF48: 0.0 | AG48: 0.0 | AH48: 0.0 | AI48: 0.0 | AJ48: 0.0 | AK48: 0.0 | AO48: 2020.0 | AP48: 0.0 | AQ48: 0.0 | AR48: 2020.0 | AS48: 0.0 | AT48: 0.0 | AU48: 0.0 | AV48: 0.0 | AW48: 0.0 | AX48: 1 Honey Mustard Wings (Boneless) [1 12pcs, 1 Add Classic Fries]
A49: SuperWings (PQ5Q+2J8) [NBO] | B49: 1.01477412193E11 | C49: 475401.0 | D49: Vendor delivery | E49: Online | G49: Y | H49: PQ5Q+2J8, Timau Road, Nairobi, Kenya | I49: Delivered | J49: 45967.770833333336 | K49: 45967.770833333336 | O49: 45967.8 | P49: 45967.80902777778 | Q49: 45967.85625 | R49: N | W49: 1150.0 | X49: 0.0 | Y49: 0.0 | Z49: 0.0 | AA49: 0.0 | AB49: 0.0 | AC49: 0.0 | AD49: 0.0 | AE49: 0.0 | AF49: 0.0 | AG49: 0.0 | AH49: 0.0 | AI49: 0.0 | AJ49: 0.0 | AK49: 0.0 | AO49: 1150.0 | AP49: 0.0 | AQ49: 0.0 | AR49: 1150.0 | AS49: 0.0 | AT49: 0.0 | AU49: 0.0 | AV49: 0.0 | AW49: 0.0 | AX49: 1 Korean-style Sweet & Spicy Wings (Boneless) [1 Add Classic Fries, 1 Ranch Dressing, 1 6pc]
A50: SuperWings (PRM3+FHW) [NBO] | B50: 1.01477498999E11 | C50: 499193.0 | D50: Vendor delivery | E50: Cash | G50: N | H50: PRM3+FHW, Nairobi, Kenya | I50: Delivered | J50: 45967.834027777775 | K50: 45967.83472222222 | O50: 45967.853472222225 | P50: 45967.87222222222 | Q50: 45967.91875 | R50: N | W50: 1550.0 | X50: 0.0 | Y50: 0.0 | Z50: 0.0 | AA50: 0.0 | AB50: 0.0 | AC50: 0.0 | AD50: 0.0 | AE50: 0.0 | AF50: 0.0 | AG50: 0.0 | AH50: 0.0 | AI50: 0.0 | AJ50: 0.0 | AK50: 0.0 | AO50: 1612.0 | AP50: 0.0 | AQ50: 0.0 | AR50: 1612.0 | AS50: 0.0 | AT50: 0.0 | AU50: 0.0 | AV50: 0.0 | AW50: 0.0 | AX50: 1 Teriyaki Wings (Bone-In) [1 12pc]
A51: Marty’s Famous Burgers (Timau Plaza) [NBO] | B51: 1.01475777555E11 | C51: 516342.0 | D51: Vendor delivery | E51: Cash | G51: N | H51: Timau Plaza, Nairobi, Kenya | I51: Delivered | J51: 45965.79861111111 | K51: 45965.79861111111 | O51: 45965.84652777778 | P51: 45965.836805555555 | Q51: 45965.88402777778 | R51: N | W51: 1900.0 | X51: 0.0 | Y51: 0.0 | Z51: 0.0 | AA51: 0.0 | AB51: 200.0 | AC51: 0.0 | AD51: 0.0 | AE51: 0.0 | AF51: 0.0 | AG51: 0.0 | AH51: 0.0 | AI51: 0.0 | AJ51: 0.0 | AK51: 0.0 | AO51: 2176.0 | AP51: 0.0 | AQ51: 0.0 | AR51: 2176.0 | AS51: 0.0 | AT51: 0.0 | AU51: 0.0 | AV51: 0.0 | AW51: 0.0 | AX51: 1 Marty's Shroom Special Classic, 1 Lemon Pepper Wings (Boneless)
A52: Marty’s Famous Burgers (Timau Plaza) [NBO] | B52: 1.01476719935E11 | C52: 516342.0 | D52: Vendor delivery | E52: Cash | G52: N | H52: Timau Plaza, Nairobi, Kenya | I52: Delivered | J52: 45966.88333333333 | K52: 45966.88333333333 | O52: 45966.89444444444 | P52: 45966.92152777778 | Q52: 45966.967361111114 | R52: N | W52: 2390.0 | X52: 0.0 | Y52: 0.0 | Z52: 0.0 | AA52: 0.0 | AB52: 200.0 | AC52: 0.0 | AD52: 0.0 | AE52: 0.0 | AF52: 0.0 | AG52: 0.0 | AH52: 0.0 | AI52: 0.0 | AJ52: 0.0 | AK52: 0.0 | AO52: 2685.6 | AP52: 0.0 | AQ52: 0.0 | AR52: 2685.6 | AS52: 0.0 | AT52: 0.0 | AU52: 0.0 | AV52: 0.0 | AW52: 0.0 | AX52: 1 Marty's Double Cheeseburger Classic, 1 Marty's Famous Cheeseburger Regular [1 Add Classic Fries], 1 Pepsi Cola 300ml
A53: Marty’s Famous Burgers (Timau Plaza) [NBO] | B53: 1.01477249215E11 | C53: 516342.0 | D53: Vendor delivery | E53: Online | G53: Y | H53: Timau Plaza, Nairobi, Kenya | I53: Delivered | J53: 45967.65694444445 | K53: 45967.65694444445 | O53: 45967.67361111111 | P53: 45967.69513888889 | Q53: 45967.686111111114 | R53: N | W53: 1490.0 | X53: 0.0 | Y53: 0.0 | Z53: 0.0 | AA53: 0.0 | AB53: 0.0 | AC53: 0.0 | AD53: 0.0 | AE53: 0.0 | AF53: 0.0 | AG53: 0.0 | AH53: 0.0 | AI53: 0.0 | AJ53: 0.0 | AK53: 0.0 | AO53: 1490.0 | AP53: 0.0 | AQ53: 0.0 | AR53: 1490.0 | AS53: 0.0 | AT53: 0.0 | AU53: 0.0 | AV53: 0.0 | AW53: 0.0 | AX53: 1 Minty Melonade, 1 Marty’s Famous Cheeseburger (Regular) + Classic Fries + Pepsi
A54: Marty’s Famous Burgers (Timau Plaza) [NBO] | B54: 1.0147745502E11 | C54: 516342.0 | D54: Vendor delivery | E54: Online | G54: N | H54: Timau Plaza, Nairobi, Kenya | I54: Delivered | J54: 45967.80347222222 | K54: 45967.80347222222 | O54: 45967.84444444445 | P54: 45967.84166666667 | Q54: 45967.8875 | R54: N | W54: 1100.0 | X54: 0.0 | Y54: 0.0 | Z54: 0.0 | AA54: 0.0 | AB54: 200.0 | AC54: 0.0 | AD54: 0.0 | AE54: 0.0 | AF54: 0.0 | AG54: 0.0 | AH54: 0.0 | AI54: 0.0 | AJ54: 0.0 | AK54: 0.0 | AO54: 1300.0 | AP54: 0.0 | AQ54: 0.0 | AR54: 1300.0 | AS54: 0.0 | AT54: 0.0 | AU54: 0.0 | AV54: 0.0 | AW54: 0.0 | AX54: 1 Marty’s Famous Cheeseburger (Regular) + Classic Fries + Pepsi
A55: Marty’s Famous Burgers (Timau Plaza) [NBO] | B55: 1.01477473155E11 | C55: 516342.0 | D55: Vendor delivery | E55: Cash | G55: Y | H55: Timau Plaza, Nairobi, Kenya | I55: Delivered | J55: 45967.81597222222 | K55: 45967.816666666666 | O55: 45967.865277777775 | P55: 45967.854166666664 | Q55: 45967.90138888889 | R55: N | W55: 1100.0 | X55: 0.0 | Y55: 0.0 | Z55: 0.0 | AA55: 0.0 | AB55: 0.0 | AC55: 0.0 | AD55: 0.0 | AE55: 0.0 | AF55: 0.0 | AG55: 0.0 | AH55: 0.0 | AI55: 0.0 | AJ55: 0.0 | AK55: 0.0 | AO55: 1100.0 | AP55: 0.0 | AQ55: 0.0 | AR55: 1100.0 | AS55: 0.0 | AT55: 0.0 | AU55: 0.0 | AV55: 0.0 | AW55: 0.0 | AX55: 1 Marty’s Famous Cheeseburger (Regular) + Classic Fries + Pepsi
A56: Marty’s Famous Burgers (Timau Plaza) [NBO] | B56: 1.01477514113E11 | C56: 516342.0 | D56: Vendor delivery | E56: Online | G56: N | H56: Timau Plaza, Nairobi, Kenya | I56: Picked up | J56: 45967.84444444445 | K56: 45967.84444444445 | O56: 45968.41458333333 | P56: 45967.88263888889 | Q56: 45967.92916666667 | R56: N | W56: 970.0 | X56: 0.0 | Y56: 0.0 | Z56: 0.0 | AA56: 0.0 | AB56: 200.0 | AC56: 0.0 | AD56: 0.0 | AE56: 0.0 | AF56: 0.0 | AG56: 0.0 | AH56: 0.0 | AI56: 0.0 | AJ56: 0.0 | AK56: 0.0 | AO56: 1170.0 | AP56: 0.0 | AQ56: 0.0 | AR56: 1170.0 | AS56: 0.0 | AT56: 0.0 | AU56: 0.0 | AV56: 0.0 | AW56: 0.0 | AX56: 1 Marty's Shroom Special Regular
A57: Marty’s Famous Burgers (PRM3+FHW Nairobi) [NBO] | B57: 1.01475546149E11 | C57: 561303.0 | D57: Vendor delivery | E57: Online | G57: Y | H57: PRM3+FHW Nairobi, Kenya | I57: Delivered | J57: 45965.626388888886 | K57: 45965.626388888886 | O57: 45965.67638888889 | P57: 45965.66458333333 | Q57: 45965.71041666667 | R57: N | W57: 990.0 | X57: 0.0 | Y57: 0.0 | Z57: 0.0 | AA57: 0.0 | AB57: 0.0 | AC57: 0.0 | AD57: 0.0 | AE57: 0.0 | AF57: 0.0 | AG57: 0.0 | AH57: 0.0 | AI57: 0.0 | AJ57: 0.0 | AK57: 0.0 | AO57: 990.0 | AP57: 0.0 | AQ57: 0.0 | AR57: 990.0 | AS57: 0.0 | AT57: 0.0 | AU57: 0.0 | AV57: 0.0 | AW57: 0.0 | AX57: 1 Marty's Double Cheeseburger Regular
... A74: Little Italy (Village Market) [NBO] | B74: 1.01477144178E11 | C74: 600955.0 | D74: Vendor delivery | E74: Cash | G74: N | H74: Village Market, Nairobi, Kenya | I74: Delivered | J74: 45967.58819444444 | K74: 45967.58819444444 | O74: 45967.595138888886 | P74: 45967.626388888886 | Q74: 45967.67222222222 | R74: N | W74: 1120.0 | X74: 0.0 | Y74: 0.0 | Z74: 0.0 | AA74: 0.0 | AB74: 200.0 | AC74: 0.0 | AD74: 0.0 | AE74: 0.0 | AF74: 0.0 | AG74: 0.0 | AH74: 0.0 | AI74: 0.0 | AJ74: 0.0 | AK74: 0.0 | AO74: 1364.8 | AP74: 1120.0 | AQ74: 0.0 | AR74: 244.8 | AS74: 0.0 | AT74: 0.0 | AU74: 0.0 | AV74: 0.0 | AW74: 0.0 | AX74: 1 Fusilli Pesto w/ Grilled Chicken - Single Portion
A75: Marty’s Famous Burgers (Village Market) [NBO] | B75: 1.01475517347E11 | C75: 601008.0 | D75: Platform delivery | E75: Online | G75: N | H75: Village Market, Nairobi, Kenya | I75: Delivered | J75: 45965.606944444444 | K75: 45965.606944444444 | L75: 45965.61736111111 | M75: 45965.61736111111 | N75: 45965.61319444444 | O75: 45965.62291666667 | P75: 45965.638194444444 | Q75: 45965.63402777778 | R75: N | W75: 1150.0 | X75: 0.0 | Y75: 0.0 | Z75: 0.0 | AA75: 0.0 | AB75: 0.0 | AC75: 0.0 | AD75: 0.0 | AE75: 0.0 | AF75: 0.0 | AG75: 0.0 | AH75: 0.0 | AI75: 0.0 | AJ75: 0.0 | AK75: 0.0 | AO75: 1150.0 | AP75: 0.0 | AQ75: 0.0 | AR75: 1150.0 | AS75: 0.0 | AT75: 0.0 | AU75: 0.0 | AV75: 0.0 | AW75: 0.0 | AX75: 1 Marty's Double Cheeseburger Classic
A76: Marty’s Famous Burgers (Village Market) [NBO] | B76: 1.01475707613E11 | C76: 601008.0 | D76: Platform delivery | E76: Online | G76: N | H76: Village Market, Nairobi, Kenya | I76: Delivered | J76: 45965.740277777775 | K76: 45965.740277777775 | L76: 45965.75277777778 | M76: 45965.754166666666 | N76: 45965.74791666667 | O76: 45965.75486111111 | P76: 45965.771527777775 | Q76: 45965.808333333334 | R76: N | W76: 2300.0 | X76: 0.0 | Y76: 0.0 | Z76: 0.0 | AA76: 0.0 | AB76: 0.0 | AC76: 0.0 | AD76: 0.0 | AE76: 0.0 | AF76: 0.0 | AG76: 0.0 | AH76: 0.0 | AI76: 0.0 | AJ76: 0.0 | AK76: 0.0 | AO76: 2300.0 | AP76: 0.0 | AQ76: 0.0 | AR76: 2300.0 | AS76: 0.0 | AT76: 0.0 | AU76: 0.0 | AV76: 0.0 | AW76: 0.0 | AX76: 2 Marty's Double Cheeseburger Classic
A77: Marty’s Famous Burgers (Village Market) [NBO] | B77: 1.01475834087E11 | C77: 601008.0 | D77: Platform delivery | E77: Online | G77: Y | H77: Village Market, Nairobi, Kenya | I77: Delivered | J77: 45965.842361111114 | K77: 45965.842361111114 | L77: 45965.85277777778 | M77: 45965.850694444445 | N77: 45965.850694444445 | O77: 45965.85972222222 | P77: 45965.873611111114 | Q77: 45965.87013888889 | R77: N | W77: 1240.0 | X77: 0.0 | Y77: 0.0 | Z77: 0.0 | AA77: 0.0 | AB77: 0.0 | AC77: 0.0 | AD77: 0.0 | AE77: 0.0 | AF77: 0.0 | AG77: 0.0 | AH77: 0.0 | AI77: 0.0 | AJ77: 0.0 | AK77: 0.0 | AO77: 1240.0 | AP77: 0.0 | AQ77: 0.0 | AR77: 1240.0 | AS77: 0.0 | AT77: 0.0 | AU77: 0.0 | AV77: 0.0 | AW77: 0.0 | AX77: 1 Marty's Double Cheeseburger Regular [1 Add Extra Prime Beef Patty]
A78: Bombay Canteen - Chai and Snacks (PRM3+FHW) [NBO] | B78: 1.01475370789E11 | C78: 611022.0 | D78: Vendor delivery | E78: Online | G78: Y | H78: PRM3+FHW, Nairobi, Kenya | I78: Delivered | J78: 45965.35972222222 | K78: 45965.35972222222 | O78: 45965.376388888886 | P78: 45965.3875 | Q78: 45965.44305555556 | R78: N | W78: 2230.0 | X78: 0.0 | Y78: 0.0 | Z78: 0.0 | AA78: 0.0 | AB78: 0.0 | AC78: 0.0 | AD78: 0.0 | AE78: 0.0 | AF78: 0.0 | AG78: 0.0 | AH78: 0.0 | AI78: 0.0 | AJ78: 0.0 | AK78: 0.0 | AO78: 2230.0 | AP78: 0.0 | AQ78: 0.0 | AR78: 2230.0 | AS78: 0.0 | AT78: 0.0 | AU78: 0.0 | AV78: 0.0 | AW78: 0.0 | AX78: 2 Paneer Tikka Paratha Roll, 1 Zafrani Chai - Signature Flask 500 ml
A79: Bombay Canteen - Chai and Snacks (PRM3+FHW) [NBO] | B79: 1.01475375557E11 | C79: 611022.0 | D79: Vendor delivery | E79: Online | G79: Y | H79: PRM3+FHW, Nairobi, Kenya | I79: Delivered | J79: 45965.39861111111 | K79: 45965.39861111111 | O79: 45965.41875 | P79: 45965.42638888889 | Q79: 45965.48472222222 | R79: N | W79: 740.0 | X79: 0.0 | Y79: 0.0 | Z79: 0.0 | AA79: 0.0 | AB79: 0.0 | AC79: 0.0 | AD79: 0.0 | AE79: 0.0 | AF79: 0.0 | AG79: 0.0 | AH79: 0.0 | AI79: 0.0 | AJ79: 0.0 | AK79: 0.0 | AO79: 740.0 | AP79: 0.0 | AQ79: 0.0 | AR79: 740.0 | AS79: 0.0 | AT79: 0.0 | AU79: 0.0 | AV79: 0.0 | AW79: 0.0 | AX79: 1 Beef Samosas, 1 NEW! Hot Chai Cup [1 Kadak Chai]
A80: Siam Thai Kitchen (PQ4Q+QV) [NBO] | B80: 1.01475418699E11 | C80: 618679.0 | D80: Vendor delivery | E80: Online | G80: Y | H80: PQ4Q+QV, Nairobi, Kenya | I80: Delivered | J80: 45965.50625 | K80: 45965.506944444445 | O80: 45965.52777777778 | P80: 45965.5375 | Q80: 45965.592361111114 | R80: N | W80: 1910.0 | X80: 0.0 | Y80: 0.0 | Z80: 0.0 | AA80: 0.0 | AB80: 0.0 | AC80: 0.0 | AD80: 0.0 | AE80: 0.0 | AF80: 0.0 | AG80: 0.0 | AH80: 0.0 | AI80: 0.0 | AJ80: 0.0 | AK80: 0.0 | AO80: 1910.0 | AP80: 0.0 | AQ80: 0.0 | AR80: 1910.0 | AS80: 0.0 | AT80: 0.0 | AU80: 0.0 | AV80: 0.0 | AW80: 0.0 | AX80: 1 Pad Thai w/ Chicken [1 BPA-Free Cutlery, 1 Double Portion]
A81: Siam Thai Kitchen (PQ4Q+QV) [NBO] | B81: 1.01475422579E11 | C81: 618679.0 | D81: Vendor delivery | E81: Online | G81: Y | H81: PQ4Q+QV, Nairobi, Kenya | I81: Delivered | J81: 45965.51180555556 | K81: 45965.5125 | O81: 45965.52777777778 | P81: 45965.54305555556 | Q81: 45965.59583333333 | R81: N | W81: 1210.0 | X81: 0.0 | Y81: 0.0 | Z81: 0.0 | AA81: 0.0 | AB81: 0.0 | AC81: 0.0 | AD81: 0.0 | AE81: 0.0 | AF81: 0.0 | AG81: 0.0 | AH81: 0.0 | AI81: 0.0 | AJ81: 0.0 | AK81: 0.0 | AO81: 1210.0 | AP81: 0.0 | AQ81: 0.0 | AR81: 1210.0 | AS81: 0.0 | AT81: 0.0 | AU81: 0.0 | AV81: 0.0 | AW81: 0.0 | AX81: 1 Pad Thai w/ Chicken [1 BPA-Free Cutlery, 1 Single Portion]
A82: Siam Thai Kitchen (PQ4Q+QV) [NBO] | B82: 1.01476268193E11 | C82: 618679.0 | D82: Vendor delivery | E82: Online | G82: N | H82: PQ4Q+QV, Nairobi, Kenya | I82: Delivered | J82: 45966.55972222222 | K82: 45966.55972222222 | O82: 45966.57013888889 | P82: 45966.59097222222 | Q82: 45966.64444444444 | R82: N | W82: 1190.0 | X82: 0.0 | Y82: 0.0 | Z82: 0.0 | AA82: 0.0 | AB82: 200.0 | AC82: 0.0 | AD82: 0.0 | AE82: 0.0 | AF82: 0.0 | AG82: 0.0 | AH82: 0.0 | AI82: 0.0 | AJ82: 0.0 | AK82: 0.0 | AO82: 1390.0 | AP82: 0.0 | AQ82: 0.0 | AR82: 1390.0 | AS82: 0.0 | AT82: 0.0 | AU82: 0.0 | AV82: 0.0 | AW82: 0.0 | AX82: 1 Spicy Drunken Noodles [1 BPA-Free Cutlery, 1 Chicken]
A83: Siam Thai Kitchen (PQ4Q+QV) [NBO] | B83: 1.01476462767E11 | C83: 618679.0 | D83: Vendor delivery | E83: Online | G83: N | H83: PQ4Q+QV, Nairobi, Kenya | I83: Delivered | J83: 45966.69375 | K83: 45966.694444444445 | O83: 45966.728472222225 | P83: 45966.725 | Q83: 45966.779861111114 | R83: N | W83: 1190.0 | X83: 0.0 | Y83: 0.0 | Z83: 0.0 | AA83: 0.0 | AB83: 200.0 | AC83: 0.0 | AD83: 0.0 | AE83: 0.0 | AF83: 0.0 | AG83: 0.0 | AH83: 0.0 | AI83: 0.0 | AJ83: 0.0 | AK83: 0.0 | AO83: 1390.0 | AP83: 0.0 | AQ83: 0.0 | AR83: 1390.0 | AS83: 0.0 | AT83: 0.0 | AU83: 0.0 | AV83: 0.0 | AW83: 0.0 | AX83: 1 Red Curry w/ Chicken & Jasmine Rice [1 No Cutlery, 1 Single Portion]
A84: Siam Thai Kitchen (PQ4Q+QV) [NBO] | B84: 1.0147666657E11 | C84: 618679.0 | D84: Vendor delivery | E84: Online | G84: N | H84: PQ4Q+QV, Nairobi, Kenya | I84: Delivered | J84: 45966.85 | K84: 45966.85 | O84: 45966.88402777778 | P84: 45966.88125 | Q84: 45966.936111111114 | R84: N | W84: 2140.0 | X84: 0.0 | Y84: 0.0 | Z84: 0.0 | AA84: 0.0 | AB84: 200.0 | AC84: 0.0 | AD84: 0.0 | AE84: 0.0 | AF84: 0.0 | AG84: 0.0 | AH84: 0.0 | AI84: 0.0 | AJ84: 0.0 | AK84: 0.0 | AO84: 2340.0 | AP84: 0.0 | AQ84: 0.0 | AR84: 2340.0 | AS84: 0.0 | AT84: 0.0 | AU84: 0.0 | AV84: 0.0 | AW84: 0.0 | AX84: 1 Pad Thai w/ Chicken [1 No Cutlery, 1 Single Portion], 1 House Special Chicken Fried Rice [1 No Cutlery]
A85: Siam Thai Kitchen (PQ4Q+QV) [NBO] | B85: 1.01477090931E11 | C85: 618679.0 | D85: Vendor delivery | E85: Online | G85: Y | H85: PQ4Q+QV, Nairobi, Kenya | I85: Delivered | J85: 45967.538194444445 | K85: 45967.538194444445 | O85: 45967.569444444445 | P85: 45967.569444444445 | Q85: 45967.623611111114 | R85: N | W85: 1190.0 | X85: 0.0 | Y85: 0.0 | Z85: 0.0 | AA85: 0.0 | AB85: 0.0 | AC85: 0.0 | AD85: 0.0 | AE85: 0.0 | AF85: 0.0 | AG85: 0.0 | AH85: 0.0 | AI85: 0.0 | AJ85: 0.0 | AK85: 0.0 | AO85: 1190.0 | AP85: 0.0 | AQ85: 0.0 | AR85: 1190.0 | AS85: 0.0 | AT85: 0.0 | AU85: 0.0 | AV85: 0.0 | AW85: 0.0 | AX85: 1 Pad Thai w/ Chicken [1 No Cutlery, 1 Single Portion]
A86: Siam Thai Kitchen (PQ4Q+QV) [NBO] | B86: 1.01477186634E11 | C86: 618679.0 | D86: Vendor delivery | E86: Online | G86: N | H86: PQ4Q+QV, Nairobi, Kenya | I86: Delivered | J86: 45967.61875 | K86: 45967.61875 | O86: 45967.63125 | P86: 45967.65 | Q86: 45967.70347222222 | R86: N | W86: 1190.0 | X86: 0.0 | Y86: 0.0 | Z86: 0.0 | AA86: 0.0 | AB86: 200.0 | AC86: 0.0 | AD86: 0.0 | AE86: 0.0 | AF86: 0.0 | AG86: 0.0 | AH86: 0.0 | AI86: 0.0 | AJ86: 0.0 | AK86: 0.0 | AO86: 1390.0 | AP86: 0.0 | AQ86: 0.0 | AR86: 1390.0 | AS86: 0.0 | AT86: 0.0 | AU86: 0.0 | AV86: 0.0 | AW86: 0.0 | AX86: 1 Spicy Drunken Noodles [1 BPA-Free Cutlery, 1 Chicken]
A87: Siam Thai Kitchen (PQ4Q+QV) [NBO] | B87: 1.01477220519E11 | C87: 618679.0 | D87: Vendor delivery | E87: Online | G87: N | H87: PQ4Q+QV, Nairobi, Kenya | I87: Delivered | J87: 45967.63958333333 | K87: 45967.64027777778 | O87: 45967.67361111111 | P87: 45967.67083333333 | Q87: 45967.72430555556 | R87: N | W87: 3020.0 | X87: 0.0 | Y87: 0.0 | Z87: 0.0 | AA87: 0.0 | AB87: 200.0 | AC87: 0.0 | AD87: 0.0 | AE87: 0.0 | AF87: 0.0 | AG87: 0.0 | AH87: 0.0 | AI87: 0.0 | AJ87: 0.0 | AK87: 0.0 | AO87: 3220.0 | AP87: 0.0 | AQ87: 0.0 | AR87: 3220.0 | AS87: 0.0 | AT87: 0.0 | AU87: 0.0 | AV87: 0.0 | AW87: 0.0 | AX87: 2 Red Curry w/ Chicken & Jasmine Rice [1 No Cutlery, 1 Single Portion, 1 Chicken (100g)]
A88: Siam Thai Kitchen (PQ4Q+QV) [NBO] | B88: 1.01477460377E11 | C88: 618679.0 | D88: Vendor delivery | E88: Online | G88: N | H88: PQ4Q+QV, Nairobi, Kenya | I88: Delivered | J88: 45967.80694444444 | K88: 45967.80694444444 | O88: 45967.84444444445 | P88: 45967.83819444444 | Q88: 45967.89097222222 | R88: N | W88: 1700.0 | X88: 0.0 | Y88: 0.0 | Z88: 0.0 | AA88: 0.0 | AB88: 200.0 | AC88: 0.0 | AD88: 0.0 | AE88: 0.0 | AF88: 0.0 | AG88: 0.0 | AH88: 0.0 | AI88: 0.0 | AJ88: 0.0 | AK88: 0.0 | AO88: 1900.0 | AP88: 0.0 | AQ88: 0.0 | AR88: 1900.0 | AS88: 0.0 | AT88: 0.0 | AU88: 0.0 | AV88: 0.0 | AW88: 0.0 | AX88: 1 Pad Thai w/ Chicken [1 Thai Iced Tea, 1 Compostable Chopsticks, 1 Single Portion]
A89: Siam Thai Kitchen (PRM3+FHW) [NBO] | B89: 1.01475548485E11 | C89: 626482.0 | D89: Vendor delivery | E89: Online | G89: N | H89: PRM3+FHW, Nairobi, Kenya | I89: Delivered | J89: 45965.62777777778 | K89: 45965.62777777778 | O89: 45965.63680555556 | P89: 45965.665972222225 | Q89: 45965.71388888889 | R89: N | W89: 1840.0 | X89: 0.0 | Y89: 0.0 | Z89: 0.0 | AA89: 0.0 | AB89: 200.0 | AC89: 0.0 | AD89: 0.0 | AE89: 0.0 | AF89: 0.0 | AG89: 0.0 | AH89: 0.0 | AI89: 0.0 | AJ89: 0.0 | AK89: 0.0 | AO89: 2040.0 | AP89: 0.0 | AQ89: 0.0 | AR89: 2040.0 | AS89: 0.0 | AT89: 0.0 | AU89: 0.0 | AV89: 0.0 | AW89: 0.0 | AX89: 1 Pad Thai w/ Chicken [1 BPA-Free Cutlery, 1 Lemongrass Ginger Iced Tea, 1 Tofu (100g), 1 Single Portion]
... A100: Siam Thai Kitchen (PRM3+FHW) [NBO] | B100: 1.01476507039E11 | C100: 626482.0 | D100: Vendor delivery | E100: Online | G100: Y | H100: PRM3+FHW, Nairobi, Kenya | I100: Delivered | J100: 45966.72638888889 | K100: 45966.72638888889 | O100: 45966.75902777778 | P100: 45966.76458333333 | Q100: 45966.811111111114 | R100: N | W100: 4380.0 | X100: 0.0 | Y100: 0.0 | Z100: 0.0 | AA100: 0.0 | AB100: 0.0 | AC100: 0.0 | AD100: 0.0 | AE100: 0.0 | AF100: 0.0 | AG100: 0.0 | AH100: 0.0 | AI100: 0.0 | AJ100: 0.0 | AK100: 0.0 | AO100: 4380.0 | AP100: 0.0 | AQ100: 0.0 | AR100: 4380.0 | AS100: 0.0 | AT100: 0.0 | AU100: 0.0 | AV100: 0.0 | AW100: 0.0 | AX100: 1 Crispy Spring Rolls [1 Veg], 1 Spicy Drunken Noodles [1 No Cutlery, 1 Tofu], 1 House Special Egg Fried Rice [1 No Cutlery], 1 Veg Dumplings [1 Deep-Fried, 1 Chilli Sauce], 1 Thai Papaya Salad
A101: Siam Thai Kitchen (PRM3+FHW) [NBO] | B101: 1.01476564577E11 | C101: 626482.0 | D101: Vendor delivery | E101: Online | G101: Y | H101: PRM3+FHW, Nairobi, Kenya | I101: Cancelled | J101: 45966.77361111111 | K101: 45966.77361111111 | O101: 45966.80694444444 | P101: 45966.81180555555 | R101: N | T101: 45966.82986111111 | U101: Unable to find customer | V101: Customer | W101: 1050.0 | X101: 0.0 | Y101: 0.0 | Z101: 0.0 | AA101: 0.0 | AB101: 0.0 | AC101: 1050.0 | AD101: 0.0 | AE101: 0.0 | AF101: 0.0 | AG101: 0.0 | AH101: 0.0 | AI101: 0.0 | AJ101: 0.0 | AK101: 0.0 | AM101: yes | AO101: 1050.0 | AP101: 0.0 | AQ101: 0.0 | AR101: 1050.0 | AS101: 0.0 | AT101: 0.0 | AU101: 0.0 | AV101: 0.0 | AW101: 0.0 | AX101: 1 Chicken Satay Skewers
A102: Siam Thai Kitchen (PRM3+FHW) [NBO] | B102: 1.01476576274E11 | C102: 626482.0 | D102: Vendor delivery | E102: Online | G102: N | H102: PRM3+FHW, Nairobi, Kenya | I102: Delivered | J102: 45966.782638888886 | K102: 45966.78333333333 | O102: 45966.80694444444 | P102: 45966.82083333333 | Q102: 45966.86666666667 | R102: N | W102: 1190.0 | X102: 0.0 | Y102: 0.0 | Z102: 0.0 | AA102: 0.0 | AB102: 200.0 | AC102: 0.0 | AD102: 0.0 | AE102: 0.0 | AF102: 0.0 | AG102: 0.0 | AH102: 0.0 | AI102: 0.0 | AJ102: 0.0 | AK102: 0.0 | AO102: 1390.0 | AP102: 0.0 | AQ102: 0.0 | AR102: 1390.0 | AS102: 0.0 | AT102: 0.0 | AU102: 0.0 | AV102: 0.0 | AW102: 0.0 | AX102: 1 Pad Thai w/ Chicken [1 No Cutlery, 1 Single Portion]
A103: Siam Thai Kitchen (PRM3+FHW) [NBO] | B103: 1.01477033017E11 | C103: 626482.0 | D103: Vendor delivery | E103: Online | G103: Y | H103: PRM3+FHW, Nairobi, Kenya | I103: Delivered | J103: 45967.44375 | K103: 45967.44375 | O103: 45967.47430555556 | P103: 45967.481944444444 | Q103: 45967.529861111114 | R103: N | W103: 1050.0 | X103: 0.0 | Y103: 0.0 | Z103: 0.0 | AA103: 0.0 | AB103: 0.0 | AC103: 0.0 | AD103: 0.0 | AE103: 0.0 | AF103: 0.0 | AG103: 0.0 | AH103: 0.0 | AI103: 0.0 | AJ103: 0.0 | AK103: 0.0 | AO103: 1050.0 | AP103: 0.0 | AQ103: 0.0 | AR103: 1050.0 | AS103: 0.0 | AT103: 0.0 | AU103: 0.0 | AV103: 0.0 | AW103: 0.0 | AX103: 1 Chicken Satay Skewers
A104: Siam Thai Kitchen (PRM3+FHW) [NBO] | B104: 1.01477051783E11 | C104: 626482.0 | D104: Vendor delivery | E104: Online | G104: N | H104: PRM3+FHW, Nairobi, Kenya | I104: Delivered | J104: 45967.48402777778 | K104: 45967.48402777778 | O104: 45967.50069444445 | P104: 45967.52222222222 | Q104: 45967.56805555556 | R104: N | W104: 3670.0 | X104: 0.0 | Y104: 0.0 | Z104: 0.0 | AA104: 0.0 | AB104: 200.0 | AC104: 0.0 | AD104: 0.0 | AE104: 0.0 | AF104: 0.0 | AG104: 0.0 | AH104: 0.0 | AI104: 0.0 | AJ104: 0.0 | AK104: 0.0 | AO104: 3870.0 | AP104: 0.0 | AQ104: 0.0 | AR104: 3870.0 | AS104: 0.0 | AT104: 0.0 | AU104: 0.0 | AV104: 0.0 | AW104: 0.0 | AX104: 2 Pad Thai w/ Chicken [1 Compostable Chopsticks, 1 Single Portion], 1 Chicken Dumplings [1 Pan-Fried, 1 Thai Chilli Oil]
A105: Siam Thai Kitchen (PRM3+FHW) [NBO] | B105: 1.01477070884E11 | C105: 626482.0 | D105: Vendor delivery | E105: Online | G105: Y | H105: PRM3+FHW, Nairobi, Kenya | I105: Delivered | J105: 45967.513194444444 | K105: 45967.513194444444 | O105: 45967.55486111111 | P105: 45967.55138888889 | Q105: 45967.59930555556 | R105: N | W105: 1190.0 | X105: 0.0 | Y105: 0.0 | Z105: 0.0 | AA105: 0.0 | AB105: 0.0 | AC105: 0.0 | AD105: 0.0 | AE105: 0.0 | AF105: 0.0 | AG105: 0.0 | AH105: 0.0 | AI105: 0.0 | AJ105: 0.0 | AK105: 0.0 | AO105: 1190.0 | AP105: 0.0 | AQ105: 0.0 | AR105: 1190.0 | AS105: 0.0 | AT105: 0.0 | AU105: 0.0 | AV105: 0.0 | AW105: 0.0 | AX105: 1 Red Curry w/ Chicken & Jasmine Rice [1 No Cutlery, 1 Single Portion]
A106: Siam Thai Kitchen (PRM3+FHW) [NBO] | B106: 1.01477071505E11 | C106: 626482.0 | D106: Vendor delivery | E106: Online | G106: N | H106: PRM3+FHW, Nairobi, Kenya | I106: Delivered | J106: 45967.51388888889 | K106: 45967.51388888889 | O106: 45967.55486111111 | P106: 45967.552083333336 | Q106: 45967.59930555556 | R106: N | W106: 1190.0 | X106: 0.0 | Y106: 0.0 | Z106: 0.0 | AA106: 0.0 | AB106: 200.0 | AC106: 0.0 | AD106: 0.0 | AE106: 0.0 | AF106: 0.0 | AG106: 0.0 | AH106: 0.0 | AI106: 0.0 | AJ106: 0.0 | AK106: 0.0 | AO106: 1390.0 | AP106: 0.0 | AQ106: 0.0 | AR106: 1390.0 | AS106: 0.0 | AT106: 0.0 | AU106: 0.0 | AV106: 0.0 | AW106: 0.0 | AX106: 1 Green Curry w/ Chicken & Jasmine Rice [1 No Cutlery, 1 Single Portion]
A107: Siam Thai Kitchen (PRM3+FHW) [NBO] | B107: 1.01477076629E11 | C107: 626482.0 | D107: Vendor delivery | E107: Online | G107: N | H107: PRM3+FHW, Nairobi, Kenya | I107: Delivered | J107: 45967.520833333336 | K107: 45967.520833333336 | O107: 45967.55486111111 | P107: 45967.55902777778 | Q107: 45967.60625 | R107: N | W107: 1190.0 | X107: 0.0 | Y107: 0.0 | Z107: 0.0 | AA107: 0.0 | AB107: 200.0 | AC107: 0.0 | AD107: 0.0 | AE107: 0.0 | AF107: 0.0 | AG107: 0.0 | AH107: 0.0 | AI107: 0.0 | AJ107: 0.0 | AK107: 0.0 | AO107: 1390.0 | AP107: 0.0 | AQ107: 0.0 | AR107: 1390.0 | AS107: 0.0 | AT107: 0.0 | AU107: 0.0 | AV107: 0.0 | AW107: 0.0 | AX107: 1 Pad Thai w/ Chicken [1 No Cutlery, 1 Single Portion]
A108: Siam Thai Kitchen (PRM3+FHW) [NBO] | B108: 1.01477118635E11 | C108: 626482.0 | D108: Vendor delivery | E108: Cash | G108: Y | H108: PRM3+FHW, Nairobi, Kenya | I108: Delivered | J108: 45967.56597222222 | K108: 45967.56597222222 | O108: 45967.572916666664 | P108: 45967.604166666664 | Q108: 45967.65138888889 | R108: N | W108: 600.0 | X108: 0.0 | Y108: 0.0 | Z108: 0.0 | AA108: 0.0 | AB108: 0.0 | AC108: 0.0 | AD108: 0.0 | AE108: 0.0 | AF108: 0.0 | AG108: 0.0 | AH108: 0.0 | AI108: 0.0 | AJ108: 0.0 | AK108: 0.0 | AO108: 600.0 | AP108: 600.0 | AQ108: 0.0 | AR108: 0.0 | AS108: 0.0 | AT108: 0.0 | AU108: 0.0 | AV108: 0.0 | AW108: 0.0 | AX108: 1 Tom Yum Soup [1 No Cutlery]
A109: Siam Thai Kitchen (PRM3+FHW) [NBO] | B109: 1.01477302535E11 | C109: 626482.0 | D109: Vendor delivery | E109: Cash | G109: Y | H109: PRM3+FHW, Nairobi, Kenya | I109: Delivered | J109: 45967.69027777778 | K109: 45967.69027777778 | O109: 45967.705555555556 | P109: 45967.728472222225 | Q109: 45967.77638888889 | R109: N | W109: 920.0 | X109: 0.0 | Y109: 0.0 | Z109: 0.0 | AA109: 0.0 | AB109: 0.0 | AC109: 0.0 | AD109: 0.0 | AE109: 0.0 | AF109: 0.0 | AG109: 0.0 | AH109: 0.0 | AI109: 0.0 | AJ109: 0.0 | AK109: 0.0 | AO109: 920.0 | AP109: 920.0 | AQ109: 0.0 | AR109: 0.0 | AS109: 0.0 | AT109: 0.0 | AU109: 0.0 | AV109: 0.0 | AW109: 0.0 | AX109: 1 Tom Yum Soup [1 No Cutlery, 1 Chicken (100g)]
A110: Siam Thai Kitchen (PRM3+FHW) [NBO] | B110: 1.0147747292E11 | C110: 626482.0 | D110: Vendor delivery | E110: Online | G110: Y | H110: PRM3+FHW, Nairobi, Kenya | I110: Delivered | J110: 45967.81597222222 | K110: 45967.81597222222 | O110: 45967.84583333333 | P110: 45967.854166666664 | Q110: 45967.90138888889 | R110: N | W110: 1610.0 | X110: 0.0 | Y110: 0.0 | Z110: 0.0 | AA110: 0.0 | AB110: 0.0 | AC110: 0.0 | AD110: 0.0 | AE110: 0.0 | AF110: 0.0 | AG110: 0.0 | AH110: 0.0 | AI110: 0.0 | AJ110: 0.0 | AK110: 0.0 | AO110: 1610.0 | AP110: 0.0 | AQ110: 0.0 | AR110: 1610.0 | AS110: 0.0 | AT110: 0.0 | AU110: 0.0 | AV110: 0.0 | AW110: 0.0 | AX110: 1 Pad Thai w/ Prawns [1 Compostable Chopsticks, 1 Single Portion]
A111: Siam Thai Kitchen (PRM3+FHW) [NBO] | B111: 1.01477515959E11 | C111: 626482.0 | D111: Vendor delivery | E111: Online | G111: N | H111: PRM3+FHW, Nairobi, Kenya | I111: Delivered | J111: 45967.84583333333 | K111: 45967.84583333333 | O111: 45967.89722222222 | P111: 45967.88402777778 | Q111: 45967.92916666667 | R111: N | W111: 2330.0 | X111: 0.0 | Y111: 0.0 | Z111: 0.0 | AA111: 0.0 | AB111: 200.0 | AC111: 0.0 | AD111: 0.0 | AE111: 0.0 | AF111: 0.0 | AG111: 0.0 | AH111: 0.0 | AI111: 0.0 | AJ111: 0.0 | AK111: 0.0 | AO111: 2530.0 | AP111: 0.0 | AQ111: 0.0 | AR111: 2530.0 | AS111: 0.0 | AT111: 0.0 | AU111: 0.0 | AV111: 0.0 | AW111: 0.0 | AX111: 1 Crispy Spring Rolls [1 Chicken], 1 Tom Yum Soup [1 No Cutlery], 1 Mango Sticky Rice, 1 Thai Papaya Salad
A112: Siam Thai Kitchen (PRM3+FHW) [NBO] | B112: 1.01477587223E11 | C112: 626482.0 | D112: Vendor delivery | E112: Cash | G112: N | H112: PRM3+FHW, Nairobi, Kenya | I112: Delivered | J112: 45967.888194444444 | K112: 45967.888194444444 | O112: 45967.90625 | P112: 45967.92638888889 | Q112: 45967.97430555556 | R112: N | W112: 1190.0 | X112: 0.0 | Y112: 0.0 | Z112: 0.0 | AA112: 0.0 | AB112: 200.0 | AC112: 0.0 | AD112: 0.0 | AE112: 0.0 | AF112: 0.0 | AG112: 0.0 | AH112: 0.0 | AI112: 0.0 | AJ112: 0.0 | AK112: 0.0 | AO112: 1437.6 | AP112: 0.0 | AQ112: 0.0 | AR112: 1437.6 | AS112: 0.0 | AT112: 0.0 | AU112: 0.0 | AV112: 0.0 | AW112: 0.0 | AX112: 1 Crispy Spring Rolls [1 Chicken], 1 Tom Yum Soup [1 No Cutlery]
A113: Siam Thai Kitchen (PRM3+FHW) [NBO] | B113: 1.01477623331E11 | C113: 626482.0 | D113: Vendor delivery | E113: Online | G113: N | H113: PRM3+FHW, Nairobi, Kenya | I113: Delivered | J113: 45967.90625 | K113: 45967.90694444445 | O113: 45967.938888888886 | P113: 45967.944444444445 | Q113: 45967.99166666667 | R113: N | W113: 5130.0 | X113: 0.0 | Y113: 0.0 | Z113: 0.0 | AA113: 0.0 | AB113: 200.0 | AC113: 0.0 | AD113: 0.0 | AE113: 0.0 | AF113: 0.0 | AG113: 0.0 | AH113: 0.0 | AI113: 0.0 | AJ113: 0.0 | AK113: 0.0 | AO113: 5330.0 | AP113: 0.0 | AQ113: 0.0 | AR113: 5330.0 | AS113: 0.0 | AT113: 0.0 | AU113: 0.0 | AV113: 0.0 | AW113: 0.0 | AX113: 1 Mango Sticky Rice, 1 Red Curry w/ Tofu & Jasmine Rice (Veg) [1 No Cutlery, 1 Single Portion], 1 Green Curry w/ Prawns & Jasmine Rice [1 No Cutlery, 1 Single Portion], 1 Veg Dumplings [1 Pan-Fried, 1 Thai Chilli Oil], 1 Thai Papaya Salad
... A145: ANDO Kitchens (PQ4Q+QV) [NBO] | B145: 1.01477440761E11 | C145: 651200.0 | D145: Vendor delivery | E145: Online | G145: Y | H145: PQ4Q+QV, Nairobi, Kenya | I145: Delivered | J145: 45967.79305555556 | K145: 45967.79305555556 | O145: 45967.84444444445 | P145: 45967.83125 | Q145: 45967.87708333333 | R145: N | W145: 1050.0 | X145: 0.0 | Y145: 0.0 | Z145: 0.0 | AA145: 0.0 | AB145: 0.0 | AC145: 0.0 | AD145: 0.0 | AE145: 0.0 | AF145: 0.0 | AG145: 0.0 | AH145: 0.0 | AI145: 0.0 | AJ145: 0.0 | AK145: 0.0 | AO145: 1050.0 | AP145: 0.0 | AQ145: 0.0 | AR145: 1050.0 | AS145: 0.0 | AT145: 0.0 | AU145: 0.0 | AV145: 0.0 | AW145: 0.0 | AX145: 1 Traditional Buffalo Wings (Boneless) [1 Add Classic Fries, 1 6pcs]
A146: ANDO Kitchens (QRC3+7W) [NBO] | B146: 1.01475668335E11 | C146: 651209.0 | D146: Platform delivery | E146: Online | G146: Y | H146: QRC3+7W, Nairobi, Kenya | I146: Delivered | J146: 45965.709027777775 | K146: 45965.709027777775 | L146: 45965.72083333333 | M146: 45965.722916666666 | N146: 45965.71597222222 | O146: 45965.722916666666 | P146: 45965.74652777778 | Q146: 45965.75833333333 | R146: N | W146: 3710.0 | X146: 0.0 | Y146: 0.0 | Z146: 0.0 | AA146: 0.0 | AB146: 0.0 | AC146: 0.0 | AD146: 0.0 | AE146: 0.0 | AF146: 0.0 | AG146: 0.0 | AH146: 0.0 | AI146: 0.0 | AJ146: 0.0 | AK146: 0.0 | AO146: 3710.0 | AP146: 0.0 | AQ146: 0.0 | AR146: 3710.0 | AS146: 0.0 | AT146: 0.0 | AU146: 0.0 | AV146: 0.0 | AW146: 0.0 | AX146: 1 Honey Mustard Wings (Bone-in) [1 12 Pcs], 1 Green Curry w/ Chicken & Jasmine Rice - Double Portion [1 BPA-Free Cutlery]
A147: Bibi's Swahili Kitchen (B Arcade kilimani 00100 Nairobi Kenya) [NBO] | B147: 1.01475411908E11 | C147: 694201.0 | D147: Vendor delivery | E147: Online | G147: N | H147: B Arcade kilimani 00100 Nairobi Kenya | I147: Delivered | J147: 45965.495833333334 | K147: 45965.49652777778 | O147: 45965.50625 | P147: 45965.53402777778 | Q147: 45965.58194444444 | R147: N | W147: 2970.0 | X147: 0.0 | Y147: 0.0 | Z147: 0.0 | AA147: 0.0 | AB147: 200.0 | AC147: 0.0 | AD147: 0.0 | AE147: 0.0 | AF147: 0.0 | AG147: 0.0 | AH147: 0.0 | AI147: 0.0 | AJ147: 0.0 | AK147: 0.0 | AO147: 3170.0 | AP147: 0.0 | AQ147: 0.0 | AR147: 3170.0 | AS147: 0.0 | AT147: 0.0 | AU147: 0.0 | AV147: 0.0 | AW147: 0.0 | AX147: 1 Mbuzi Karanga [1 Coconut Rice], 1 Mutton Pilau, 1 Bibi's Famous Chicken Biryani
A148: Bibi's Swahili Kitchen (B Arcade kilimani 00100 Nairobi Kenya) [NBO] | B148: 1.01475625949E11 | C148: 694201.0 | D148: Vendor delivery | E148: Online | G148: N | H148: B Arcade kilimani 00100 Nairobi Kenya | I148: Delivered | J148: 45965.67847222222 | K148: 45965.67847222222 | O148: 45965.69027777778 | P148: 45965.71666666667 | Q148: 45965.7625 | R148: N | W148: 1980.0 | X148: 0.0 | Y148: 0.0 | Z148: 0.0 | AA148: 0.0 | AB148: 200.0 | AC148: 0.0 | AD148: 0.0 | AE148: 0.0 | AF148: 0.0 | AG148: 0.0 | AH148: 0.0 | AI148: 0.0 | AJ148: 0.0 | AK148: 0.0 | AO148: 2180.0 | AP148: 0.0 | AQ148: 0.0 | AR148: 2180.0 | AS148: 0.0 | AT148: 0.0 | AU148: 0.0 | AV148: 0.0 | AW148: 0.0 | AX148: 2 Mbuzi Karanga [1 Coconut Rice]
A149: Bibi's Swahili Kitchen (B Arcade kilimani 00100 Nairobi Kenya) [NBO] | B149: 1.01475775992E11 | C149: 694201.0 | D149: Vendor delivery | E149: Online | G149: N | H149: B Arcade kilimani 00100 Nairobi Kenya | I149: Delivered | J149: 45965.79722222222 | K149: 45965.79722222222 | O149: 45965.84652777778 | P149: 45965.83541666667 | Q149: 45965.87847222222 | R149: Y | S149: Missing item | W149: 2470.0 | X149: 0.0 | Y149: 0.0 | Z149: 0.0 | AA149: 0.0 | AB149: 200.0 | AC149: 0.0 | AD149: 0.0 | AE149: 0.0 | AF149: 0.0 | AG149: 0.0 | AH149: 0.0 | AI149: 990.0 | AJ149: 0.0 | AK149: 0.0 | AO149: 1680.0 | AP149: 0.0 | AQ149: 0.0 | AR149: 1680.0 | AS149: 0.0 | AT149: 0.0 | AU149: 0.0 | AV149: 0.0 | AW149: 0.0 | AX149: 1 Mbuzi Karanga [1 Chapati], 1 Mutton Pilau, 1 Bhajias
A150: Bibi's Swahili Kitchen (B Arcade kilimani 00100 Nairobi Kenya) [NBO] | B150: 1.01475787442E11 | C150: 694201.0 | D150: Vendor delivery | E150: Online | G150: N | H150: B Arcade kilimani 00100 Nairobi Kenya | I150: Delivered | J150: 45965.80625 | K150: 45965.80625 | O150: 45965.84652777778 | P150: 45965.84444444445 | Q150: 45965.89097222222 | R150: N | W150: 1530.0 | X150: 0.0 | Y150: 0.0 | Z150: 0.0 | AA150: 0.0 | AB150: 200.0 | AC150: 0.0 | AD150: 0.0 | AE150: 0.0 | AF150: 0.0 | AG150: 0.0 | AH150: 0.0 | AI150: 0.0 | AJ150: 0.0 | AK150: 0.0 | AO150: 1730.0 | AP150: 0.0 | AQ150: 0.0 | AR150: 1730.0 | AS150: 0.0 | AT150: 0.0 | AU150: 0.0 | AV150: 0.0 | AW150: 0.0 | AX150: 1 Mutton Pilau, 1 Tamarind and Ginger Juice
A151: Bibi's Swahili Kitchen (B Arcade kilimani 00100 Nairobi Kenya) [NBO] | B151: 1.01475883375E11 | C151: 694201.0 | D151: Vendor delivery | E151: Online | G151: Y | H151: B Arcade kilimani 00100 Nairobi Kenya | I151: Picked up | J151: 45965.876388888886 | K151: 45965.87777777778 | O151: 45966.518055555556 | P151: 45965.91458333333 | Q151: 45965.96041666667 | R151: N | W151: 2940.0 | X151: 0.0 | Y151: 0.0 | Z151: 0.0 | AA151: 0.0 | AB151: 0.0 | AC151: 0.0 | AD151: 0.0 | AE151: 0.0 | AF151: 0.0 | AG151: 0.0 | AH151: 0.0 | AI151: 0.0 | AJ151: 0.0 | AK151: 0.0 | AO151: 2940.0 | AP151: 0.0 | AQ151: 0.0 | AR151: 2940.0 | AS151: 0.0 | AT151: 0.0 | AU151: 0.0 | AV151: 0.0 | AW151: 0.0 | AX151: 1 Mbuzi Karanga [1 Coconut Rice], 1 Kaimati, 1 Bibi's Famous Chicken Biryani, 1 Minty Melonade, 1 Pepsi Cola 300ml
A152: Bibi's Swahili Kitchen (B Arcade kilimani 00100 Nairobi Kenya) [NBO] | B152: 1.01476244801E11 | C152: 694201.0 | D152: Vendor delivery | E152: Online | G152: Y | H152: B Arcade kilimani 00100 Nairobi Kenya | I152: Delivered | J152: 45966.53402777778 | K152: 45966.53402777778 | O152: 45966.569444444445 | P152: 45966.572222222225 | Q152: 45966.62013888889 | R152: N | W152: 890.0 | X152: 0.0 | Y152: 0.0 | Z152: 0.0 | AA152: 0.0 | AB152: 0.0 | AC152: 0.0 | AD152: 0.0 | AE152: 0.0 | AF152: 0.0 | AG152: 0.0 | AH152: 0.0 | AI152: 0.0 | AJ152: 0.0 | AK152: 0.0 | AO152: 890.0 | AP152: 0.0 | AQ152: 0.0 | AR152: 890.0 | AS152: 0.0 | AT152: 0.0 | AU152: 0.0 | AV152: 0.0 | AW152: 0.0 | AX152: 1 Bibi's Famous Chicken Biryani
A153: Bibi's Swahili Kitchen (B Arcade kilimani 00100 Nairobi Kenya) [NBO] | B153: 1.01476256037E11 | C153: 694201.0 | D153: Vendor delivery | E153: Online | G153: N | H153: B Arcade kilimani 00100 Nairobi Kenya | I153: Delivered | J153: 45966.54722222222 | K153: 45966.54722222222 | O153: 45966.57013888889 | P153: 45966.58472222222 | Q153: 45966.63055555556 | R153: N | W153: 890.0 | X153: 0.0 | Y153: 0.0 | Z153: 0.0 | AA153: 0.0 | AB153: 200.0 | AC153: 0.0 | AD153: 0.0 | AE153: 0.0 | AF153: 0.0 | AG153: 0.0 | AH153: 0.0 | AI153: 0.0 | AJ153: 0.0 | AK153: 0.0 | AO153: 1090.0 | AP153: 0.0 | AQ153: 0.0 | AR153: 1090.0 | AS153: 0.0 | AT153: 0.0 | AU153: 0.0 | AV153: 0.0 | AW153: 0.0 | AX153: 1 Bibi's Famous Chicken Biryani
A154: Bibi's Swahili Kitchen (B Arcade kilimani 00100 Nairobi Kenya) [NBO] | B154: 1.01476558562E11 | C154: 694201.0 | D154: Vendor delivery | E154: Online | G154: Y | H154: B Arcade kilimani 00100 Nairobi Kenya | I154: Delivered | J154: 45966.76875 | K154: 45966.76875 | O154: 45966.80069444444 | P154: 45966.80694444444 | Q154: 45966.85277777778 | R154: N | W154: 990.0 | X154: 0.0 | Y154: 0.0 | Z154: 0.0 | AA154: 0.0 | AB154: 0.0 | AC154: 0.0 | AD154: 0.0 | AE154: 0.0 | AF154: 0.0 | AG154: 0.0 | AH154: 0.0 | AI154: 0.0 | AJ154: 0.0 | AK154: 0.0 | AO154: 990.0 | AP154: 0.0 | AQ154: 0.0 | AR154: 990.0 | AS154: 0.0 | AT154: 0.0 | AU154: 0.0 | AV154: 0.0 | AW154: 0.0 | AX154: 1 Mbuzi Karanga [1 Coconut Rice]
A155: Bibi's Swahili Kitchen (B Arcade kilimani 00100 Nairobi Kenya) [NBO] | B155: 1.01476644738E11 | C155: 694201.0 | D155: Vendor delivery | E155: Cash | G155: N | H155: B Arcade kilimani 00100 Nairobi Kenya | I155: Delivered | J155: 45966.83472222222 | K155: 45966.83541666667 | O155: 45966.84861111111 | P155: 45966.87291666667 | Q155: 45966.91875 | R155: N | W155: 1280.0 | X155: 0.0 | Y155: 0.0 | Z155: 0.0 | AA155: 0.0 | AB155: 200.0 | AC155: 0.0 | AD155: 0.0 | AE155: 0.0 | AF155: 0.0 | AG155: 0.0 | AH155: 0.0 | AI155: 0.0 | AJ155: 0.0 | AK155: 0.0 | AO155: 1531.2 | AP155: 1280.0 | AQ155: 0.0 | AR155: 251.2 | AS155: 0.0 | AT155: 0.0 | AU155: 0.0 | AV155: 0.0 | AW155: 0.0 | AX155: 1 Bhajias, 1 Bibi's Famous Chicken Biryani
A156: Bibi's Swahili Kitchen (B Arcade kilimani 00100 Nairobi Kenya) [NBO] | B156: 1.01477053694E11 | C156: 694201.0 | D156: Vendor delivery | E156: Cash | G156: N | H156: B Arcade kilimani 00100 Nairobi Kenya | I156: Delivered | J156: 45967.4875 | K156: 45967.4875 | O156: 45967.504166666666 | P156: 45967.52569444444 | Q156: 45967.57152777778 | R156: N | W156: 890.0 | X156: 0.0 | Y156: 0.0 | Z156: 0.0 | AA156: 0.0 | AB156: 200.0 | AC156: 0.0 | AD156: 0.0 | AE156: 0.0 | AF156: 0.0 | AG156: 0.0 | AH156: 0.0 | AI156: 0.0 | AJ156: 0.0 | AK156: 0.0 | AO156: 1125.6 | AP156: 890.0 | AQ156: 0.0 | AR156: 235.6 | AS156: 0.0 | AT156: 0.0 | AU156: 0.0 | AV156: 0.0 | AW156: 0.0 | AX156: 1 Bibi's Famous Chicken Biryani
A157: Bibi's Swahili Kitchen (B Arcade kilimani 00100 Nairobi Kenya) [NBO] | B157: 1.01477079083E11 | C157: 694201.0 | D157: Vendor delivery | E157: Online | G157: N | H157: B Arcade kilimani 00100 Nairobi Kenya | I157: Delivered | J157: 45967.524305555555 | K157: 45967.524305555555 | O157: 45967.55416666667 | P157: 45967.56180555555 | Q157: 45967.60972222222 | R157: N | W157: 2080.0 | X157: 0.0 | Y157: 0.0 | Z157: 0.0 | AA157: 0.0 | AB157: 200.0 | AC157: 0.0 | AD157: 0.0 | AE157: 0.0 | AF157: 0.0 | AG157: 0.0 | AH157: 0.0 | AI157: 0.0 | AJ157: 0.0 | AK157: 0.0 | AO157: 2280.0 | AP157: 0.0 | AQ157: 0.0 | AR157: 2280.0 | AS157: 0.0 | AT157: 0.0 | AU157: 0.0 | AV157: 0.0 | AW157: 0.0 | AX157: 1 Mbuzi Karanga [1 Chapati], 1 Mutton Pilau
A158: Bibi's Swahili Kitchen (B Arcade kilimani 00100 Nairobi Kenya) [NBO] | B158: 1.01477138528E11 | C158: 694201.0 | D158: Vendor delivery | E158: Online | G158: N | H158: B Arcade kilimani 00100 Nairobi Kenya | I158: Delivered | J158: 45967.584027777775 | K158: 45967.584027777775 | O158: 45967.63125 | P158: 45967.62222222222 | Q158: 45967.66875 | R158: N | W158: 2030.0 | X158: 0.0 | Y158: 0.0 | Z158: 0.0 | AA158: 0.0 | AB158: 200.0 | AC158: 0.0 | AD158: 0.0 | AE158: 0.0 | AF158: 0.0 | AG158: 0.0 | AH158: 0.0 | AI158: 0.0 | AJ158: 0.0 | AK158: 0.0 | AO158: 2230.0 | AP158: 0.0 | AQ158: 0.0 | AR158: 2230.0 | AS158: 0.0 | AT158: 0.0 | AU158: 0.0 | AV158: 0.0 | AW158: 0.0 | AX158: 1 Beef Samosas, 1 Samaki wa Nazi (Fish in Coconut)
A159: Bibi's Swahili Kitchen (B Arcade kilimani 00100 Nairobi Kenya) [NBO] | B159: 1.01477302149E11 | C159: 694201.0 | D159: Vendor delivery | E159: Cash | G159: N | H159: B Arcade kilimani 00100 Nairobi Kenya | I159: Delivered | J159: 45967.68958333333 | K159: 45967.69027777778 | O159: 45967.711805555555 | P159: 45967.72777777778 | Q159: 45967.77638888889 | R159: N | W159: 1970.0 | X159: 0.0 | Y159: 0.0 | Z159: 0.0 | AA159: 0.0 | AB159: 200.0 | AC159: 0.0 | AD159: 0.0 | AE159: 0.0 | AF159: 0.0 | AG159: 0.0 | AH159: 0.0 | AI159: 0.0 | AJ159: 0.0 | AK159: 0.0 | AO159: 2248.8 | AP159: 1970.0 | AQ159: 0.0 | AR159: 278.8 | AS159: 0.0 | AT159: 0.0 | AU159: 0.0 | AV159: 0.0 | AW159: 0.0 | AX159: 1 Mutton Pilau, 1 Mbaazi na Mahamri [1 Mahamri]
A160: Bibi's Swahili Kitchen (B Arcade kilimani 00100 Nairobi Kenya) [NBO] | B160: 1.01477540824E11 | C160: 694201.0 | D160: Vendor delivery | E160: Online | G160: Y | H160: B Arcade kilimani 00100 Nairobi Kenya | I160: Picked up | J160: 45967.861805555556 | K160: 45967.861805555556 | O160: 45968.41458333333 | P160: 45967.899305555555 | Q160: 45967.94652777778 | R160: N | W160: 880.0 | X160: 0.0 | Y160: 0.0 | Z160: 0.0 | AA160: 0.0 | AB160: 0.0 | AC160: 0.0 | AD160: 0.0 | AE160: 0.0 | AF160: 0.0 | AG160: 0.0 | AH160: 0.0 | AI160: 0.0 | AJ160: 0.0 | AK160: 0.0 | AO160: 880.0 | AP160: 0.0 | AQ160: 0.0 | AR160: 880.0 | AS160: 0.0 | AT160: 0.0 | AU160: 0.0 | AV160: 0.0 | AW160: 0.0 | AX160: 1 Bhajias, 1 Egg Rolex
A161: Bibi's Swahili Kitchen (B Arcade kilimani 00100 Nairobi Kenya) [NBO] | B161: 1.01477548502E11 | C161: 694201.0 | D161: Vendor delivery | E161: Online | G161: Y | H161: B Arcade kilimani 00100 Nairobi Kenya | I161: Picked up | J161: 45967.86597222222 | K161: 45967.86597222222 | O161: 45968.41458333333 | P161: 45967.90416666667 | Q161: 45967.950694444444 | R161: N | W161: 990.0 | X161: 0.0 | Y161: 0.0 | Z161: 0.0 | AA161: 0.0 | AB161: 0.0 | AC161: 0.0 | AD161: 0.0 | AE161: 0.0 | AF161: 0.0 | AG161: 0.0 | AH161: 0.0 | AI161: 0.0 | AJ161: 0.0 | AK161: 0.0 | AO161: 990.0 | AP161: 0.0 | AQ161: 0.0 | AR161: 990.0 | AS161: 0.0 | AT161: 0.0 | AU161: 0.0 | AV161: 0.0 | AW161: 0.0 | AX161: 1 Kuku Wa Kupaka [1 Coconut Rice]
A162: Curry Club (PRM3+FHW) [NBO] | B162: 1.01477239615E11 | C162: 724495.0 | D162: Platform delivery | E162: Online | G162: Y | H162: PRM3+FHW, Nairobi, Kenya | I162: Delivered | J162: 45967.65138888889 | K162: 45967.65138888889 | L162: 45967.660416666666 | M162: 45967.65972222222 | N162: 45967.65833333333 | O162: 45967.6625 | P162: 45967.68263888889 | Q162: 45967.675 | R162: N | W162: 1250.0 | X162: 0.0 | Y162: 0.0 | Z162: 0.0 | AA162: 0.0 | AB162: 0.0 | AC162: 0.0 | AD162: 0.0 | AE162: 0.0 | AF162: 0.0 | AG162: 0.0 | AH162: 0.0 | AI162: 0.0 | AJ162: 0.0 | AK162: 0.0 | AO162: 1250.0 | AP162: 0.0 | AQ162: 0.0 | AR162: 1250.0 | AS162: 0.0 | AT162: 0.0 | AU162: 0.0 | AV162: 0.0 | AW162: 0.0 | AX162: 1 Chicken Tikka Masala [1 Medium, 1 Tandoori Methi Naan], 1 Tandoori Methi naan
A163: Little Italy (Mpaka Rd) [NBO] | B163: 1.01475425597E11 | C163: 731381.0 | D163: Vendor delivery | E163: Online | G163: N | H163: Mpaka Rd, Nairobi, Kenya | I163: Delivered | J163: 45965.51597222222 | K163: 45965.51597222222 | O163: 45965.52847222222 | P163: 45965.55069444444 | Q163: 45965.54722222222 | R163: Y | S163: Wrong item | W163: 1440.0 | X163: 0.0 | Y163: 0.0 | Z163: 0.0 | AA163: 0.0 | AB163: 200.0 | AC163: 0.0 | AD163: 0.0 | AE163: 0.0 | AF163: 0.0 | AG163: 0.0 | AH163: 0.0 | AI163: 720.0 | AJ163: 0.0 | AK163: 0.0 | AO163: 920.0 | AP163: 0.0 | AQ163: 0.0 | AR163: 920.0 | AS163: 0.0 | AT163: 0.0 | AU163: 0.0 | AV163: 0.0 | AW163: 0.0 | AX163: 1 Kale Caesar Salad w/ Grilled Chicken
A164: Little Italy (Mpaka Rd) [NBO] | B164: 1.01475462213E11 | C164: 731381.0 | D164: Vendor delivery | E164: Online | G164: N | H164: Mpaka Rd, Nairobi, Kenya | I164: Delivered | J164: 45965.55972222222 | K164: 45965.55972222222 | O164: 45965.58888888889 | P164: 45965.59097222222 | Q164: 45965.64444444444 | R164: N | W164: 2410.0 | X164: 0.0 | Y164: 0.0 | Z164: 0.0 | AA164: 0.0 | AB164: 200.0 | AC164: 0.0 | AD164: 0.0 | AE164: 0.0 | AF164: 0.0 | AG164: 0.0 | AH164: 0.0 | AI164: 0.0 | AJ164: 0.0 | AK164: 0.0 | AO164: 2610.0 | AP164: 0.0 | AQ164: 0.0 | AR164: 2610.0 | AS164: 0.0 | AT164: 0.0 | AU164: 0.0 | AV164: 0.0 | AW164: 0.0 | AX164: 1 Fusilli Pesto w/ Grilled Chicken - Single Portion, 1 Mac & Cheese Regular
A165: Little Italy (Mpaka Rd) [NBO] | B165: 1.01475479917E11 | C165: 731381.0 | D165: Vendor delivery | E165: Cash | G165: N | H165: Mpaka Rd, Nairobi, Kenya | I165: Delivered | J165: 45965.57708333333 | K165: 45965.57708333333 | O165: 45965.58888888889 | P165: 45965.60833333333 | Q165: 45965.66180555556 | R165: N | W165: 1210.0 | X165: 0.0 | Y165: 0.0 | Z165: 0.0 | AA165: 0.0 | AB165: 200.0 | AC165: 0.0 | AD165: 0.0 | AE165: 0.0 | AF165: 0.0 | AG165: 0.0 | AH165: 0.0 | AI165: 0.0 | AJ165: 0.0 | AK165: 0.0 | AO165: 1458.4 | AP165: 1210.0 | AQ165: 0.0 | AR165: 248.4 | AS165: 0.0 | AT165: 0.0 | AU165: 0.0 | AV165: 0.0 | AW165: 0.0 | AX165: 1 Mother’s Lasagna
A166: Little Italy (Mpaka Rd) [NBO] | B166: 1.014755031E11 | C166: 731381.0 | D166: Vendor delivery | E166: Cash | G166: Y | H166: Mpaka Rd, Nairobi, Kenya | I166: Delivered | J166: 45965.59652777778 | K166: 45965.59652777778 | O166: 45965.60763888889 | P166: 45965.62777777778 | Q166: 45965.68263888889 | R166: N | W166: 2470.0 | X166: 0.0 | Y166: 0.0 | Z166: 0.0 | AA166: 0.0 | AB166: 0.0 | AC166: 0.0 | AD166: 0.0 | AE166: 0.0 | AF166: 0.0 | AG166: 0.0 | AH166: 0.0 | AI166: 0.0 | AJ166: 0.0 | AK166: 0.0 | AO166: 2470.0 | AP166: 0.0 | AQ166: 0.0 | AR166: 2470.0 | AS166: 0.0 | AT166: 0.0 | AU166: 0.0 | AV166: 0.0 | AW166: 0.0 | AX166: 1 Fusilli Pesto w/ Grilled Chicken - Double Portion, 1 Mixed Berry Crespelle
A167: Little Italy (Mpaka Rd) [NBO] | B167: 1.01475684394E11 | C167: 731381.0 | D167: Vendor delivery | E167: Online | G167: Y | H167: Mpaka Rd, Nairobi, Kenya | I167: Delivered | J167: 45965.72152777778 | K167: 45965.72152777778 | O167: 45965.73333333333 | P167: 45965.75625 | Q167: 45965.80763888889 | R167: N | W167: 2970.0 | X167: 0.0 | Y167: 0.0 | Z167: 0.0 | AA167: 0.0 | AB167: 0.0 | AC167: 0.0 | AD167: 0.0 | AE167: 0.0 | AF167: 0.0 | AG167: 0.0 | AH167: 0.0 | AI167: 0.0 | AJ167: 0.0 | AK167: 0.0 | AO167: 2970.0 | AP167: 0.0 | AQ167: 0.0 | AR167: 2970.0 | AS167: 0.0 | AT167: 0.0 | AU167: 0.0 | AV167: 0.0 | AW167: 0.0 | AX167: 1 Spaghetti Bolognese - Single Portion, 1 Mother’s Lasagna, 1 Mac & Cheese - Kids' Portion
A168: Little Italy (Mpaka Rd) [NBO] | B168: 1.01475828943E11 | C168: 731381.0 | D168: Vendor delivery | E168: Cash | G168: N | H168: Mpaka Rd, Nairobi, Kenya | I168: Delivered | J168: 45965.83819444444 | K168: 45965.83819444444 | O168: 45965.84861111111 | P168: 45965.86944444444 | Q168: 45965.92222222222 | R168: N | W168: 2370.0 | X168: 0.0 | Y168: 0.0 | Z168: 0.0 | AA168: 0.0 | AB168: 200.0 | AC168: 0.0 | AD168: 0.0 | AE168: 0.0 | AF168: 0.0 | AG168: 0.0 | AH168: 0.0 | AI168: 0.0 | AJ168: 0.0 | AK168: 0.0 | AO168: 2664.8 | AP168: 0.0 | AQ168: 0.0 | AR168: 2664.8 | AS168: 0.0 | AT168: 0.0 | AU168: 0.0 | AV168: 0.0 | AW168: 0.0 | AX168: 1 Fusilli Pesto w/ Grilled Chicken - Single Portion [1 BPA-Free Cutlery], 1 Papa’s Lasagna [1 BPA-Free Cutlery]
A169: Little Italy (Mpaka Rd) [NBO] | B169: 1.01475831417E11 | C169: 731381.0 | D169: Vendor delivery | E169: Cash | G169: N | H169: Mpaka Rd, Nairobi, Kenya | I169: Delivered | J169: 45965.84027777778 | K169: 45965.84027777778 | O169: 45965.84861111111 | P169: 45965.875 | Q169: 45965.92569444444 | R169: N | W169: 1070.0 | X169: 0.0 | Y169: 0.0 | Z169: 0.0 | AA169: 0.0 | AB169: 200.0 | AC169: 0.0 | AD169: 0.0 | AE169: 0.0 | AF169: 0.0 | AG169: 0.0 | AH169: 0.0 | AI169: 0.0 | AJ169: 0.0 | AK169: 0.0 | AO169: 1312.8 | AP169: 1070.0 | AQ169: 0.0 | AR169: 242.8 | AS169: 0.0 | AT169: 0.0 | AU169: 0.0 | AV169: 0.0 | AW169: 0.0 | AX169: 1 NEW! Spaghetti Chicken Bolognese - Single Portion
A170: Little Italy (Mpaka Rd) [NBO] | B170: 1.01475887393E11 | C170: 731381.0 | D170: Vendor delivery | E170: Online | G170: Y | H170: Mpaka Rd, Nairobi, Kenya | I170: Delivered | J170: 45965.87847222222 | K170: 45965.87847222222 | O170: 45965.884722222225 | P170: 45965.913194444445 | Q170: 45965.96388888889 | R170: N | W170: 1560.0 | X170: 0.0 | Y170: 0.0 | Z170: 0.0 | AA170: 0.0 | AB170: 0.0 | AC170: 0.0 | AD170: 0.0 | AE170: 0.0 | AF170: 0.0 | AG170: 0.0 | AH170: 0.0 | AI170: 0.0 | AJ170: 0.0 | AK170: 0.0 | AO170: 1560.0 | AP170: 0.0 | AQ170: 0.0 | AR170: 1560.0 | AS170: 0.0 | AT170: 0.0 | AU170: 0.0 | AV170: 0.0 | AW170: 0.0 | AX170: 1 Mother’s Lasagna [1 Classic Lemonade]
A171: Little Italy (Mpaka Rd) [NBO] | B171: 1.0147709792E11 | C171: 731381.0 | D171: Vendor delivery | E171: Online | G171: N | H171: Mpaka Rd, Nairobi, Kenya | I171: Delivered | J171: 45967.54583333333 | K171: 45967.54583333333 | O171: 45967.56458333333 | P171: 45967.57708333333 | Q171: 45967.63055555556 | R171: N | W171: 1210.0 | X171: 0.0 | Y171: 0.0 | Z171: 0.0 | AA171: 0.0 | AB171: 200.0 | AC171: 0.0 | AD171: 0.0 | AE171: 0.0 | AF171: 0.0 | AG171: 0.0 | AH171: 0.0 | AI171: 0.0 | AJ171: 0.0 | AK171: 0.0 | AO171: 1410.0 | AP171: 0.0 | AQ171: 0.0 | AR171: 1410.0 | AS171: 0.0 | AT171: 0.0 | AU171: 0.0 | AV171: 0.0 | AW171: 0.0 | AX171: 1 Lasagna Vegetariana
...

Sheet Auditing Nov 4-6 2025
A1: kitchen_code | B1: rider_username | C1: rider_name | D1: kitchen_name | E1: status | F1: order_id | G1: validated_id | H1: duplicate | I1: order_accepted_time | J1: order_source | K1: payment_status | L1: customer_name | M1: customer_number | N1: customer_address | O1: estimated_delivery_time | P1: estimated_delivery_distance | Q1: order_amount | R1: vehicle_type | S1: brand_name | T1: is_bulk | U1: is_earnings_processed | V1: assigned_at | W1: rejected_at | X1: delivery_fees
A2: nsk | B2: +2540794092505 | C2: Abdulaziz Juma Ebikes | D2: NSK NRB | E2: COMPLETED | F2: A6DF5 | G2: =IF(K2="Pick-up","PICKUPS",IF(K2="Staff drop-off","STAFF_DROPOFF",IF(K2="Replacements","REPLACEMENT",IF(K2="Central Stores Dispatch","CENTRAL STORES DISPATCH",IFNA(IFNA(VLOOKUP(F2,'Raw Platform Nov 4-6 2025'!C:C,1,FALSE),VLOOKUP(F2,'Raw Platform Nov 4-6 2025'!D:D,1,FALSE)),IFNA(VLOOKUP(F2,'Glovo Raw Nov 4-6 2025'!B:B,1,FALSE),"Not Matched")))))) | H2: =COUNTIF(F:F,F2) | I2: Nov 6, 2025, 9:45:14 PM | J2: Uber Eats | K2: UNPAID | L2: AMAURY F | M2: 0758992983 | N2: Westlands place apartments, Westlands Close, Nairobi, Kenya | O2: 2.0 | P2: 0.4 | Q2: 1960 | R2: BICYCLE | S2: Siam - Thai Kitchen | T2: false | U2: true | V2: Nov 6, 2025, 10:01:02 PM | X2: 0
A3: nsk | B3: +2540794092505 | C3: Abdulaziz Juma Ebikes | D3: NSK NRB | E3: COMPLETED | F3: 853EC | G3: =IF(K3="Pick-up","PICKUPS",IF(K3="Staff drop-off","STAFF_DROPOFF",IF(K3="Replacements","REPLACEMENT",IF(K3="Central Stores Dispatch","CENTRAL STORES DISPATCH",IFNA(IFNA(VLOOKUP(F3,'Raw Platform Nov 4-6 2025'!C:C,1,FALSE),VLOOKUP(F3,'Raw Platform Nov 4-6 2025'!D:D,1,FALSE)),IFNA(VLOOKUP(F3,'Glovo Raw Nov 4-6 2025'!B:B,1,FALSE),"Not Matched")))))) | H3: =COUNTIF(F:F,F3) | I3: Nov 6, 2025, 9:30:09 PM | J3: Uber Eats | K3: PAID | L3: CATIA P | M3: 0758992983 | N3: MP Shah Hospital, Shivachi Road, Nairobi, Kenya | O3: 7.0 | P3: 1.4 | Q3: 0 | R3: BICYCLE | S3: Siam - Thai Kitchen | T3: false | U3: true | V3: Nov 6, 2025, 9:47:37 PM | X3: 0
A4: nsk-copy | B4: +2540794092505 | C4: Abdulaziz Juma Ebikes | D4: NSK NRB | E4: COMPLETED | F4: 101477539337 | G4: =IF(K4="Pick-up","PICKUPS",IF(K4="Staff drop-off","STAFF_DROPOFF",IF(K4="Replacements","REPLACEMENT",IF(K4="Central Stores Dispatch","CENTRAL STORES DISPATCH",IFNA(IFNA(VLOOKUP(F4,'Raw Platform Nov 4-6 2025'!C:C,1,FALSE),VLOOKUP(F4,'Raw Platform Nov 4-6 2025'!D:D,1,FALSE)),IFNA(VLOOKUP(F4,'Glovo Raw Nov 4-6 2025'!B:B,1,FALSE),"Not Matched")))))) | H4: =COUNTIF(F:F,F4) | I4: Nov 6, 2025, 8:58:03 PM | J4: Glovo | K4: PAID | L4: MHMD | M4: 0792472323 | N4: Capital M Residences - LEED Certified, Muthithi Road, Nairobi, Kenya | O4: 2.0 | P4: 0.5 | Q4: 0 | R4: BICYCLE | S4: Little Italy | T4: false | U4: true | V4: Nov 6, 2025, 8:59:04 PM | X4: 0
A5: nsk | B5: +2540794092505 | C5: Abdulaziz Juma Ebikes | D5: NSK NRB | E5: COMPLETED | F5: FED45 | G5: =IF(K5="Pick-up","PICKUPS",IF(K5="Staff drop-off","STAFF_DROPOFF",IF(K5="Replacements","REPLACEMENT",IF(K5="Central Stores Dispatch","CENTRAL STORES DISPATCH",IFNA(IFNA(VLOOKUP(F5,'Raw Platform Nov 4-6 2025'!C:C,1,FALSE),VLOOKUP(F5,'Raw Platform Nov 4-6 2025'!D:D,1,FALSE)),IFNA(VLOOKUP(F5,'Glovo Raw Nov 4-6 2025'!B:B,1,FALSE),"Not Matched")))))) | H5: =COUNTIF(F:F,F5) | I5: Nov 6, 2025, 7:36:38 PM | J5: Uber Eats | K5: PAID | L5: STEPHANIE P | M5: 0745420817 | N5: CMM Gardens, Rhapta Road, Nairobi, Kenya | O5: 7.0 | P5: 2.8 | Q5: 0 | R5: BICYCLE | S5: Siam - Thai Kitchen | T5: false | U5: true | V5: Nov 6, 2025, 8:07:29 PM | X5: 0
A6: nsk | B6: +2540794092505 | C6: Abdulaziz Juma Ebikes | D6: NSK NRB | E6: COMPLETED | F6: 101477472920 | G6: =IF(K6="Pick-up","PICKUPS",IF(K6="Staff drop-off","STAFF_DROPOFF",IF(K6="Replacements","REPLACEMENT",IF(K6="Central Stores Dispatch","CENTRAL STORES DISPATCH",IFNA(IFNA(VLOOKUP(F6,'Raw Platform Nov 4-6 2025'!C:C,1,FALSE),VLOOKUP(F6,'Raw Platform Nov 4-6 2025'!D:D,1,FALSE)),IFNA(VLOOKUP(F6,'Glovo Raw Nov 4-6 2025'!B:B,1,FALSE),"Not Matched")))))) | H6: =COUNTIF(F:F,F6) | I6: Nov 6, 2025, 7:35:09 PM | J6: Glovo | K6: PAID | L6: IBRAHIM K | M6: 0759158120 | N6: Orchid Residency by Kaisa, Nairobi, Kenya | O6: 5.0 | P6: 2.1 | Q6: 0 | R6: BICYCLE | S6: Siam - Thai Kitchen | T6: false | U6: true | V6: Nov 6, 2025, 8:05:52 PM | X6: 0
A7: nsk-copy | B7: +2540794092505 | C7: Abdulaziz Juma Ebikes | D7: NSK NRB | E7: COMPLETED | F7: 501D9 | G7: =IF(K7="Pick-up","PICKUPS",IF(K7="Staff drop-off","STAFF_DROPOFF",IF(K7="Replacements","REPLACEMENT",IF(K7="Central Stores Dispatch","CENTRAL STORES DISPATCH",IFNA(IFNA(VLOOKUP(F7,'Raw Platform Nov 4-6 2025'!C:C,1,FALSE),VLOOKUP(F7,'Raw Platform Nov 4-6 2025'!D:D,1,FALSE)),IFNA(VLOOKUP(F7,'Glovo Raw Nov 4-6 2025'!B:B,1,FALSE),"Not Matched")))))) | H7: =COUNTIF(F:F,F7) | I7: Nov 6, 2025, 6:07:30 PM | J7: Uber Eats | K7: PAID | L7: NATALIE N | M7: +491602097107 | N7: Pleasant View Villas, Shanzu Road, Nairobi, Kenya | O7: 12.0 | P7: 4.0 | Q7: 0 | R7: BICYCLE | S7: Little Italy | T7: false | U7: true | V7: Nov 6, 2025, 6:14:27 PM | X7: 0
A8: nsk-copy | B8: +2540794092505 | C8: Abdulaziz Juma Ebikes | D8: NSK NRB | E8: COMPLETED | F8: A31AC | G8: =IF(K8="Pick-up","PICKUPS",IF(K8="Staff drop-off","STAFF_DROPOFF",IF(K8="Replacements","REPLACEMENT",IF(K8="Central Stores Dispatch","CENTRAL STORES DISPATCH",IFNA(IFNA(VLOOKUP(F8,'Raw Platform Nov 4-6 2025'!C:C,1,FALSE),VLOOKUP(F8,'Raw Platform Nov 4-6 2025'!D:D,1,FALSE)),IFNA(VLOOKUP(F8,'Glovo Raw Nov 4-6 2025'!B:B,1,FALSE),"Not Matched")))))) | H8: =COUNTIF(F:F,F8) | I8: Nov 6, 2025, 5:39:24 PM | J8: Uber Eats | K8: UNPAID | L8: WINNIE A | M8: 0722587621 | N8: The Piano, Brookside Drive, Nairobi, Kenya | O8: 6.0 | P8: 1.8 | Q8: 996 | R8: BICYCLE | S8: Little Italy | T8: false | U8: true | V8: Nov 6, 2025, 5:41:01 PM | X8: 0
A9: nsk-copy | B9: +2540794092505 | C9: Abdulaziz Juma Ebikes | D9: NSK NRB | E9: COMPLETED | F9: 2CAF1 | G9: =IF(K9="Pick-up","PICKUPS",IF(K9="Staff drop-off","STAFF_DROPOFF",IF(K9="Replacements","REPLACEMENT",IF(K9="Central Stores Dispatch","CENTRAL STORES DISPATCH",IFNA(IFNA(VLOOKUP(F9,'Raw Platform Nov 4-6 2025'!C:C,1,FALSE),VLOOKUP(F9,'Raw Platform Nov 4-6 2025'!D:D,1,FALSE)),IFNA(VLOOKUP(F9,'Glovo Raw Nov 4-6 2025'!B:B,1,FALSE),"Not Matched")))))) | H9: =COUNTIF(F:F,F9) | I9: Nov 6, 2025, 5:04:11 PM | J9: Uber Eats | K9: PAID | L9: LIA B | M9: 0708763422 | N9: 87 Rhapta Road, Nairobi, Kenya | O9: 5.0 | P9: 1.9 | Q9: 0 | R9: BICYCLE | S9: Little Italy | T9: false | U9: true | V9: Nov 6, 2025, 5:09:19 PM | X9: 0
A10: nsk | B10: +2540794092505 | C10: Abdulaziz Juma Ebikes | D10: NSK NRB | E10: COMPLETED | F10: 101477071505 | G10: =IF(K10="Pick-up","PICKUPS",IF(K10="Staff drop-off","STAFF_DROPOFF",IF(K10="Replacements","REPLACEMENT",IF(K10="Central Stores Dispatch","CENTRAL STORES DISPATCH",IFNA(IFNA(VLOOKUP(F10,'Raw Platform Nov 4-6 2025'!C:C,1,FALSE),VLOOKUP(F10,'Raw Platform Nov 4-6 2025'!D:D,1,FALSE)),IFNA(VLOOKUP(F10,'Glovo Raw Nov 4-6 2025'!B:B,1,FALSE),"Not Matched")))))) | H10: =COUNTIF(F:F,F10) | I10: Nov 6, 2025, 4:57:57 PM | J10: Glovo | K10: PAID | L10: INES | M10: 0758992983 | N10: McKinsey & Company Inc, Mzima Springs Lane, Nairobi, Kenya | O10: 10.0 | P10: 5.9 | Q10: 0 | R10: BICYCLE | S10: Siam - Thai Kitchen | T10: false | U10: true | V10: Nov 6, 2025, 4:59:35 PM | X10: 0
A11: nsk | B11: +2540794092505 | C11: Abdulaziz Juma Ebikes | D11: NSK NRB | E11: COMPLETED | F11: FF96A | G11: =IF(K11="Pick-up","PICKUPS",IF(K11="Staff drop-off","STAFF_DROPOFF",IF(K11="Replacements","REPLACEMENT",IF(K11="Central Stores Dispatch","CENTRAL STORES DISPATCH",IFNA(IFNA(VLOOKUP(F11,'Raw Platform Nov 4-6 2025'!C:C,1,FALSE),VLOOKUP(F11,'Raw Platform Nov 4-6 2025'!D:D,1,FALSE)),IFNA(VLOOKUP(F11,'Glovo Raw Nov 4-6 2025'!B:B,1,FALSE),"Not Matched")))))) | H11: =COUNTIF(F:F,F11) | I11: Nov 6, 2025, 4:55:00 PM | J11: Uber Eats | K11: PAID | L11: MAXIME S | M11: 0758992983 | N11: Delta Riverside Office Park, Riverside Drive, Nairobi, Kenya | O11: 6.0 | P11: 2.1 | Q11: 0 | R11: BICYCLE | S11: Siam - Thai Kitchen | T11: false | U11: true | V11: Nov 6, 2025, 5:00:47 PM | X11: 0
A12: nsk-copy | B12: +2540794092505 | C12: Abdulaziz Juma Ebikes | D12: NSK NRB | E12: COMPLETED | F12: A6151 | G12: =IF(K12="Pick-up","PICKUPS",IF(K12="Staff drop-off","STAFF_DROPOFF",IF(K12="Replacements","REPLACEMENT",IF(K12="Central Stores Dispatch","CENTRAL STORES DISPATCH",IFNA(IFNA(VLOOKUP(F12,'Raw Platform Nov 4-6 2025'!C:C,1,FALSE),VLOOKUP(F12,'Raw Platform Nov 4-6 2025'!D:D,1,FALSE)),IFNA(VLOOKUP(F12,'Glovo Raw Nov 4-6 2025'!B:B,1,FALSE),"Not Matched")))))) | H12: =COUNTIF(F:F,F12) | I12: Nov 6, 2025, 3:40:45 PM | J12: Uber Eats | K12: PAID | L12: AYAN M | M12: 0705252321 | N12: Clock Tower Suites, Mpaka Road, Nairobi, Kenya | O12: 7.0 | P12: 2.3 | Q12: 0 | R12: BICYCLE | S12: Little Italy | T12: false | U12: true | V12: Nov 6, 2025, 4:11:52 PM | X12: 0
A13: nsk-copy | B13: +2540794092505 | C13: Abdulaziz Juma Ebikes | D13: NSK NRB | E13: COMPLETED | F13: 64A37 | G13: =IF(K13="Pick-up","PICKUPS",IF(K13="Staff drop-off","STAFF_DROPOFF",IF(K13="Replacements","REPLACEMENT",IF(K13="Central Stores Dispatch","CENTRAL STORES DISPATCH",IFNA(IFNA(VLOOKUP(F13,'Raw Platform Nov 4-6 2025'!C:C,1,FALSE),VLOOKUP(F13,'Raw Platform Nov 4-6 2025'!D:D,1,FALSE)),IFNA(VLOOKUP(F13,'Glovo Raw Nov 4-6 2025'!B:B,1,FALSE),"Not Matched")))))) | H13: =COUNTIF(F:F,F13) | I13: Nov 6, 2025, 1:30:12 PM | J13: Uber Eats | K13: PAID | L13: SAMPA S | M13: +254116639992 | N13: Le'Mac, Church Road, Nairobi, Kenya | O13: 7.0 | P13: 3.0 | Q13: 0 | R13: BICYCLE | S13: Little Italy | T13: false | U13: true | V13: Nov 6, 2025, 1:35:15 PM | X13: 0
... A61: westlands | B61: +2540707098612 | C61: Benard Ogada | D61: Westlands NRB | E61: COMPLETED | F61: 95F5D | G61: =IF(K61="Pick-up","PICKUPS",IF(K61="Staff drop-off","STAFF_DROPOFF",IF(K61="Replacements","REPLACEMENT",IF(K61="Central Stores Dispatch","CENTRAL STORES DISPATCH",IFNA(IFNA(VLOOKUP(F61,'Raw Platform Nov 4-6 2025'!C:C,1,FALSE),VLOOKUP(F61,'Raw Platform Nov 4-6 2025'!D:D,1,FALSE)),IFNA(VLOOKUP(F61,'Glovo Raw Nov 4-6 2025'!B:B,1,FALSE),"Not Matched")))))) | H61: =COUNTIF(F:F,F61) | I61: Nov 6, 2025, 7:50:00 PM | J61: Uber Eats | K61: PAID | L61: Noreen | M61: 0705030903 | N61: Gatundu Crescent, Nairobi, Kenya | O61: 11.0 | P61: 4.5 | Q61: 0 | R61: MOTORCYCLE | S61: DILLI! - Curries & Grill | T61: false | U61: true | V61: Nov 6, 2025, 8:09:18 PM | X61: 146
A62: purvi-auro | B62: +2540707098612 | C62: Benard Ogada | E62: COMPLETED | F62: CF95B | G62: =IF(K62="Pick-up","PICKUPS",IF(K62="Staff drop-off","STAFF_DROPOFF",IF(K62="Replacements","REPLACEMENT",IF(K62="Central Stores Dispatch","CENTRAL STORES DISPATCH",IFNA(IFNA(VLOOKUP(F62,'Raw Platform Nov 4-6 2025'!C:C,1,FALSE),VLOOKUP(F62,'Raw Platform Nov 4-6 2025'!D:D,1,FALSE)),IFNA(VLOOKUP(F62,'Glovo Raw Nov 4-6 2025'!B:B,1,FALSE),"Not Matched")))))) | H62: =COUNTIF(F:F,F62) | I62: Nov 6, 2025, 6:57:16 PM | J62: Uber Eats | K62: PAID | L62: Elizabeth W | M62: 0714266979 | N62: Enaki Resort Residence, Nairobi, Kenya | O62: 14.0 | P62: 9.6 | Q62: 0 | R62: MOTORCYCLE | T62: false | U62: true | V62: Nov 6, 2025, 7:06:35 PM | X62: 263.3
A63: westlands | B63: +2540707098612 | C63: Benard Ogada | D63: Westlands NRB | E63: COMPLETED | F63: 101477381676 | G63: =IF(K63="Pick-up","PICKUPS",IF(K63="Staff drop-off","STAFF_DROPOFF",IF(K63="Replacements","REPLACEMENT",IF(K63="Central Stores Dispatch","CENTRAL STORES DISPATCH",IFNA(IFNA(VLOOKUP(F63,'Raw Platform Nov 4-6 2025'!C:C,1,FALSE),VLOOKUP(F63,'Raw Platform Nov 4-6 2025'!D:D,1,FALSE)),IFNA(VLOOKUP(F63,'Glovo Raw Nov 4-6 2025'!B:B,1,FALSE),"Not Matched")))))) | H63: =COUNTIF(F:F,F63) | I63: Nov 6, 2025, 5:56:25 PM | J63: Glovo | K63: PAID | L63: FREDERICK | M63: 0796757063 | N63: City Oasis Gardens, Argwings Kodhek Road, Nairobi, Kenya | O63: 14.0 | P63: 6.1 | Q63: 0 | R63: MOTORCYCLE | S63: Khan's Pakistani Kitchen | T63: false | U63: true | V63: Nov 6, 2025, 6:19:44 PM | X63: 182.8
A64: nsk | B64: +2540707098612 | C64: Benard Ogada | D64: NSK NRB | E64: COMPLETED | F64: 00909 | G64: =IF(K64="Pick-up","PICKUPS",IF(K64="Staff drop-off","STAFF_DROPOFF",IF(K64="Replacements","REPLACEMENT",IF(K64="Central Stores Dispatch","CENTRAL STORES DISPATCH",IFNA(IFNA(VLOOKUP(F64,'Raw Platform Nov 4-6 2025'!C:C,1,FALSE),VLOOKUP(F64,'Raw Platform Nov 4-6 2025'!D:D,1,FALSE)),IFNA(VLOOKUP(F64,'Glovo Raw Nov 4-6 2025'!B:B,1,FALSE),"Not Matched")))))) | H64: =COUNTIF(F:F,F64) | I64: Nov 6, 2025, 5:09:56 PM | J64: Uber Eats | K64: PAID | L64: CHANIA F | M64: 0758992983 | N64: McKinsey & Company Inc, Mzima Springs Lane, Nairobi, Kenya | O64: 10.0 | P64: 5.9 | Q64: 0 | R64: MOTORCYCLE | S64: Siam - Thai Kitchen | T64: false | U64: true | V64: Nov 6, 2025, 5:51:13 PM | X64: 178.2
A65: westlands | B65: +2540707098612 | C65: Benard Ogada | D65: Westlands NRB | E65: COMPLETED | F65: 394A9 | G65: =IF(K65="Pick-up","PICKUPS",IF(K65="Staff drop-off","STAFF_DROPOFF",IF(K65="Replacements","REPLACEMENT",IF(K65="Central Stores Dispatch","CENTRAL STORES DISPATCH",IFNA(IFNA(VLOOKUP(F65,'Raw Platform Nov 4-6 2025'!C:C,1,FALSE),VLOOKUP(F65,'Raw Platform Nov 4-6 2025'!D:D,1,FALSE)),IFNA(VLOOKUP(F65,'Glovo Raw Nov 4-6 2025'!B:B,1,FALSE),"Not Matched")))))) | H65: =COUNTIF(F:F,F65) | I65: Nov 6, 2025, 3:12:00 PM | J65: Uber Eats | K65: UNPAID | L65: Zakaria | M65: 0712883411 | N65: Sky View Heights, Nairobi, Kenya | O65: 19.0 | P65: 17.2 | Q65: 1590 | R65: MOTORCYCLE | S65: Marty's Famous Burgers | T65: false | U65: true | V65: Nov 6, 2025, 3:34:20 PM | X65: 438.1
A66: westlands | B66: +2540707098612 | C66: Benard Ogada | D66: Westlands NRB | E66: COMPLETED | F66: F1CC6 | G66: =IF(K66="Pick-up","PICKUPS",IF(K66="Staff drop-off","STAFF_DROPOFF",IF(K66="Replacements","REPLACEMENT",IF(K66="Central Stores Dispatch","CENTRAL STORES DISPATCH",IFNA(IFNA(VLOOKUP(F66,'Raw Platform Nov 4-6 2025'!C:C,1,FALSE),VLOOKUP(F66,'Raw Platform Nov 4-6 2025'!D:D,1,FALSE)),IFNA(VLOOKUP(F66,'Glovo Raw Nov 4-6 2025'!B:B,1,FALSE),"Not Matched")))))) | H66: =COUNTIF(F:F,F66) | I66: Nov 6, 2025, 1:56:24 PM | J66: Uber Eats | K66: PAID | L66: DABIEL O | M66: 0716112660 | N66: McKinsey & Company Inc, Mzima Springs Lane, Nairobi, Kenya | O66: 10.0 | P66: 5.8 | Q66: 0 | R66: MOTORCYCLE | S66: Khan's Pakistani Kitchen | T66: false | U66: true | V66: Nov 6, 2025, 2:14:44 PM | X66: 175.9
A67: nsk-copy | B67: +2540707098612 | C67: Benard Ogada | D67: NSK NRB | E67: COMPLETED | F67: PICKUPMILK,0,M | G67: =IF(K67="Pick-up","PICKUPS",IF(K67="Staff drop-off","STAFF_DROPOFF",IF(K67="Replacements","REPLACEMENT",IF(K67="Central Stores Dispatch","CENTRAL STORES DISPATCH",IFNA(IFNA(VLOOKUP(F67,'Raw Platform Nov 4-6 2025'!C:C,1,FALSE),VLOOKUP(F67,'Raw Platform Nov 4-6 2025'!D:D,1,FALSE)),IFNA(VLOOKUP(F67,'Glovo Raw Nov 4-6 2025'!B:B,1,FALSE),"Not Matched")))))) | H67: =COUNTIF(F:F,F67) | I67: Nov 6, 2025, 12:55:45 PM | J67: Pick-up | K67: PAID | L67: L.ITALY | M67: 0115133474 | N67: Purvi House, Nairobi, Kenya | O67: 0.0 | P67: 0.0 | Q67: 0 | R67: MOTORCYCLE | S67: Pick- Ups | T67: false | U67: true | V67: Nov 6, 2025, 12:56:59 PM | X67: 100
A68: nsk-copy | B68: +2540707098612 | C68: Benard Ogada | D68: NSK NRB | E68: COMPLETED | F68: B4C22 | G68: =IF(K68="Pick-up","PICKUPS",IF(K68="Staff drop-off","STAFF_DROPOFF",IF(K68="Replacements","REPLACEMENT",IF(K68="Central Stores Dispatch","CENTRAL STORES DISPATCH",IFNA(IFNA(VLOOKUP(F68,'Raw Platform Nov 4-6 2025'!C:C,1,FALSE),VLOOKUP(F68,'Raw Platform Nov 4-6 2025'!D:D,1,FALSE)),IFNA(VLOOKUP(F68,'Glovo Raw Nov 4-6 2025'!B:B,1,FALSE),"Not Matched")))))) | H68: =COUNTIF(F:F,F68) | I68: Nov 6, 2025, 12:35:19 PM | J68: Uber Eats | K68: PAID | L68: ALLAN M | M68: 0705474946 | N68: Financial Sector Deepening Africa - FSD Africa, Riverside Drive, Nairobi, Kenya | O68: 6.0 | P68: 2.3 | Q68: 0 | R68: MOTORCYCLE | S68: Little Italy | T68: false | U68: true | V68: Nov 6, 2025, 12:57:29 PM | X68: 100
A69: westlands | B69: +2540707098612 | C69: Benard Ogada | D69: Westlands NRB | E69: COMPLETED | F69: F29C2 | G69: =IF(K69="Pick-up","PICKUPS",IF(K69="Staff drop-off","STAFF_DROPOFF",IF(K69="Replacements","REPLACEMENT",IF(K69="Central Stores Dispatch","CENTRAL STORES DISPATCH",IFNA(IFNA(VLOOKUP(F69,'Raw Platform Nov 4-6 2025'!C:C,1,FALSE),VLOOKUP(F69,'Raw Platform Nov 4-6 2025'!D:D,1,FALSE)),IFNA(VLOOKUP(F69,'Glovo Raw Nov 4-6 2025'!B:B,1,FALSE),"Not Matched")))))) | H69: =COUNTIF(F:F,F69) | I69: Nov 6, 2025, 11:37:06 AM | J69: Uber Eats | K69: PAID | L69: Katherine m | M69: 0793535213 | N69: Krishna Views Apartment, General Mathenge Road, Nairobi, Kenya | O69: 9.0 | P69: 2.8 | Q69: 0 | R69: MOTORCYCLE | S69: DILLI! - Curries & Grill | T69: false | U69: true | V69: Nov 6, 2025, 12:15:39 PM | X69: 106.9
A70: westlands | B70: +2540707098612 | C70: Benard Ogada | D70: Westlands NRB | E70: COMPLETED | F70: 52B6D | G70: =IF(K70="Pick-up","PICKUPS",IF(K70="Staff drop-off","STAFF_DROPOFF",IF(K70="Replacements","REPLACEMENT",IF(K70="Central Stores Dispatch","CENTRAL STORES DISPATCH",IFNA(IFNA(VLOOKUP(F70,'Raw Platform Nov 4-6 2025'!C:C,1,FALSE),VLOOKUP(F70,'Raw Platform Nov 4-6 2025'!D:D,1,FALSE)),IFNA(VLOOKUP(F70,'Glovo Raw Nov 4-6 2025'!B:B,1,FALSE),"Not Matched")))))) | H70: =COUNTIF(F:F,F70) | I70: Nov 5, 2025, 6:39:24 PM | J70: Uber Eats | K70: PAID | L70: SAHER A | M70: 0741551950 | N70: The Soho Serviced Apartments, Kirichwa Road, Nairobi, Kenya | O70: 15.0 | P70: 6.1 | Q70: 0 | R70: MOTORCYCLE | S70: Khan's Pakistani Kitchen | T70: false | U70: true | V70: Nov 5, 2025, 6:55:30 PM | X70: 182.8
A71: westlands | B71: +2540707098612 | C71: Benard Ogada | D71: Westlands NRB | E71: COMPLETED | F71: 1.01476355587E11 | G71: =IF(K71="Pick-up","PICKUPS",IF(K71="Staff drop-off","STAFF_DROPOFF",IF(K71="Replacements","REPLACEMENT",IF(K71="Central Stores Dispatch","CENTRAL STORES DISPATCH",IFNA(IFNA(VLOOKUP(F71,'Raw Platform Nov 4-6 2025'!C:C,1,FALSE),VLOOKUP(F71,'Raw Platform Nov 4-6 2025'!D:D,1,FALSE)),IFNA(VLOOKUP(F71,'Glovo Raw Nov 4-6 2025'!B:B,1,FALSE),"Not Matched")))))) | H71: =COUNTIF(F:F,F71) | I71: Nov 5, 2025, 3:24:46 PM | J71: Glovo | K71: PAID | L71: SADIA-amedsadia | M71: 0725144794 | N71: Business Bay Square (BBS Mall), General Waruingi Road, Nairobi, Kenya | O71: 11.0 | P71: 6.9 | Q71: 0 | R71: MOTORCYCLE | S71: ANDO Kitchens | T71: false | U71: true | V71: Nov 5, 2025, 3:27:07 PM | X71: 201.2
A72: westlands | B72: +2540707098612 | C72: Benard Ogada | D72: Westlands NRB | E72: COMPLETED | F72: kilimani(75ML)5.11 | G72: =IF(K72="Pick-up","PICKUPS",IF(K72="Staff drop-off","STAFF_DROPOFF",IF(K72="Replacements","REPLACEMENT",IF(K72="Central Stores Dispatch","CENTRAL STORES DISPATCH",IFNA(IFNA(VLOOKUP(F72,'Raw Platform Nov 4-6 2025'!C:C,1,FALSE),VLOOKUP(F72,'Raw Platform Nov 4-6 2025'!D:D,1,FALSE)),IFNA(VLOOKUP(F72,'Glovo Raw Nov 4-6 2025'!B:B,1,FALSE),"Not Matched")))))) | H72: =COUNTIF(F:F,F72) | I72: Nov 5, 2025, 2:23:34 PM | J72: Central Stores Dispatch | K72: PAID | L72: PROCUMENT/ | M72: 0795148192 | N72: B-Arcade Mall, Kilimani, Argwings Kodhek Road, Nairobi, Kenya | O72: 13.0 | P72: 6.4 | Q72: 0 | R72: MOTORCYCLE | S72: Pick- Ups | T72: false | U72: true | V72: Nov 5, 2025, 2:24:49 PM | X72: 189.7
A73: westlands-copy-2 | B73: +2540707098612 | C73: Benard Ogada | D73: Kilimani NRB | E73: COMPLETED | F73: 1:57PICKUP | G73: =IF(K73="Pick-up","PICKUPS",IF(K73="Staff drop-off","STAFF_DROPOFF",IF(K73="Replacements","REPLACEMENT",IF(K73="Central Stores Dispatch","CENTRAL STORES DISPATCH",IFNA(IFNA(VLOOKUP(F73,'Raw Platform Nov 4-6 2025'!C:C,1,FALSE),VLOOKUP(F73,'Raw Platform Nov 4-6 2025'!D:D,1,FALSE)),IFNA(VLOOKUP(F73,'Glovo Raw Nov 4-6 2025'!B:B,1,FALSE),"Not Matched")))))) | H73: =COUNTIF(F:F,F73) | I73: Nov 5, 2025, 1:57:34 PM | J73: Pick-up | K73: PAID | L73: KILIMANI | M73: 0769304599 | N73: Purvi House, Nairobi, Kenya | O73: 16.0 | P73: 7.1 | Q73: 0 | R73: MOTORCYCLE | S73: ANDO Kitchens | T73: false | U73: true | V73: Nov 5, 2025, 1:58:11 PM | X73: 205.8
A74: westlands | B74: +2540707098612 | C74: Benard Ogada | D74: Westlands NRB | E74: COMPLETED | F74: 11E9A | G74: =IF(K74="Pick-up","PICKUPS",IF(K74="Staff drop-off","STAFF_DROPOFF",IF(K74="Replacements","REPLACEMENT",IF(K74="Central Stores Dispatch","CENTRAL STORES DISPATCH",IFNA(IFNA(VLOOKUP(F74,'Raw Platform Nov 4-6 2025'!C:C,1,FALSE),VLOOKUP(F74,'Raw Platform Nov 4-6 2025'!D:D,1,FALSE)),IFNA(VLOOKUP(F74,'Glovo Raw Nov 4-6 2025'!B:B,1,FALSE),"Not Matched")))))) | H74: =COUNTIF(F:F,F74) | I74: Nov 5, 2025, 1:05:00 PM | J74: Uber Eats | K74: PAID | L74: DAMARIS | M74: 0790430137 | N74: Malakal Court, Westlands Avenue, Nairobi, Kenya | O74: 4.0 | P74: 1.5 | Q74: 0 | R74: MOTORCYCLE | S74: Marty's Famous Burgers | T74: false | U74: true | V74: Nov 5, 2025, 1:25:34 PM | X74: 100
... A184: nsk-copy | B184: +254790564971 | C184: Chrispine Omondi | D184: NSK NRB | E184: COMPLETED | F184: PICKUPCHEESE345776 | G184: =IF(K184="Pick-up","PICKUPS",IF(K184="Staff drop-off","STAFF_DROPOFF",IF(K184="Replacements","REPLACEMENT",IF(K184="Central Stores Dispatch","CENTRAL STORES DISPATCH",IFNA(IFNA(VLOOKUP(F184,'Raw Platform Nov 4-6 2025'!C:C,1,FALSE),VLOOKUP(F184,'Raw Platform Nov 4-6 2025'!D:D,1,FALSE)),IFNA(VLOOKUP(F184,'Glovo Raw Nov 4-6 2025'!B:B,1,FALSE),"Not Matched")))))) | H184: =COUNTIF(F:F,F184) | I184: Nov 4, 2025, 3:01:21 PM | J184: Pick-up | K184: PAID | L184: L.ITALY | M184: 0115133474 | N184: B-Arcade Mall, Kilimani, Argwings Kodhek Road, Nairobi, Kenya | O184: 14.0 | P184: 6.5 | Q184: 0 | R184: CAR | S184: Little Italy | T184: false | U184: true | V184: Nov 4, 2025, 3:02:52 PM | X184: 192
A185: steady-pizza-chicken-house | B185: +250783568521 | C185: Cyprien Nsengiyaremye | E185: COMPLETED | F185: 139579 | G185: =IF(K185="Pick-up","PICKUPS",IF(K185="Staff drop-off","STAFF_DROPOFF",IF(K185="Replacements","REPLACEMENT",IF(K185="Central Stores Dispatch","CENTRAL STORES DISPATCH",IFNA(IFNA(VLOOKUP(F185,'Raw Platform Nov 4-6 2025'!C:C,1,FALSE),VLOOKUP(F185,'Raw Platform Nov 4-6 2025'!D:D,1,FALSE)),IFNA(VLOOKUP(F185,'Glovo Raw Nov 4-6 2025'!B:B,1,FALSE),"Not Matched")))))) | H185: =COUNTIF(F:F,F185) | I185: Nov 4, 2025, 7:22:00 PM | J185: Ando App | K185: UNPAID | L185: stella kaniaru | M185: +250791591916 | N185: Biryogo Car Free Zone, Macoco restaurant | O185: 21.0 | P185: 10.6 | Q185: 1500 | R185: BICYCLE | T185: false | U185: true | V185: Nov 4, 2025, 8:18:26 PM | X185: 2000
A186: pad-thai-restaurant | B186: +250783568521 | C186: Cyprien Nsengiyaremye | E186: REJECTED | F186: 138783 | G186: =IF(K186="Pick-up","PICKUPS",IF(K186="Staff drop-off","STAFF_DROPOFF",IF(K186="Replacements","REPLACEMENT",IF(K186="Central Stores Dispatch","CENTRAL STORES DISPATCH",IFNA(IFNA(VLOOKUP(F186,'Raw Platform Nov 4-6 2025'!C:C,1,FALSE),VLOOKUP(F186,'Raw Platform Nov 4-6 2025'!D:D,1,FALSE)),IFNA(VLOOKUP(F186,'Glovo Raw Nov 4-6 2025'!B:B,1,FALSE),"Not Matched")))))) | H186: =COUNTIF(F:F,F186) | I186: Nov 4, 2025, 7:11:58 PM | J186: Ando App | K186: UNPAID | L186: MAHORO Geofrey | M186: +250795019129 | N186: Kigali | O186: 20.0 | P186: 10.0 | Q186: 15000 | R186: BICYCLE | T186: false | U186: false | V186: Nov 4, 2025, 8:14:19 PM | X186: 0
A187: westlands-copy-2 | B187: +254748392704 | C187: Daniel Namaswa | D187: Kilimani NRB | E187: COMPLETED | F187: 101477514113 | G187: =IF(K187="Pick-up","PICKUPS",IF(K187="Staff drop-off","STAFF_DROPOFF",IF(K187="Replacements","REPLACEMENT",IF(K187="Central Stores Dispatch","CENTRAL STORES DISPATCH",IFNA(IFNA(VLOOKUP(F187,'Raw Platform Nov 4-6 2025'!C:C,1,FALSE),VLOOKUP(F187,'Raw Platform Nov 4-6 2025'!D:D,1,FALSE)),IFNA(VLOOKUP(F187,'Glovo Raw Nov 4-6 2025'!B:B,1,FALSE),"Not Matched")))))) | H187: =COUNTIF(F:F,F187) | I187: Nov 6, 2025, 8:16:04 PM | J187: Glovo | K187: PAID | L187: TIFFANY | M187: 0706282867 | N187: Dolphine studio apartments, Kahuho, Nairobi, Kenya | O187: 26.0 | P187: 9.0 | Q187: 0 | R187: MOTORCYCLE | S187: Marty's Famous Burgers | T187: false | U187: true | V187: Nov 6, 2025, 8:37:40 PM | X187: 249.5
A188: westlands-copy-2 | B188: +254748392704 | C188: Daniel Namaswa | D188: Kilimani NRB | E188: COMPLETED | F188: CC8AF | G188: =IF(K188="Pick-up","PICKUPS",IF(K188="Staff drop-off","STAFF_DROPOFF",IF(K188="Replacements","REPLACEMENT",IF(K188="Central Stores Dispatch","CENTRAL STORES DISPATCH",IFNA(IFNA(VLOOKUP(F188,'Raw Platform Nov 4-6 2025'!C:C,1,FALSE),VLOOKUP(F188,'Raw Platform Nov 4-6 2025'!D:D,1,FALSE)),IFNA(VLOOKUP(F188,'Glovo Raw Nov 4-6 2025'!B:B,1,FALSE),"Not Matched")))))) | H188: =COUNTIF(F:F,F188) | I188: Nov 6, 2025, 6:56:35 PM | J188: Uber Eats | K188: PAID | L188: CALVIN M. | M188: 0722165694 | N188: Racecourse Gardens Apartments, Mama Wahu Road, Nairobi, Kenya | O188: 16.0 | P188: 6.7 | Q188: 0 | R188: MOTORCYCLE | S188: ANDO Kitchens | T188: false | U188: true | V188: Nov 6, 2025, 7:39:19 PM | X188: 196.6
A189: westlands-copy-2 | B189: +254748392704 | C189: Daniel Namaswa | D189: AURO | E189: COMPLETED | F189: 5A454 | G189: =IF(K189="Pick-up","PICKUPS",IF(K189="Staff drop-off","STAFF_DROPOFF",IF(K189="Replacements","REPLACEMENT",IF(K189="Central Stores Dispatch","CENTRAL STORES DISPATCH",IFNA(IFNA(VLOOKUP(F189,'Raw Platform Nov 4-6 2025'!C:C,1,FALSE),VLOOKUP(F189,'Raw Platform Nov 4-6 2025'!D:D,1,FALSE)),IFNA(VLOOKUP(F189,'Glovo Raw Nov 4-6 2025'!B:B,1,FALSE),"Not Matched")))))) | H189: =COUNTIF(F:F,F189) | I189: Nov 6, 2025, 5:53:26 PM | J189: Uber Eats | K189: PAID | L189: SHAN W. | M189: 0111627411 | N189: The Soho Serviced Apartments, Kirichwa Road, Nairobi, Kenya | O189: 5.0 | P189: 1.2 | Q189: 0 | R189: MOTORCYCLE | S189: KAI The Sushi Bar | T189: false | U189: true | V189: Nov 6, 2025, 6:30:29 PM | X189: 100
A190: westlands-copy-2 | B190: +254748392704 | C190: Daniel Namaswa | D190: Kilimani NRB | E190: COMPLETED | F190: 4788.0 | G190: =IF(K190="Pick-up","PICKUPS",IF(K190="Staff drop-off","STAFF_DROPOFF",IF(K190="Replacements","REPLACEMENT",IF(K190="Central Stores Dispatch","CENTRAL STORES DISPATCH",IFNA(IFNA(VLOOKUP(F190,'Raw Platform Nov 4-6 2025'!C:C,1,FALSE),VLOOKUP(F190,'Raw Platform Nov 4-6 2025'!D:D,1,FALSE)),IFNA(VLOOKUP(F190,'Glovo Raw Nov 4-6 2025'!B:B,1,FALSE),"Not Matched")))))) | H190: =COUNTIF(F:F,F190) | I190: Nov 6, 2025, 5:00:05 PM | J190: Uber Eats | K190: PAID | L190: KARL | M190: 0792358430 | N190: Mugumo Village, Nairobi, Kenya | O190: 9.0 | P190: 3.3 | Q190: 0 | R190: MOTORCYCLE | S190: Marty's Famous Burgers | T190: false | U190: true | V190: Nov 6, 2025, 5:01:33 PM | X190: 118.4
A191: westlands-copy-2 | B191: +254748392704 | C191: Daniel Namaswa | D191: Kilimani NRB | E191: COMPLETED | F191: DD3B3 | G191: =IF(K191="Pick-up","PICKUPS",IF(K191="Staff drop-off","STAFF_DROPOFF",IF(K191="Replacements","REPLACEMENT",IF(K191="Central Stores Dispatch","CENTRAL STORES DISPATCH",IFNA(IFNA(VLOOKUP(F191,'Raw Platform Nov 4-6 2025'!C:C,1,FALSE),VLOOKUP(F191,'Raw Platform Nov 4-6 2025'!D:D,1,FALSE)),IFNA(VLOOKUP(F191,'Glovo Raw Nov 4-6 2025'!B:B,1,FALSE),"Not Matched")))))) | H191: =COUNTIF(F:F,F191) | I191: Nov 6, 2025, 2:55:47 PM | J191: Uber Eats | K191: PAID | L191: JERMAINE C. | M191: 0796743688 | N191: GATUNDU HEIGHTS, Gatundu Road, Nairobi, Kenya | O191: 8.0 | P191: 2.6 | Q191: 0 | R191: MOTORCYCLE | S191: Little Italy | T191: false | U191: true | V191: Nov 6, 2025, 3:30:07 PM | X191: 102.3
A192: westlands-copy-2 | B192: +254748392704 | C192: Daniel Namaswa | D192: Kilimani NRB | E192: COMPLETED | F192: 58705 | G192: =IF(K192="Pick-up","PICKUPS",IF(K192="Staff drop-off","STAFF_DROPOFF",IF(K192="Replacements","REPLACEMENT",IF(K192="Central Stores Dispatch","CENTRAL STORES DISPATCH",IFNA(IFNA(VLOOKUP(F192,'Raw Platform Nov 4-6 2025'!C:C,1,FALSE),VLOOKUP(F192,'Raw Platform Nov 4-6 2025'!D:D,1,FALSE)),IFNA(VLOOKUP(F192,'Glovo Raw Nov 4-6 2025'!B:B,1,FALSE),"Not Matched")))))) | H192: =COUNTIF(F:F,F192) | I192: Nov 6, 2025, 1:52:16 PM | J192: Uber Eats | K192: PAID | L192: JOSEPH M. | M192: 0700545574 | N192: McKinsey & Company Inc, Mzima Springs Lane, Nairobi, Kenya | O192: 10.0 | P192: 4.2 | Q192: 0 | R192: MOTORCYCLE | S192: Siam - Thai Kitchen | T192: false | U192: true | V192: Nov 6, 2025, 2:06:54 PM | X192: 139.1
A193: westlands-copy-2 | B193: +254748392704 | C193: Daniel Namaswa | D193: Kilimani NRB | E193: COMPLETED | F193: 62305.0 | G193: =IF(K193="Pick-up","PICKUPS",IF(K193="Staff drop-off","STAFF_DROPOFF",IF(K193="Replacements","REPLACEMENT",IF(K193="Central Stores Dispatch","CENTRAL STORES DISPATCH",IFNA(IFNA(VLOOKUP(F193,'Raw Platform Nov 4-6 2025'!C:C,1,FALSE),VLOOKUP(F193,'Raw Platform Nov 4-6 2025'!D:D,1,FALSE)),IFNA(VLOOKUP(F193,'Glovo Raw Nov 4-6 2025'!B:B,1,FALSE),"Not Matched")))))) | H193: =COUNTIF(F:F,F193) | I193: Nov 6, 2025, 12:40:27 PM | J193: Uber Eats | K193: PAID | L193: ANN H | M193: 0718978238 | N193: Britam Tower, Nairobi, Kenya | O193: 10.0 | P193: 3.7 | Q193: 0 | R193: MOTORCYCLE | S193: Little Italy | T193: false | U193: true | V193: Nov 6, 2025, 1:05:24 PM | X193: 127.6
A194: westlands-copy-2 | B194: +254748392704 | C194: Daniel Namaswa | D194: Kilimani NRB | E194: COMPLETED | F194: E2FF3 | G194: =IF(K194="Pick-up","PICKUPS",IF(K194="Staff drop-off","STAFF_DROPOFF",IF(K194="Replacements","REPLACEMENT",IF(K194="Central Stores Dispatch","CENTRAL STORES DISPATCH",IFNA(IFNA(VLOOKUP(F194,'Raw Platform Nov 4-6 2025'!C:C,1,FALSE),VLOOKUP(F194,'Raw Platform Nov 4-6 2025'!D:D,1,FALSE)),IFNA(VLOOKUP(F194,'Glovo Raw Nov 4-6 2025'!B:B,1,FALSE),"Not Matched")))))) | H194: =COUNTIF(F:F,F194) | I194: Nov 6, 2025, 11:54:24 AM | J194: Uber Eats | K194: PAID | L194: RON S | M194: 0769304599 | N194: Mzima House, Nairobi, Kenya | O194: 10.0 | P194: 4.2 | Q194: 0 | R194: MOTORCYCLE | S194: Marty's Famous Burgers | T194: false | U194: true | V194: Nov 6, 2025, 12:12:08 PM | X194: 139.1
A195: westlands-copy-2 | B195: +254748392704 | C195: Daniel Namaswa | D195: Kilimani NRB | E195: COMPLETED | F195: D6AB3 | G195: =IF(K195="Pick-up","PICKUPS",IF(K195="Staff drop-off","STAFF_DROPOFF",IF(K195="Replacements","REPLACEMENT",IF(K195="Central Stores Dispatch","CENTRAL STORES DISPATCH",IFNA(IFNA(VLOOKUP(F195,'Raw Platform Nov 4-6 2025'!C:C,1,FALSE),VLOOKUP(F195,'Raw Platform Nov 4-6 2025'!D:D,1,FALSE)),IFNA(VLOOKUP(F195,'Glovo Raw Nov 4-6 2025'!B:B,1,FALSE),"Not Matched")))))) | H195: =COUNTIF(F:F,F195) | I195: Nov 5, 2025, 7:00:28 PM | J195: Uber Eats | K195: UNPAID | L195: SALLY M. | M195: 0757171825 | N195: Added Value Properties Yellow Birch Apartment, Nairobi, Kenya | O195: 21.0 | P195: 10.3 | Q195: 3518 | R195: MOTORCYCLE | S195: Little Italy | T195: false | U195: true | V195: Nov 5, 2025, 7:13:22 PM | X195: 279.4
A196: westlands-copy-2 | B196: +254748392704 | C196: Daniel Namaswa | D196: Kilimani NRB | E196: COMPLETED | F196: 5F028 | G196: =IF(K196="Pick-up","PICKUPS",IF(K196="Staff drop-off","STAFF_DROPOFF",IF(K196="Replacements","REPLACEMENT",IF(K196="Central Stores Dispatch","CENTRAL STORES DISPATCH",IFNA(IFNA(VLOOKUP(F196,'Raw Platform Nov 4-6 2025'!C:C,1,FALSE),VLOOKUP(F196,'Raw Platform Nov 4-6 2025'!D:D,1,FALSE)),IFNA(VLOOKUP(F196,'Glovo Raw Nov 4-6 2025'!B:B,1,FALSE),"Not Matched")))))) | H196: =COUNTIF(F:F,F196) | I196: Nov 5, 2025, 6:54:13 PM | J196: Uber Eats | K196: PAID | L196: JONATHAN B. | M196: 0769304599 | N196: Elsie Ridge, Lower Kabete Lane, Nairobi, Kenya | O196: 20.0 | P196: 11.3 | Q196: 0 | R196: MOTORCYCLE | S196: Bibi's Swahili Kitchen | T196: false | U196: true | V196: Nov 5, 2025, 7:10:59 PM | X196: 302.4
A197: westlands-copy-2 | B197: +254748392704 | C197: Daniel Namaswa | D197: Kilimani NRB | E197: COMPLETED | F197: 3C369 | G197: =IF(K197="Pick-up","PICKUPS",IF(K197="Staff drop-off","STAFF_DROPOFF",IF(K197="Replacements","REPLACEMENT",IF(K197="Central Stores Dispatch","CENTRAL STORES DISPATCH",IFNA(IFNA(VLOOKUP(F197,'Raw Platform Nov 4-6 2025'!C:C,1,FALSE),VLOOKUP(F197,'Raw Platform Nov 4-6 2025'!D:D,1,FALSE)),IFNA(VLOOKUP(F197,'Glovo Raw Nov 4-6 2025'!B:B,1,FALSE),"Not Matched")))))) | H197: =COUNTIF(F:F,F197) | I197: Nov 5, 2025, 6:10:33 PM | J197: Uber Eats | K197: PAID | L197: DENNIS M. | M197: 0723846070 | N197: Bristow Apartments, Gitanga Road, Nairobi, Kenya | O197: 12.0 | P197: 3.8 | Q197: 0 | R197: MOTORCYCLE | S197: ANDO Kitchens | T197: false | U197: true | V197: Nov 5, 2025, 6:20:21 PM | X197: 129.9
A198: westlands-copy-2 | B198: +254748392704 | C198: Daniel Namaswa | D198: Kilimani NRB | E198: COMPLETED | F198: 0139D | G198: =IF(K198="Pick-up","PICKUPS",IF(K198="Staff drop-off","STAFF_DROPOFF",IF(K198="Replacements","REPLACEMENT",IF(K198="Central Stores Dispatch","CENTRAL STORES DISPATCH",IFNA(IFNA(VLOOKUP(F198,'Raw Platform Nov 4-6 2025'!C:C,1,FALSE),VLOOKUP(F198,'Raw Platform Nov 4-6 2025'!D:D,1,FALSE)),IFNA(VLOOKUP(F198,'Glovo Raw Nov 4-6 2025'!B:B,1,FALSE),"Not Matched")))))) | H198: =COUNTIF(F:F,F198) | I198: Nov 5, 2025, 4:40:45 PM | J198: Uber Eats | K198: PAID | L198: PETER K. | M198: 0708086123 | N198: Riana Woods Apartments - Kilimani, Maalim Juma Road, Nairobi, Kenya | O198: 6.0 | P198: 1.5 | Q198: 0 | R198: MOTORCYCLE | S198: Little Italy | T198: false | U198: true | V198: Nov 5, 2025, 5:09:02 PM | X198: 100
... A724: purvi-auro | B724: +254720770213 | C724: Joseph Okado | D724: AURO | E724: COMPLETED | F724: 4BC24 | G724: =IF(K724="Pick-up","PICKUPS",IF(K724="Staff drop-off","STAFF_DROPOFF",IF(K724="Replacements","REPLACEMENT",IF(K724="Central Stores Dispatch","CENTRAL STORES DISPATCH",IFNA(IFNA(VLOOKUP(F724,'Raw Platform Nov 4-6 2025'!C:C,1,FALSE),VLOOKUP(F724,'Raw Platform Nov 4-6 2025'!D:D,1,FALSE)),IFNA(VLOOKUP(F724,'Glovo Raw Nov 4-6 2025'!B:B,1,FALSE),"Not Matched")))))) | H724: =COUNTIF(F:F,F724) | I724: Nov 4, 2025, 3:26:24 PM | J724: Uber Eats | K724: UNPAID | L724: Andy R | M724: 0787528151 | N724: Garden City Mall, Thika Road, Nairobi, Kenya | O724: 18.0 | P724: 11.6 | Q724: 780 | R724: MOTORCYCLE | S724: Tandoori Patio | T724: true | U724: true | V724: Nov 4, 2025, 3:27:58 PM | X724: 489
A725: purvi-auro | B725: +254720770213 | C725: Joseph Okado | E725: COMPLETED | F725: #139535 | G725: =IF(K725="Pick-up","PICKUPS",IF(K725="Staff drop-off","STAFF_DROPOFF",IF(K725="Replacements","REPLACEMENT",IF(K725="Central Stores Dispatch","CENTRAL STORES DISPATCH",IFNA(IFNA(VLOOKUP(F725,'Raw Platform Nov 4-6 2025'!C:C,1,FALSE),VLOOKUP(F725,'Raw Platform Nov 4-6 2025'!D:D,1,FALSE)),IFNA(VLOOKUP(F725,'Glovo Raw Nov 4-6 2025'!B:B,1,FALSE),"Not Matched")))))) | H725: =COUNTIF(F:F,F725) | I725: Nov 4, 2025, 2:14:29 PM | J725: Ando App | K725: PAID | L725: Vineet N. | M725: 0758407982 | N725: Woodvale Grove, Nairobi, Kenya | O725: 2.0 | P725: 0.3 | Q725: 0 | R725: MOTORCYCLE | T725: false | U725: true | V725: Nov 4, 2025, 3:19:30 PM | X725: 100
A726: purvi-auro | B726: +254720770213 | C726: Joseph Okado | E726: COMPLETED | F726: 139536 | G726: =IF(K726="Pick-up","PICKUPS",IF(K726="Staff drop-off","STAFF_DROPOFF",IF(K726="Replacements","REPLACEMENT",IF(K726="Central Stores Dispatch","CENTRAL STORES DISPATCH",IFNA(IFNA(VLOOKUP(F726,'Raw Platform Nov 4-6 2025'!C:C,1,FALSE),VLOOKUP(F726,'Raw Platform Nov 4-6 2025'!D:D,1,FALSE)),IFNA(VLOOKUP(F726,'Glovo Raw Nov 4-6 2025'!B:B,1,FALSE),"Not Matched")))))) | H726: =COUNTIF(F:F,F726) | I726: Nov 4, 2025, 1:35:00 PM | J726: Ando App | K726: UNPAID | L726: Vineet | M726: +254758407982 | N726: Purvi House | O726: 1.0 | P726: 0.2 | Q726: 1712 | R726: MOTORCYCLE | T726: false | U726: true | V726: Nov 4, 2025, 3:21:02 PM | X726: 100
A727: westlands-copy-2 | B727: +254720770213 | C727: Joseph Okado | D727: AURO | E727: COMPLETED | F727: 556FE | G727: =IF(K727="Pick-up","PICKUPS",IF(K727="Staff drop-off","STAFF_DROPOFF",IF(K727="Replacements","REPLACEMENT",IF(K727="Central Stores Dispatch","CENTRAL STORES DISPATCH",IFNA(IFNA(VLOOKUP(F727,'Raw Platform Nov 4-6 2025'!C:C,1,FALSE),VLOOKUP(F727,'Raw Platform Nov 4-6 2025'!D:D,1,FALSE)),IFNA(VLOOKUP(F727,'Glovo Raw Nov 4-6 2025'!B:B,1,FALSE),"Not Matched")))))) | H727: =COUNTIF(F:F,F727) | I727: Nov 4, 2025, 12:45:16 PM | J727: Uber Eats | K727: PAID | L727: Antant | M727: +015104329299 | N727: Riverbank Apartments at Two Rivers, Two Rivers, Nairobi, Kenya | O727: 31.0 | P727: 16.2 | Q727: 0 | R727: MOTORCYCLE | S727: TastiWok | T727: false | U727: true | V727: Nov 4, 2025, 1:14:34 PM | X727: 415.1
A728: westlands-copy-2 | B728: +254720770213 | C728: Joseph Okado | D728: AURO | E728: REJECTED | F728: 556FE | G728: =IF(K728="Pick-up","PICKUPS",IF(K728="Staff drop-off","STAFF_DROPOFF",IF(K728="Replacements","REPLACEMENT",IF(K728="Central Stores Dispatch","CENTRAL STORES DISPATCH",IFNA(IFNA(VLOOKUP(F728,'Raw Platform Nov 4-6 2025'!C:C,1,FALSE),VLOOKUP(F728,'Raw Platform Nov 4-6 2025'!D:D,1,FALSE)),IFNA(VLOOKUP(F728,'Glovo Raw Nov 4-6 2025'!B:B,1,FALSE),"Not Matched")))))) | H728: =COUNTIF(F:F,F728) | I728: Nov 4, 2025, 12:45:16 PM | J728: Uber Eats | K728: PAID | L728: Antant | M728: +015104329299 | N728: Riverbank Apartments at Two Rivers, Two Rivers, Nairobi, Kenya | O728: 31.0 | P728: 16.2 | Q728: 0 | R728: MOTORCYCLE | S728: TastiWok | T728: false | U728: false | V728: Nov 4, 2025, 12:46:25 PM | X728: 0
A729: westlands | B729: +254720770213 | C729: Joseph Okado | D729: AURO | E729: COMPLETED | F729: pickupAntant | G729: =IF(K729="Pick-up","PICKUPS",IF(K729="Staff drop-off","STAFF_DROPOFF",IF(K729="Replacements","REPLACEMENT",IF(K729="Central Stores Dispatch","CENTRAL STORES DISPATCH",IFNA(IFNA(VLOOKUP(F729,'Raw Platform Nov 4-6 2025'!C:C,1,FALSE),VLOOKUP(F729,'Raw Platform Nov 4-6 2025'!D:D,1,FALSE)),IFNA(VLOOKUP(F729,'Glovo Raw Nov 4-6 2025'!B:B,1,FALSE),"Not Matched")))))) | H729: =COUNTIF(F:F,F729) | I729: Nov 4, 2025, 12:44:19 PM | J729: Uber Eats | K729: PAID | L729: Antant | M729: 0797777711 | N729: Rose Avenue Shopping Centre, Kindaruma Road, Nairobi, Kenya | O729: 13.0 | P729: 6.2 | Q729: 0 | R729: MOTORCYCLE | S729: TastiWok | T729: false | U729: true | V729: Nov 4, 2025, 12:45:12 PM | X729: 185.1
A730: westlands-copy-2 | B730: +254745423824 | C730: Joseph Karimi | D730: Kilimani NRB | E730: COMPLETED | F730: 2F699 | G730: =IF(K730="Pick-up","PICKUPS",IF(K730="Staff drop-off","STAFF_DROPOFF",IF(K730="Replacements","REPLACEMENT",IF(K730="Central Stores Dispatch","CENTRAL STORES DISPATCH",IFNA(IFNA(VLOOKUP(F730,'Raw Platform Nov 4-6 2025'!C:C,1,FALSE),VLOOKUP(F730,'Raw Platform Nov 4-6 2025'!D:D,1,FALSE)),IFNA(VLOOKUP(F730,'Glovo Raw Nov 4-6 2025'!B:B,1,FALSE),"Not Matched")))))) | H730: =COUNTIF(F:F,F730) | I730: Nov 5, 2025, 4:30:21 PM | J730: Uber Eats | K730: PAID | L730: WISLAY K. | M730: 0706891843 | N730: Pinetree Plaza Kaburu Drive, Kamburu Drive, Nairobi, Kenya | O730: 6.0 | P730: 1.6 | Q730: 0 | R730: MOTORCYCLE | S730: ANDO Kitchens | T730: false | U730: true | V730: Nov 5, 2025, 4:44:43 PM | X730: 100
A731: westlands-copy-2 | B731: +254745423824 | C731: Joseph Karimi | D731: Kilimani NRB | E731: COMPLETED | F731: PICKUP,SPANISH,PARPRIKA. | G731: =IF(K731="Pick-up","PICKUPS",IF(K731="Staff drop-off","STAFF_DROPOFF",IF(K731="Replacements","REPLACEMENT",IF(K731="Central Stores Dispatch","CENTRAL STORES DISPATCH",IFNA(IFNA(VLOOKUP(F731,'Raw Platform Nov 4-6 2025'!C:C,1,FALSE),VLOOKUP(F731,'Raw Platform Nov 4-6 2025'!D:D,1,FALSE)),IFNA(VLOOKUP(F731,'Glovo Raw Nov 4-6 2025'!B:B,1,FALSE),"Not Matched")))))) | H731: =COUNTIF(F:F,F731) | I731: Nov 5, 2025, 3:01:39 PM | J731: Pick-up | K731: PAID | L731: KILIMANI | M731: 0769304599 | N731: Nairobi Street Kitchen, Mpaka Road, Nairobi, Kenya | O731: 16.0 | P731: 7.1 | Q731: 0 | R731: MOTORCYCLE | S731: Pick- Ups | T731: false | U731: true | V731: Nov 5, 2025, 3:03:22 PM | X731: 205.8
A732: westlands-copy-2 | B732: +254745423824 | C732: Joseph Karimi | D732: Kilimani NRB | E732: COMPLETED | F732: 85258 | G732: =IF(K732="Pick-up","PICKUPS",IF(K732="Staff drop-off","STAFF_DROPOFF",IF(K732="Replacements","REPLACEMENT",IF(K732="Central Stores Dispatch","CENTRAL STORES DISPATCH",IFNA(IFNA(VLOOKUP(F732,'Raw Platform Nov 4-6 2025'!C:C,1,FALSE),VLOOKUP(F732,'Raw Platform Nov 4-6 2025'!D:D,1,FALSE)),IFNA(VLOOKUP(F732,'Glovo Raw Nov 4-6 2025'!B:B,1,FALSE),"Not Matched")))))) | H732: =COUNTIF(F:F,F732) | I732: Nov 5, 2025, 2:50:32 PM | J732: Uber Eats | K732: PAID | L732: NICOLA B. | M732: 0728567442 | N732: Faddville Estate, Oloitokitok Road, Likoni Lane, Nairobi, Kenya | O732: 6.0 | P732: 1.7 | Q732: 0 | R732: MOTORCYCLE | S732: Bibi's Swahili Kitchen | T732: false | U732: true | V732: Nov 5, 2025, 3:12:37 PM | X732: 100
A733: westlands-copy-2 | B733: +254745423824 | C733: Joseph Karimi | D733: Kilimani NRB | E733: COMPLETED | F733: D04A3 | G733: =IF(K733="Pick-up","PICKUPS",IF(K733="Staff drop-off","STAFF_DROPOFF",IF(K733="Replacements","REPLACEMENT",IF(K733="Central Stores Dispatch","CENTRAL STORES DISPATCH",IFNA(IFNA(VLOOKUP(F733,'Raw Platform Nov 4-6 2025'!C:C,1,FALSE),VLOOKUP(F733,'Raw Platform Nov 4-6 2025'!D:D,1,FALSE)),IFNA(VLOOKUP(F733,'Glovo Raw Nov 4-6 2025'!B:B,1,FALSE),"Not Matched")))))) | H733: =COUNTIF(F:F,F733) | I733: Nov 5, 2025, 1:14:24 PM | J733: Uber Eats | K733: UNPAID | L733: AUGUSTE N. | M733: 0769304599 | N733: Riara One Residency, Riara Road, Nairobi, Kenya | O733: 11.0 | P733: 3.6 | Q733: 962 | R733: MOTORCYCLE | S733: Bibi's Swahili Kitchen | T733: false | U733: true | V733: Nov 5, 2025, 1:31:58 PM | X733: 125.3
A734: westlands-copy-2 | B734: +254745423824 | C734: Joseph Karimi | D734: Kilimani NRB | E734: COMPLETED | F734: 440C7 | G734: =IF(K734="Pick-up","PICKUPS",IF(K734="Staff drop-off","STAFF_DROPOFF",IF(K734="Replacements","REPLACEMENT",IF(K734="Central Stores Dispatch","CENTRAL STORES DISPATCH",IFNA(IFNA(VLOOKUP(F734,'Raw Platform Nov 4-6 2025'!C:C,1,FALSE),VLOOKUP(F734,'Raw Platform Nov 4-6 2025'!D:D,1,FALSE)),IFNA(VLOOKUP(F734,'Glovo Raw Nov 4-6 2025'!B:B,1,FALSE),"Not Matched")))))) | H734: =COUNTIF(F:F,F734) | I734: Nov 5, 2025, 11:48:06 AM | J734: Uber Eats | K734: PAID | L734: FREDDIE T. | M734: 0769304599 | N734: The Address, Muthangari Drive, Nairobi, Kenya | O734: 15.0 | P734: 6.2 | Q734: 0 | R734: MOTORCYCLE | S734: Siam - Thai Kitchen | T734: false | U734: true | V734: Nov 5, 2025, 12:04:39 PM | X734: 185.1
A735: nsk-copy | B735: +254745423824 | C735: Joseph Karimi | D735: NSK NRB | E735: COMPLETED | F735: 12D32 | G735: =IF(K735="Pick-up","PICKUPS",IF(K735="Staff drop-off","STAFF_DROPOFF",IF(K735="Replacements","REPLACEMENT",IF(K735="Central Stores Dispatch","CENTRAL STORES DISPATCH",IFNA(IFNA(VLOOKUP(F735,'Raw Platform Nov 4-6 2025'!C:C,1,FALSE),VLOOKUP(F735,'Raw Platform Nov 4-6 2025'!D:D,1,FALSE)),IFNA(VLOOKUP(F735,'Glovo Raw Nov 4-6 2025'!B:B,1,FALSE),"Not Matched")))))) | H735: =COUNTIF(F:F,F735) | I735: Nov 4, 2025, 8:14:32 PM | J735: Uber Eats | K735: PAID | L735: KWESI C | M735: +017707133649 | N735: Sandalwood garden, Argwings kodhek road, Argwings Kodhek Road, Nairobi, Kenya | O735: 12.0 | P735: 6.0 | Q735: 0 | R735: MOTORCYCLE | S735: Little Italy | T735: false | U735: true | V735: Nov 4, 2025, 8:15:41 PM | X735: 180.5
A736: westlands-copy-2 | B736: +254745423824 | C736: Joseph Karimi | D736: Kilimani NRB | E736: COMPLETED | F736: AFD96 | G736: =IF(K736="Pick-up","PICKUPS",IF(K736="Staff drop-off","STAFF_DROPOFF",IF(K736="Replacements","REPLACEMENT",IF(K736="Central Stores Dispatch","CENTRAL STORES DISPATCH",IFNA(IFNA(VLOOKUP(F736,'Raw Platform Nov 4-6 2025'!C:C,1,FALSE),VLOOKUP(F736,'Raw Platform Nov 4-6 2025'!D:D,1,FALSE)),IFNA(VLOOKUP(F736,'Glovo Raw Nov 4-6 2025'!B:B,1,FALSE),"Not Matched")))))) | H736: =COUNTIF(F:F,F736) | I736: Nov 4, 2025, 8:09:55 PM | J736: Uber Eats | K736: PAID | L736: ABD EL RAOUF H. | M736: 0769304599 | N736: Hyatt House Nairobi Westlands, Lower Kabete Road, Nairobi, Kenya | O736: 17.0 | P736: 6.0 | Q736: 0 | R736: MOTORCYCLE | S736: Little Italy | T736: false | U736: true | V736: Nov 4, 2025, 8:45:03 PM | X736: 180.5
A737: westlands-copy-2 | B737: +254745423824 | C737: Joseph Karimi | D737: Kilimani NRB | E737: COMPLETED | F737: F7018 | G737: =IF(K737="Pick-up","PICKUPS",IF(K737="Staff drop-off","STAFF_DROPOFF",IF(K737="Replacements","REPLACEMENT",IF(K737="Central Stores Dispatch","CENTRAL STORES DISPATCH",IFNA(IFNA(VLOOKUP(F737,'Raw Platform Nov 4-6 2025'!C:C,1,FALSE),VLOOKUP(F737,'Raw Platform Nov 4-6 2025'!D:D,1,FALSE)),IFNA(VLOOKUP(F737,'Glovo Raw Nov 4-6 2025'!B:B,1,FALSE),"Not Matched")))))) | H737: =COUNTIF(F:F,F737) | I737: Nov 4, 2025, 6:57:03 PM | J737: Uber Eats | K737: PAID | L737: JONATHAN B. | M737: 0769304599 | N737: Elsie Ridge, Lower Kabete Lane, Nairobi, Kenya | O737: 20.0 | P737: 11.3 | Q737: 0 | R737: MOTORCYCLE | S737: Bibi's Swahili Kitchen | T737: false | U737: true | V737: Nov 4, 2025, 7:12:03 PM | X737: 302.4
A738: westlands-copy-2 | B738: +254745423824 | C738: Joseph Karimi | D738: Kilimani NRB | E738: COMPLETED | F738: 9C361 | G738: =IF(K738="Pick-up","PICKUPS",IF(K738="Staff drop-off","STAFF_DROPOFF",IF(K738="Replacements","REPLACEMENT",IF(K738="Central Stores Dispatch","CENTRAL STORES DISPATCH",IFNA(IFNA(VLOOKUP(F738,'Raw Platform Nov 4-6 2025'!C:C,1,FALSE),VLOOKUP(F738,'Raw Platform Nov 4-6 2025'!D:D,1,FALSE)),IFNA(VLOOKUP(F738,'Glovo Raw Nov 4-6 2025'!B:B,1,FALSE),"Not Matched")))))) | H738: =COUNTIF(F:F,F738) | I738: Nov 4, 2025, 5:26:34 PM | J738: Uber Eats | K738: PAID | L738: ALEXANDER H. | M738: 0711679869 | N738: Tabere Heights Apartments - Kileleshwa, Tabere Crescent, Nairobi, Kenya | O738: 8.0 | P738: 2.6 | Q738: 0 | R738: MOTORCYCLE | S738: Little Italy | T738: false | U738: true | V738: Nov 4, 2025, 5:38:35 PM | X738: 102.3
... A796: village-market | B796: +254758380544 | C796: Kenneth Nginga | D796: Village Market NRB | E796: COMPLETED | F796: PICKUP-FISHSAUCE | G796: =IF(K796="Pick-up","PICKUPS",IF(K796="Staff drop-off","STAFF_DROPOFF",IF(K796="Replacements","REPLACEMENT",IF(K796="Central Stores Dispatch","CENTRAL STORES DISPATCH",IFNA(IFNA(VLOOKUP(F796,'Raw Platform Nov 4-6 2025'!C:C,1,FALSE),VLOOKUP(F796,'Raw Platform Nov 4-6 2025'!D:D,1,FALSE)),IFNA(VLOOKUP(F796,'Glovo Raw Nov 4-6 2025'!B:B,1,FALSE),"Not Matched")))))) | H796: =COUNTIF(F:F,F796) | I796: Nov 4, 2025, 1:47:34 PM | J796: Pick-up | K796: PAID | L796: VM | M796: 0799133519 | N796: Purvi House, Nairobi, Kenya | O796: 15.0 | P796: 6.2 | Q796: 0 | R796: MOTORCYCLE | S796: Pick- Ups | T796: false | U796: true | V796: Nov 4, 2025, 3:02:26 PM | X796: 185.1
A797: tamu-tamu-dishes-westlands | B797: +254758380544 | C797: Kenneth Nginga | E797: REJECTED | F797: 139535 | G797: =IF(K797="Pick-up","PICKUPS",IF(K797="Staff drop-off","STAFF_DROPOFF",IF(K797="Replacements","REPLACEMENT",IF(K797="Central Stores Dispatch","CENTRAL STORES DISPATCH",IFNA(IFNA(VLOOKUP(F797,'Raw Platform Nov 4-6 2025'!C:C,1,FALSE),VLOOKUP(F797,'Raw Platform Nov 4-6 2025'!D:D,1,FALSE)),IFNA(VLOOKUP(F797,'Glovo Raw Nov 4-6 2025'!B:B,1,FALSE),"Not Matched")))))) | H797: =COUNTIF(F:F,F797) | I797: Nov 4, 2025, 1:35:00 PM | J797: Ando App | K797: UNPAID | L797: Vineet | M797: +254758407982 | N797: Purvi House | O797: 3.0 | P797: 0.4 | Q797: 2160 | R797: MOTORCYCLE | T797: false | U797: false | V797: Nov 4, 2025, 1:35:00 PM | X797: 0
A798: village-market | B798: +254758380544 | C798: Kenneth Nginga | D798: Village Market NRB | E798: COMPLETED | F798: 2EC23 | G798: =IF(K798="Pick-up","PICKUPS",IF(K798="Staff drop-off","STAFF_DROPOFF",IF(K798="Replacements","REPLACEMENT",IF(K798="Central Stores Dispatch","CENTRAL STORES DISPATCH",IFNA(IFNA(VLOOKUP(F798,'Raw Platform Nov 4-6 2025'!C:C,1,FALSE),VLOOKUP(F798,'Raw Platform Nov 4-6 2025'!D:D,1,FALSE)),IFNA(VLOOKUP(F798,'Glovo Raw Nov 4-6 2025'!B:B,1,FALSE),"Not Matched")))))) | H798: =COUNTIF(F:F,F798) | I798: Nov 4, 2025, 1:14:43 PM | J798: Uber Eats | K798: UNPAID | L798: PURITY M | M798: 0722583609 | N798: Rivunia Apartments, Ruaka, Kenya | O798: 17.0 | P798: 7.1 | Q798: 1145 | R798: MOTORCYCLE | S798: Khan's Pakistani Kitchen | T798: false | U798: true | V798: Nov 4, 2025, 1:44:19 PM | X798: 205.8
A799: village-market | B799: +254758380544 | C799: Kenneth Nginga | D799: Village Market NRB | E799: COMPLETED | F799: 6F2DA | G799: =IF(K799="Pick-up","PICKUPS",IF(K799="Staff drop-off","STAFF_DROPOFF",IF(K799="Replacements","REPLACEMENT",IF(K799="Central Stores Dispatch","CENTRAL STORES DISPATCH",IFNA(IFNA(VLOOKUP(F799,'Raw Platform Nov 4-6 2025'!C:C,1,FALSE),VLOOKUP(F799,'Raw Platform Nov 4-6 2025'!D:D,1,FALSE)),IFNA(VLOOKUP(F799,'Glovo Raw Nov 4-6 2025'!B:B,1,FALSE),"Not Matched")))))) | H799: =COUNTIF(F:F,F799) | I799: Nov 4, 2025, 12:10:00 PM | J799: Uber Eats | K799: PAID | L799: MUJIN L. | M799: 0713568049 | N799: Gachie, Kenya | O799: 13.0 | P799: 4.8 | Q799: 0 | R799: MOTORCYCLE | S799: Siam - Thai Kitchen | T799: false | U799: true | V799: Nov 4, 2025, 12:25:02 PM | X799: 152.9
A800: village-market | B800: +254758380544 | C800: Kenneth Nginga | D800: Village Market NRB | E800: COMPLETED | F800: 2807D | G800: =IF(K800="Pick-up","PICKUPS",IF(K800="Staff drop-off","STAFF_DROPOFF",IF(K800="Replacements","REPLACEMENT",IF(K800="Central Stores Dispatch","CENTRAL STORES DISPATCH",IFNA(IFNA(VLOOKUP(F800,'Raw Platform Nov 4-6 2025'!C:C,1,FALSE),VLOOKUP(F800,'Raw Platform Nov 4-6 2025'!D:D,1,FALSE)),IFNA(VLOOKUP(F800,'Glovo Raw Nov 4-6 2025'!B:B,1,FALSE),"Not Matched")))))) | H800: =COUNTIF(F:F,F800) | I800: Nov 4, 2025, 12:09:00 PM | J800: Uber Eats | K800: PAID | L800: BEA E. | M800: 0748459451 | N800: Enaki Town, Red Hill Road, Nairobi, Kenya | O800: 7.0 | P800: 2.7 | Q800: 0 | R800: MOTORCYCLE | S800: Siam - Thai Kitchen | T800: false | U800: true | V800: Nov 4, 2025, 12:23:29 PM | X800: 104.6
A801: village-market | B801: +254758380544 | C801: Kenneth Nginga | D801: Village Market NRB | E801: COMPLETED | F801: 92261 | G801: =IF(K801="Pick-up","PICKUPS",IF(K801="Staff drop-off","STAFF_DROPOFF",IF(K801="Replacements","REPLACEMENT",IF(K801="Central Stores Dispatch","CENTRAL STORES DISPATCH",IFNA(IFNA(VLOOKUP(F801,'Raw Platform Nov 4-6 2025'!C:C,1,FALSE),VLOOKUP(F801,'Raw Platform Nov 4-6 2025'!D:D,1,FALSE)),IFNA(VLOOKUP(F801,'Glovo Raw Nov 4-6 2025'!B:B,1,FALSE),"Not Matched")))))) | H801: =COUNTIF(F:F,F801) | I801: Nov 4, 2025, 11:49:00 AM | J801: Uber Eats | K801: UNPAID | L801: HANNES B. | M801: +017078187070 | N801: Enaki Town, Red Hill Road, Nairobi, Kenya | O801: 7.0 | P801: 2.7 | Q801: 740 | R801: MOTORCYCLE | S801: DILLI! - Curries & Grill | T801: false | U801: true | V801: Nov 4, 2025, 12:21:11 PM | X801: 104.6
A802: village-market | B802: +254758380544 | C802: Kenneth Nginga | D802: Village Market NRB | E802: COMPLETED | F802: 2BBEC | G802: =IF(K802="Pick-up","PICKUPS",IF(K802="Staff drop-off","STAFF_DROPOFF",IF(K802="Replacements","REPLACEMENT",IF(K802="Central Stores Dispatch","CENTRAL STORES DISPATCH",IFNA(IFNA(VLOOKUP(F802,'Raw Platform Nov 4-6 2025'!C:C,1,FALSE),VLOOKUP(F802,'Raw Platform Nov 4-6 2025'!D:D,1,FALSE)),IFNA(VLOOKUP(F802,'Glovo Raw Nov 4-6 2025'!B:B,1,FALSE),"Not Matched")))))) | H802: =COUNTIF(F:F,F802) | I802: Nov 4, 2025, 10:50:00 AM | J802: Uber Eats | K802: PAID | L802: MUTHONI K. | M802: 0719346939 | N802: 17 Thigiri Road, Nairobi, Kenya | O802: 7.0 | P802: 2.8 | Q802: 0 | R802: MOTORCYCLE | S802: Siam - Thai Kitchen | T802: false | U802: true | V802: Nov 4, 2025, 11:08:53 AM | X802: 106.9
A803: village-market | B803: +254758380544 | C803: Kenneth Nginga | D803: Village Market NRB | E803: COMPLETED | F803: INVOICES(VM-PURVI). | G803: =IF(K803="Pick-up","PICKUPS",IF(K803="Staff drop-off","STAFF_DROPOFF",IF(K803="Replacements","REPLACEMENT",IF(K803="Central Stores Dispatch","CENTRAL STORES DISPATCH",IFNA(IFNA(VLOOKUP(F803,'Raw Platform Nov 4-6 2025'!C:C,1,FALSE),VLOOKUP(F803,'Raw Platform Nov 4-6 2025'!D:D,1,FALSE)),IFNA(VLOOKUP(F803,'Glovo Raw Nov 4-6 2025'!B:B,1,FALSE),"Not Matched")))))) | H803: =COUNTIF(F:F,F803) | I803: Nov 3, 2025, 3:34:19 PM | J803: Pick-up | K803: PAID | L803: VM | M803: 0799133519 | N803: Purvi House, Nairobi, Kenya | O803: 15.0 | P803: 6.2 | Q803: 0 | R803: MOTORCYCLE | S803: Pick- Ups | T803: false | U803: true | V803: Nov 4, 2025, 2:47:04 PM | X803: 185.1
A804: westlands-copy-2 | B804: +254791301548 | C804: Kevin Aloo | D804: Kilimani NRB | E804: COMPLETED | F804: 7D135 | G804: =IF(K804="Pick-up","PICKUPS",IF(K804="Staff drop-off","STAFF_DROPOFF",IF(K804="Replacements","REPLACEMENT",IF(K804="Central Stores Dispatch","CENTRAL STORES DISPATCH",IFNA(IFNA(VLOOKUP(F804,'Raw Platform Nov 4-6 2025'!C:C,1,FALSE),VLOOKUP(F804,'Raw Platform Nov 4-6 2025'!D:D,1,FALSE)),IFNA(VLOOKUP(F804,'Glovo Raw Nov 4-6 2025'!B:B,1,FALSE),"Not Matched")))))) | H804: =COUNTIF(F:F,F804) | I804: Nov 6, 2025, 9:15:13 PM | J804: Uber Eats | K804: PAID | L804: SAMIRA O. | M804: 0758319732 | N804: Staroot Residences, Wood Avenue, Nairobi, Kenya | O804: 3.0 | P804: 0.5 | Q804: 0 | R804: MOTORCYCLE | S804: Siam - Thai Kitchen | T804: false | U804: true | V804: Nov 6, 2025, 9:25:21 PM | X804: 100
A805: westlands-copy-2 | B805: +254791301548 | C805: Kevin Aloo | D805: AURO | E805: COMPLETED | F805: C8C6B | G805: =IF(K805="Pick-up","PICKUPS",IF(K805="Staff drop-off","STAFF_DROPOFF",IF(K805="Replacements","REPLACEMENT",IF(K805="Central Stores Dispatch","CENTRAL STORES DISPATCH",IFNA(IFNA(VLOOKUP(F805,'Raw Platform Nov 4-6 2025'!C:C,1,FALSE),VLOOKUP(F805,'Raw Platform Nov 4-6 2025'!D:D,1,FALSE)),IFNA(VLOOKUP(F805,'Glovo Raw Nov 4-6 2025'!B:B,1,FALSE),"Not Matched")))))) | H805: =COUNTIF(F:F,F805) | I805: Nov 6, 2025, 8:02:03 PM | J805: Uber Eats | K805: PAID | L805: NAHIA A. | M805: 0787664748 | N805: Alkira Residences, Othaya Road, Nairobi, Kenya | O805: 9.0 | P805: 2.4 | Q805: 0 | R805: MOTORCYCLE | S805: KAI The Sushi Bar | T805: false | U805: true | V805: Nov 6, 2025, 8:37:29 PM | X805: 100
A806: westlands-copy-2 | B806: +254791301548 | C806: Kevin Aloo | D806: Kilimani NRB | E806: COMPLETED | F806: 3BDA1 | G806: =IF(K806="Pick-up","PICKUPS",IF(K806="Staff drop-off","STAFF_DROPOFF",IF(K806="Replacements","REPLACEMENT",IF(K806="Central Stores Dispatch","CENTRAL STORES DISPATCH",IFNA(IFNA(VLOOKUP(F806,'Raw Platform Nov 4-6 2025'!C:C,1,FALSE),VLOOKUP(F806,'Raw Platform Nov 4-6 2025'!D:D,1,FALSE)),IFNA(VLOOKUP(F806,'Glovo Raw Nov 4-6 2025'!B:B,1,FALSE),"Not Matched")))))) | H806: =COUNTIF(F:F,F806) | I806: Nov 6, 2025, 7:29:57 PM | J806: Uber Eats | K806: PAID | L806: SHIWEI L. | M806: 0704339615 | N806: Lalucia Court, Mugoiri Road, Nairobi, Kenya | O806: 9.0 | P806: 2.7 | Q806: 0 | R806: MOTORCYCLE | S806: Marty's Famous Burgers | T806: false | U806: true | V806: Nov 6, 2025, 7:51:18 PM | X806: 104.6
A807: westlands-copy-2 | B807: +254791301548 | C807: Kevin Aloo | D807: AURO | E807: COMPLETED | F807: FEACF | G807: =IF(K807="Pick-up","PICKUPS",IF(K807="Staff drop-off","STAFF_DROPOFF",IF(K807="Replacements","REPLACEMENT",IF(K807="Central Stores Dispatch","CENTRAL STORES DISPATCH",IFNA(IFNA(VLOOKUP(F807,'Raw Platform Nov 4-6 2025'!C:C,1,FALSE),VLOOKUP(F807,'Raw Platform Nov 4-6 2025'!D:D,1,FALSE)),IFNA(VLOOKUP(F807,'Glovo Raw Nov 4-6 2025'!B:B,1,FALSE),"Not Matched")))))) | H807: =COUNTIF(F:F,F807) | I807: Nov 6, 2025, 6:40:40 PM | J807: Uber Eats | K807: UNPAID | L807: ESTHER K. | M807: 0713726607 | N807: The CUBE-Riverside, Nairobi, Kenya | O807: 12.0 | P807: 4.5 | Q807: 3263 | R807: MOTORCYCLE | S807: KAI The Sushi Bar | T807: false | U807: true | V807: Nov 6, 2025, 7:11:10 PM | X807: 146
A808: westlands-copy-2 | B808: +254791301548 | C808: Kevin Aloo | D808: AURO | E808: COMPLETED | F808: BE057 | G808: =IF(K808="Pick-up","PICKUPS",IF(K808="Staff drop-off","STAFF_DROPOFF",IF(K808="Replacements","REPLACEMENT",IF(K808="Central Stores Dispatch","CENTRAL STORES DISPATCH",IFNA(IFNA(VLOOKUP(F808,'Raw Platform Nov 4-6 2025'!C:C,1,FALSE),VLOOKUP(F808,'Raw Platform Nov 4-6 2025'!D:D,1,FALSE)),IFNA(VLOOKUP(F808,'Glovo Raw Nov 4-6 2025'!B:B,1,FALSE),"Not Matched")))))) | H808: =COUNTIF(F:F,F808) | I808: Nov 6, 2025, 4:48:00 PM | J808: Uber Eats | K808: PAID | L808: YUKI K | M808: 0710687912 | N808: Kenya, Nairobi, GTC Apartment | O808: 13.0 | P808: 6.2 | Q808: 0 | R808: MOTORCYCLE | S808: KAI The Sushi Bar | T808: false | U808: true | V808: Nov 6, 2025, 5:20:43 PM | X808: 185.1
A809: westlands-copy-2 | B809: +254791301548 | C809: Kevin Aloo | E809: COMPLETED | F809: 4E193 | G809: =IF(K809="Pick-up","PICKUPS",IF(K809="Staff drop-off","STAFF_DROPOFF",IF(K809="Replacements","REPLACEMENT",IF(K809="Central Stores Dispatch","CENTRAL STORES DISPATCH",IFNA(IFNA(VLOOKUP(F809,'Raw Platform Nov 4-6 2025'!C:C,1,FALSE),VLOOKUP(F809,'Raw Platform Nov 4-6 2025'!D:D,1,FALSE)),IFNA(VLOOKUP(F809,'Glovo Raw Nov 4-6 2025'!B:B,1,FALSE),"Not Matched")))))) | H809: =COUNTIF(F:F,F809) | I809: Nov 6, 2025, 2:49:56 PM | J809: Uber Eats | K809: PAID | L809: Mwas K | M809: 0725808548 | N809: Timau Road, Nairobi, Kenya | O809: 2.0 | P809: 0.2 | Q809: 0 | R809: MOTORCYCLE | T809: false | U809: true | V809: Nov 6, 2025, 3:22:10 PM | X809: 100
A810: westlands-copy-2 | B810: +254791301548 | C810: Kevin Aloo | D810: AURO | E810: COMPLETED | F810: 1D949 | G810: =IF(K810="Pick-up","PICKUPS",IF(K810="Staff drop-off","STAFF_DROPOFF",IF(K810="Replacements","REPLACEMENT",IF(K810="Central Stores Dispatch","CENTRAL STORES DISPATCH",IFNA(IFNA(VLOOKUP(F810,'Raw Platform Nov 4-6 2025'!C:C,1,FALSE),VLOOKUP(F810,'Raw Platform Nov 4-6 2025'!D:D,1,FALSE)),IFNA(VLOOKUP(F810,'Glovo Raw Nov 4-6 2025'!B:B,1,FALSE),"Not Matched")))))) | H810: =COUNTIF(F:F,F810) | I810: Nov 6, 2025, 2:07:48 PM | J810: Uber Eats | K810: PAID | L810: Tamara M | M810: 0769186611 | N810: Phoenix Aviation, Langata Road, Nairobi, Kenya | O810: 14.0 | P810: 5.9 | Q810: 0 | R810: MOTORCYCLE | S810: TastiWok | T810: false | U810: true | V810: Nov 6, 2025, 2:08:35 PM | X810: 178.2
A811: pot-of-jollof | B811: +254791301548 | C811: Kevin Aloo | D811: AURO | E811: COMPLETED | F811: 89935 | G811: =IF(K811="Pick-up","PICKUPS",IF(K811="Staff drop-off","STAFF_DROPOFF",IF(K811="Replacements","REPLACEMENT",IF(K811="Central Stores Dispatch","CENTRAL STORES DISPATCH",IFNA(IFNA(VLOOKUP(F811,'Raw Platform Nov 4-6 2025'!C:C,1,FALSE),VLOOKUP(F811,'Raw Platform Nov 4-6 2025'!D:D,1,FALSE)),IFNA(VLOOKUP(F811,'Glovo Raw Nov 4-6 2025'!B:B,1,FALSE),"Not Matched")))))) | H811: =COUNTIF(F:F,F811) | I811: Nov 6, 2025, 1:16:15 PM | J811: Uber Eats | K811: UNPAID | L811: Folosade O | M811: 0797777711 | N811: Myra Residences, Kindaruma Road, Nairobi, Kenya | O811: 4.0 | P811: 0.7 | Q811: 1977 | R811: MOTORCYCLE | S811: Pot of Jollof Kitchen | T811: false | U811: true | V811: Nov 6, 2025, 1:16:54 PM | X811: 100
A812: westlands-copy-2 | B812: +254791301548 | C812: Kevin Aloo | D812: Kilimani NRB | E812: COMPLETED | F812: 656FD | G812: =IF(K812="Pick-up","PICKUPS",IF(K812="Staff drop-off","STAFF_DROPOFF",IF(K812="Replacements","REPLACEMENT",IF(K812="Central Stores Dispatch","CENTRAL STORES DISPATCH",IFNA(IFNA(VLOOKUP(F812,'Raw Platform Nov 4-6 2025'!C:C,1,FALSE),VLOOKUP(F812,'Raw Platform Nov 4-6 2025'!D:D,1,FALSE)),IFNA(VLOOKUP(F812,'Glovo Raw Nov 4-6 2025'!B:B,1,FALSE),"Not Matched")))))) | H812: =COUNTIF(F:F,F812) | I812: Nov 6, 2025, 12:42:48 PM | J812: Uber Eats | K812: PAID | L812: ZANGOSE T | M812: 0741898352 | N812: Chasewood Park Serviced Apartments, Westlands Avenue, Nairobi, Kenya | O812: 14.0 | P812: 5.6 | Q812: 0 | R812: MOTORCYCLE | S812: Little Italy | T812: false | U812: true | V812: Nov 6, 2025, 1:02:30 PM | X812: 171.3
A813: pot-of-jollof | B813: +254791301548 | C813: Kevin Aloo | D813: AURO | E813: COMPLETED | F813: 00279 | G813: =IF(K813="Pick-up","PICKUPS",IF(K813="Staff drop-off","STAFF_DROPOFF",IF(K813="Replacements","REPLACEMENT",IF(K813="Central Stores Dispatch","CENTRAL STORES DISPATCH",IFNA(IFNA(VLOOKUP(F813,'Raw Platform Nov 4-6 2025'!C:C,1,FALSE),VLOOKUP(F813,'Raw Platform Nov 4-6 2025'!D:D,1,FALSE)),IFNA(VLOOKUP(F813,'Glovo Raw Nov 4-6 2025'!B:B,1,FALSE),"Not Matched")))))) | H813: =COUNTIF(F:F,F813) | I813: Nov 6, 2025, 12:31:57 PM | J813: Uber Eats | K813: PAID | L813: Esua B | M813: 0797777711 | N813: Staroot Residences, Wood Avenue, Nairobi, Kenya | O813: 5.0 | P813: 1.3 | Q813: 0 | R813: MOTORCYCLE | S813: Pot of Jollof Kitchen | T813: false | U813: true | V813: Nov 6, 2025, 1:13:48 PM | X813: 100
A814: westlands-copy-2 | B814: +254791301548 | C814: Kevin Aloo | D814: Kilimani NRB | E814: COMPLETED | F814: 5C65F | G814: =IF(K814="Pick-up","PICKUPS",IF(K814="Staff drop-off","STAFF_DROPOFF",IF(K814="Replacements","REPLACEMENT",IF(K814="Central Stores Dispatch","CENTRAL STORES DISPATCH",IFNA(IFNA(VLOOKUP(F814,'Raw Platform Nov 4-6 2025'!C:C,1,FALSE),VLOOKUP(F814,'Raw Platform Nov 4-6 2025'!D:D,1,FALSE)),IFNA(VLOOKUP(F814,'Glovo Raw Nov 4-6 2025'!B:B,1,FALSE),"Not Matched")))))) | H814: =COUNTIF(F:F,F814) | I814: Nov 6, 2025, 12:05:34 PM | J814: Uber Eats | K814: UNPAID | L814: AUSTINE A | M814: 0724436623 | N814: Avenue 5, Rose Avenue, Nairobi, Kenya | O814: 4.0 | P814: 1.0 | Q814: 1478 | R814: MOTORCYCLE | S814: Little Italy | T814: false | U814: true | V814: Nov 6, 2025, 12:26:50 PM | X814: 100
A815: westlands-copy-2 | B815: +254791301548 | C815: Kevin Aloo | D815: Kilimani NRB | E815: COMPLETED | F815: 8AEF8 | G815: =IF(K815="Pick-up","PICKUPS",IF(K815="Staff drop-off","STAFF_DROPOFF",IF(K815="Replacements","REPLACEMENT",IF(K815="Central Stores Dispatch","CENTRAL STORES DISPATCH",IFNA(IFNA(VLOOKUP(F815,'Raw Platform Nov 4-6 2025'!C:C,1,FALSE),VLOOKUP(F815,'Raw Platform Nov 4-6 2025'!D:D,1,FALSE)),IFNA(VLOOKUP(F815,'Glovo Raw Nov 4-6 2025'!B:B,1,FALSE),"Not Matched")))))) | H815: =COUNTIF(F:F,F815) | I815: Nov 5, 2025, 9:30:48 PM | J815: Uber Eats | K815: PAID | L815: JASON W. | M815: 0700090954 | N815: Mugumo Court Apartments, Nairobi, Kenya | O815: 16.0 | P815: 5.1 | Q815: 0 | R815: MOTORCYCLE | S815: Siam - Thai Kitchen | T815: false | U815: true | V815: Nov 5, 2025, 9:42:52 PM | X815: 159.8
A816: westlands-copy-2 | B816: +254791301548 | C816: Kevin Aloo | D816: Kilimani NRB | E816: COMPLETED | F816: 101476644738 | G816: =IF(K816="Pick-up","PICKUPS",IF(K816="Staff drop-off","STAFF_DROPOFF",IF(K816="Replacements","REPLACEMENT",IF(K816="Central Stores Dispatch","CENTRAL STORES DISPATCH",IFNA(IFNA(VLOOKUP(F816,'Raw Platform Nov 4-6 2025'!C:C,1,FALSE),VLOOKUP(F816,'Raw Platform Nov 4-6 2025'!D:D,1,FALSE)),IFNA(VLOOKUP(F816,'Glovo Raw Nov 4-6 2025'!B:B,1,FALSE),"Not Matched")))))) | H816: =COUNTIF(F:F,F816) | I816: Nov 5, 2025, 8:02:36 PM | J816: Glovo | K816: UNPAID | L816: DOLPHIN | M816: 0740780566 | N816: Kan Apartments - Kileleshwa, Nairobi, Kenya | O816: 10.0 | P816: 3.2 | Q816: 1531 | R816: MOTORCYCLE | S816: Bibi's Swahili Kitchen | T816: false | U816: true | V816: Nov 5, 2025, 8:32:16 PM | X816: 116.1
A817: westlands-copy-2 | B817: +254791301548 | C817: Kevin Aloo | D817: Kilimani NRB | E817: COMPLETED | F817: 5C443 | G817: =IF(K817="Pick-up","PICKUPS",IF(K817="Staff drop-off","STAFF_DROPOFF",IF(K817="Replacements","REPLACEMENT",IF(K817="Central Stores Dispatch","CENTRAL STORES DISPATCH",IFNA(IFNA(VLOOKUP(F817,'Raw Platform Nov 4-6 2025'!C:C,1,FALSE),VLOOKUP(F817,'Raw Platform Nov 4-6 2025'!D:D,1,FALSE)),IFNA(VLOOKUP(F817,'Glovo Raw Nov 4-6 2025'!B:B,1,FALSE),"Not Matched")))))) | H817: =COUNTIF(F:F,F817) | I817: Nov 5, 2025, 7:55:13 PM | J817: Uber Eats | K817: PAID | L817: CARMELLA M. | M817: 0110590919 | N817: Staroot Residences, Wood Avenue, Nairobi, Kenya | O817: 3.0 | P817: 0.5 | Q817: 0 | R817: MOTORCYCLE | S817: Little Italy | T817: false | U817: true | V817: Nov 5, 2025, 8:08:50 PM | X817: 100
A818: westlands-copy-2 | B818: +254791301548 | C818: Kevin Aloo | D818: Kilimani NRB | E818: COMPLETED | F818: 40571 | G818: =IF(K818="Pick-up","PICKUPS",IF(K818="Staff drop-off","STAFF_DROPOFF",IF(K818="Replacements","REPLACEMENT",IF(K818="Central Stores Dispatch","CENTRAL STORES DISPATCH",IFNA(IFNA(VLOOKUP(F818,'Raw Platform Nov 4-6 2025'!C:C,1,FALSE),VLOOKUP(F818,'Raw Platform Nov 4-6 2025'!D:D,1,FALSE)),IFNA(VLOOKUP(F818,'Glovo Raw Nov 4-6 2025'!B:B,1,FALSE),"Not Matched")))))) | H818: =COUNTIF(F:F,F818) | I818: Nov 5, 2025, 7:35:32 PM | J818: Uber Eats | K818: PAID | L818: LEAH M. | M818: 0790869418 | N818: Jade Residency, Kindaruma Road, Nairobi, Kenya | O818: 6.0 | P818: 1.5 | Q818: 0 | R818: MOTORCYCLE | S818: Marty's Famous Burgers | T818: false | U818: true | V818: Nov 5, 2025, 8:06:36 PM | X818: 100
A819: westlands-copy-2 | B819: +254791301548 | C819: Kevin Aloo | D819: Kilimani NRB | E819: COMPLETED | F819: 24339 | G819: =IF(K819="Pick-up","PICKUPS",IF(K819="Staff drop-off","STAFF_DROPOFF",IF(K819="Replacements","REPLACEMENT",IF(K819="Central Stores Dispatch","CENTRAL STORES DISPATCH",IFNA(IFNA(VLOOKUP(F819,'Raw Platform Nov 4-6 2025'!C:C,1,FALSE),VLOOKUP(F819,'Raw Platform Nov 4-6 2025'!D:D,1,FALSE)),IFNA(VLOOKUP(F819,'Glovo Raw Nov 4-6 2025'!B:B,1,FALSE),"Not Matched")))))) | H819: =COUNTIF(F:F,F819) | I819: Nov 5, 2025, 7:15:37 PM | J819: Uber Eats | K819: PAID | L819: NOREEN K. | M819: 0705030903 | N819: The Crescent Apartments, Gatundu Crescent, Nairobi, Kenya | O819: 8.0 | P819: 2.5 | Q819: 0 | R819: MOTORCYCLE | S819: Bibi's Swahili Kitchen | T819: false | U819: true | V819: Nov 5, 2025, 7:27:13 PM | X819: 100
A820: westlands-copy-2 | B820: +254791301548 | C820: Kevin Aloo | D820: Kilimani NRB | E820: COMPLETED | F820: AD9E7 | G820: =IF(K820="Pick-up","PICKUPS",IF(K820="Staff drop-off","STAFF_DROPOFF",IF(K820="Replacements","REPLACEMENT",IF(K820="Central Stores Dispatch","CENTRAL STORES DISPATCH",IFNA(IFNA(VLOOKUP(F820,'Raw Platform Nov 4-6 2025'!C:C,1,FALSE),VLOOKUP(F820,'Raw Platform Nov 4-6 2025'!D:D,1,FALSE)),IFNA(VLOOKUP(F820,'Glovo Raw Nov 4-6 2025'!B:B,1,FALSE),"Not Matched")))))) | H820: =COUNTIF(F:F,F820) | I820: Nov 5, 2025, 7:00:27 PM | J820: Uber Eats | K820: UNPAID | L820: MAZZA L. | M820: 0721634124 | N820: Oloitoktok Court - Kileleshwa, Nairobi, Kenya | O820: 7.0 | P820: 2.3 | Q820: 390 | R820: MOTORCYCLE | S820: Marty's Famous Burgers | T820: false | U820: true | V820: Nov 5, 2025, 7:28:44 PM | X820: 100
A821: westlands-copy-2 | B821: +254791301548 | C821: Kevin Aloo | E821: COMPLETED | F821: 8A3D6 | G821: =IF(K821="Pick-up","PICKUPS",IF(K821="Staff drop-off","STAFF_DROPOFF",IF(K821="Replacements","REPLACEMENT",IF(K821="Central Stores Dispatch","CENTRAL STORES DISPATCH",IFNA(IFNA(VLOOKUP(F821,'Raw Platform Nov 4-6 2025'!C:C,1,FALSE),VLOOKUP(F821,'Raw Platform Nov 4-6 2025'!D:D,1,FALSE)),IFNA(VLOOKUP(F821,'Glovo Raw Nov 4-6 2025'!B:B,1,FALSE),"Not Matched")))))) | H821: =COUNTIF(F:F,F821) | I821: Nov 5, 2025, 5:08:52 PM | J821: Uber Eats | K821: PAID | L821: Suleiman | M821: 0797777711 | N821: MARINA BAY SQUARE, Sports Road, Nairobi, Kenya | O821: 13.0 | P821: 5.4 | Q821: 0 | R821: MOTORCYCLE | T821: false | U821: true | V821: Nov 5, 2025, 5:33:27 PM | X821: 166.7
A822: westlands-copy-2 | B822: +254791301548 | C822: Kevin Aloo | D822: Kilimani NRB | E822: COMPLETED | F822: F37A3 | G822: =IF(K822="Pick-up","PICKUPS",IF(K822="Staff drop-off","STAFF_DROPOFF",IF(K822="Replacements","REPLACEMENT",IF(K822="Central Stores Dispatch","CENTRAL STORES DISPATCH",IFNA(IFNA(VLOOKUP(F822,'Raw Platform Nov 4-6 2025'!C:C,1,FALSE),VLOOKUP(F822,'Raw Platform Nov 4-6 2025'!D:D,1,FALSE)),IFNA(VLOOKUP(F822,'Glovo Raw Nov 4-6 2025'!B:B,1,FALSE),"Not Matched")))))) | H822: =COUNTIF(F:F,F822) | I822: Nov 5, 2025, 3:19:04 PM | J822: Uber Eats | K822: PAID | L822: IMAN E | M822: 0726885529 | N822: Alina Ridge kileleshwa, Oloitoktok Road, Nairobi, Kenya | O822: 8.0 | P822: 2.6 | Q822: 0 | R822: MOTORCYCLE | S822: Bibi's Swahili Kitchen | T822: false | U822: true | V822: Nov 5, 2025, 3:32:43 PM | X822: 102.3
A823: westlands-copy-2 | B823: +254791301548 | C823: Kevin Aloo | D823: AURO | E823: COMPLETED | F823: B5EDA | G823: =IF(K823="Pick-up","PICKUPS",IF(K823="Staff drop-off","STAFF_DROPOFF",IF(K823="Replacements","REPLACEMENT",IF(K823="Central Stores Dispatch","CENTRAL STORES DISPATCH",IFNA(IFNA(VLOOKUP(F823,'Raw Platform Nov 4-6 2025'!C:C,1,FALSE),VLOOKUP(F823,'Raw Platform Nov 4-6 2025'!D:D,1,FALSE)),IFNA(VLOOKUP(F823,'Glovo Raw Nov 4-6 2025'!B:B,1,FALSE),"Not Matched")))))) | H823: =COUNTIF(F:F,F823) | I823: Nov 5, 2025, 12:58:44 PM | J823: Uber Eats | K823: UNPAID | L823: Elma Kajuju K | M823: 0714117685 | N823: Epic Brownstone - Phase 1, Kirawa Road, Nairobi, Kenya | O823: 26.0 | P823: 12.2 | Q823: 2500 | R823: MOTORCYCLE | S823: TastiWok | T823: false | U823: true | V823: Nov 5, 2025, 1:37:00 PM | X823: 323.1
A824: westlands-copy-2 | B824: +254791301548 | C824: Kevin Aloo | D824: Kilimani NRB | E824: COMPLETED | F824: 8F2DD | G824: =IF(K824="Pick-up","PICKUPS",IF(K824="Staff drop-off","STAFF_DROPOFF",IF(K824="Replacements","REPLACEMENT",IF(K824="Central Stores Dispatch","CENTRAL STORES DISPATCH",IFNA(IFNA(VLOOKUP(F824,'Raw Platform Nov 4-6 2025'!C:C,1,FALSE),VLOOKUP(F824,'Raw Platform Nov 4-6 2025'!D:D,1,FALSE)),IFNA(VLOOKUP(F824,'Glovo Raw Nov 4-6 2025'!B:B,1,FALSE),"Not Matched")))))) | H824: =COUNTIF(F:F,F824) | I824: Nov 5, 2025, 12:47:07 PM | J824: Uber Eats | K824: PAID | L824: JACK A. | M824: 0727089013 | N824: Watu - Headquarters, Lower Hill Road, Nairobi, Kenya | O824: 12.0 | P824: 4.7 | Q824: 0 | R824: MOTORCYCLE | S824: Bibi's Swahili Kitchen | T824: false | U824: true | V824: Nov 5, 2025, 12:59:34 PM | X824: 150.6
A825: westlands-copy-2 | B825: +254791301548 | C825: Kevin Aloo | D825: Kilimani NRB | E825: COMPLETED | F825: B7947 | G825: =IF(K825="Pick-up","PICKUPS",IF(K825="Staff drop-off","STAFF_DROPOFF",IF(K825="Replacements","REPLACEMENT",IF(K825="Central Stores Dispatch","CENTRAL STORES DISPATCH",IFNA(IFNA(VLOOKUP(F825,'Raw Platform Nov 4-6 2025'!C:C,1,FALSE),VLOOKUP(F825,'Raw Platform Nov 4-6 2025'!D:D,1,FALSE)),IFNA(VLOOKUP(F825,'Glovo Raw Nov 4-6 2025'!B:B,1,FALSE),"Not Matched")))))) | H825: =COUNTIF(F:F,F825) | I825: Nov 5, 2025, 11:27:09 AM | J825: Uber Eats | K825: PAID | L825: CLAIRE K. | M825: 0722906999 | N825: Mayfair Centre, Ralph Bunche Road, Nairobi, Kenya | O825: 6.0 | P825: 2.0 | Q825: 0 | R825: MOTORCYCLE | S825: Little Italy | T825: false | U825: true | V825: Nov 5, 2025, 11:27:51 AM | X825: 100
A826: westlands-copy-2 | B826: +254791301548 | C826: Kevin Aloo | D826: Kilimani NRB | E826: COMPLETED | F826: C8975 | G826: =IF(K826="Pick-up","PICKUPS",IF(K826="Staff drop-off","STAFF_DROPOFF",IF(K826="Replacements","REPLACEMENT",IF(K826="Central Stores Dispatch","CENTRAL STORES DISPATCH",IFNA(IFNA(VLOOKUP(F826,'Raw Platform Nov 4-6 2025'!C:C,1,FALSE),VLOOKUP(F826,'Raw Platform Nov 4-6 2025'!D:D,1,FALSE)),IFNA(VLOOKUP(F826,'Glovo Raw Nov 4-6 2025'!B:B,1,FALSE),"Not Matched")))))) | H826: =COUNTIF(F:F,F826) | I826: Nov 4, 2025, 8:52:34 PM | J826: Uber Eats | K826: PAID | L826: ELLIOT M. | M826: 0769304599 | N826: Jamesborough Residences, Nairobi, Kenya | O826: 17.0 | P826: 8.1 | Q826: 0 | R826: MOTORCYCLE | S826: Bibi's Swahili Kitchen | T826: false | U826: true | V826: Nov 4, 2025, 9:33:20 PM | X826: 228.8
A827: westlands-copy-2 | B827: +254791301548 | C827: Kevin Aloo | D827: Kilimani NRB | E827: COMPLETED | F827: 101475830948 | G827: =IF(K827="Pick-up","PICKUPS",IF(K827="Staff drop-off","STAFF_DROPOFF",IF(K827="Replacements","REPLACEMENT",IF(K827="Central Stores Dispatch","CENTRAL STORES DISPATCH",IFNA(IFNA(VLOOKUP(F827,'Raw Platform Nov 4-6 2025'!C:C,1,FALSE),VLOOKUP(F827,'Raw Platform Nov 4-6 2025'!D:D,1,FALSE)),IFNA(VLOOKUP(F827,'Glovo Raw Nov 4-6 2025'!B:B,1,FALSE),"Not Matched")))))) | H827: =COUNTIF(F:F,F827) | I827: Nov 4, 2025, 8:09:52 PM | J827: Glovo | K827: PAID | L827: KUL | M827: 0711436435 | N827: Savannah Sands Executive Apartments, Ngong Road, Nairobi, Kenya | O827: 7.0 | P827: 1.9 | Q827: 0 | R827: MOTORCYCLE | S827: Little Italy | T827: false | U827: true | V827: Nov 4, 2025, 8:41:51 PM | X827: 100
A828: westlands-copy-2 | B828: +254791301548 | C828: Kevin Aloo | D828: Kilimani NRB | E828: COMPLETED | F828: 46B28 | G828: =IF(K828="Pick-up","PICKUPS",IF(K828="Staff drop-off","STAFF_DROPOFF",IF(K828="Replacements","REPLACEMENT",IF(K828="Central Stores Dispatch","CENTRAL STORES DISPATCH",IFNA(IFNA(VLOOKUP(F828,'Raw Platform Nov 4-6 2025'!C:C,1,FALSE),VLOOKUP(F828,'Raw Platform Nov 4-6 2025'!D:D,1,FALSE)),IFNA(VLOOKUP(F828,'Glovo Raw Nov 4-6 2025'!B:B,1,FALSE),"Not Matched")))))) | H828: =COUNTIF(F:F,F828) | I828: Nov 4, 2025, 7:35:21 PM | J828: Uber Eats | K828: UNPAID | L828: SHARON M. | M828: 0793552740 | N828: Kristy Homes Apartments, Langata Road, Nairobi, Kenya | O828: 16.0 | P828: 8.0 | Q828: 1046 | R828: MOTORCYCLE | S828: Little Italy | T828: false | U828: true | V828: Nov 4, 2025, 7:59:28 PM | X828: 226.5
A829: westlands-copy-2 | B829: +254791301548 | C829: Kevin Aloo | D829: Kilimani NRB | E829: COMPLETED | F829: E138A | G829: =IF(K829="Pick-up","PICKUPS",IF(K829="Staff drop-off","STAFF_DROPOFF",IF(K829="Replacements","REPLACEMENT",IF(K829="Central Stores Dispatch","CENTRAL STORES DISPATCH",IFNA(IFNA(VLOOKUP(F829,'Raw Platform Nov 4-6 2025'!C:C,1,FALSE),VLOOKUP(F829,'Raw Platform Nov 4-6 2025'!D:D,1,FALSE)),IFNA(VLOOKUP(F829,'Glovo Raw Nov 4-6 2025'!B:B,1,FALSE),"Not Matched")))))) | H829: =COUNTIF(F:F,F829) | I829: Nov 4, 2025, 6:43:57 PM | J829: Uber Eats | K829: UNPAID | L829: CELINE J. | M829: 0769304599 | N829: Nandwa IVY Residence, Othaya Road, Nairobi, Kenya | O829: 8.0 | P829: 2.6 | Q829: 3208 | R829: MOTORCYCLE | S829: Little Italy | T829: false | U829: true | V829: Nov 4, 2025, 7:05:25 PM | X829: 102.3
A830: westlands-copy-2 | B830: +254791301548 | C830: Kevin Aloo | E830: COMPLETED | F830: F91CB | G830: =IF(K830="Pick-up","PICKUPS",IF(K830="Staff drop-off","STAFF_DROPOFF",IF(K830="Replacements","REPLACEMENT",IF(K830="Central Stores Dispatch","CENTRAL STORES DISPATCH",IFNA(IFNA(VLOOKUP(F830,'Raw Platform Nov 4-6 2025'!C:C,1,FALSE),VLOOKUP(F830,'Raw Platform Nov 4-6 2025'!D:D,1,FALSE)),IFNA(VLOOKUP(F830,'Glovo Raw Nov 4-6 2025'!B:B,1,FALSE),"Not Matched")))))) | H830: =COUNTIF(F:F,F830) | I830: Nov 4, 2025, 5:51:03 PM | J830: Uber Eats | K830: UNPAID | L830: MARY L | M830: 0113161443 | N830: Makongeni Police Station., Nairobi, Kenya | O830: 21.0 | P830: 9.7 | Q830: 1900 | R830: MOTORCYCLE | T830: false | U830: true | V830: Nov 4, 2025, 5:59:54 PM | X830: 265.6
A831: westlands-copy-2 | B831: +254791301548 | C831: Kevin Aloo | D831: AURO | E831: COMPLETED | F831: 4A5AB | G831: =IF(K831="Pick-up","PICKUPS",IF(K831="Staff drop-off","STAFF_DROPOFF",IF(K831="Replacements","REPLACEMENT",IF(K831="Central Stores Dispatch","CENTRAL STORES DISPATCH",IFNA(IFNA(VLOOKUP(F831,'Raw Platform Nov 4-6 2025'!C:C,1,FALSE),VLOOKUP(F831,'Raw Platform Nov 4-6 2025'!D:D,1,FALSE)),IFNA(VLOOKUP(F831,'Glovo Raw Nov 4-6 2025'!B:B,1,FALSE),"Not Matched")))))) | H831: =COUNTIF(F:F,F831) | I831: Nov 4, 2025, 5:17:29 PM | J831: Uber Eats | K831: PAID | L831: DANIEL J | M831: 0759120311 | N831: 14 Mbaazi Road, Nairobi, Kenya | O831: 13.0 | P831: 4.0 | Q831: 0 | R831: MOTORCYCLE | S831: Pot of Jollof Kitchen | T831: false | U831: true | V831: Nov 4, 2025, 5:27:11 PM | X831: 134.5
A832: westlands-copy-2 | B832: +254791301548 | C832: Kevin Aloo | D832: AURO | E832: REJECTED | F832: 4A5AB | G832: =IF(K832="Pick-up","PICKUPS",IF(K832="Staff drop-off","STAFF_DROPOFF",IF(K832="Replacements","REPLACEMENT",IF(K832="Central Stores Dispatch","CENTRAL STORES DISPATCH",IFNA(IFNA(VLOOKUP(F832,'Raw Platform Nov 4-6 2025'!C:C,1,FALSE),VLOOKUP(F832,'Raw Platform Nov 4-6 2025'!D:D,1,FALSE)),IFNA(VLOOKUP(F832,'Glovo Raw Nov 4-6 2025'!B:B,1,FALSE),"Not Matched")))))) | H832: =COUNTIF(F:F,F832) | I832: Nov 4, 2025, 5:17:29 PM | J832: Uber Eats | K832: PAID | L832: DANIEL J | M832: 0759120311 | N832: 14 Mbaazi Road, Nairobi, Kenya | O832: 13.0 | P832: 4.0 | Q832: 0 | R832: MOTORCYCLE | S832: Pot of Jollof Kitchen | T832: false | U832: false | V832: Nov 4, 2025, 5:20:22 PM | X832: 0
A833: westlands-copy-2 | B833: +254791301548 | C833: Kevin Aloo | D833: Kilimani NRB | E833: COMPLETED | F833: 5F449 | G833: =IF(K833="Pick-up","PICKUPS",IF(K833="Staff drop-off","STAFF_DROPOFF",IF(K833="Replacements","REPLACEMENT",IF(K833="Central Stores Dispatch","CENTRAL STORES DISPATCH",IFNA(IFNA(VLOOKUP(F833,'Raw Platform Nov 4-6 2025'!C:C,1,FALSE),VLOOKUP(F833,'Raw Platform Nov 4-6 2025'!D:D,1,FALSE)),IFNA(VLOOKUP(F833,'Glovo Raw Nov 4-6 2025'!B:B,1,FALSE),"Not Matched")))))) | H833: =COUNTIF(F:F,F833) | I833: Nov 4, 2025, 3:55:24 PM | J833: Uber Eats | K833: PAID | L833: TROY G. | M833: +141578618750 | N833: iMAGINE by benaa, Wood Avenue, Nairobi, Kenya | O833: 4.0 | P833: 0.9 | Q833: 0 | R833: MOTORCYCLE | S833: Siam - Thai Kitchen | T833: false | U833: true | V833: Nov 4, 2025, 4:11:31 PM | X833: 100
A834: village-market | B834: +254799956687 | C834: Kevin Auko | D834: Village Market NRB | E834: COMPLETED | F834: 57A80 | G834: =IF(K834="Pick-up","PICKUPS",IF(K834="Staff drop-off","STAFF_DROPOFF",IF(K834="Replacements","REPLACEMENT",IF(K834="Central Stores Dispatch","CENTRAL STORES DISPATCH",IFNA(IFNA(VLOOKUP(F834,'Raw Platform Nov 4-6 2025'!C:C,1,FALSE),VLOOKUP(F834,'Raw Platform Nov 4-6 2025'!D:D,1,FALSE)),IFNA(VLOOKUP(F834,'Glovo Raw Nov 4-6 2025'!B:B,1,FALSE),"Not Matched")))))) | H834: =COUNTIF(F:F,F834) | I834: Nov 6, 2025, 8:17:00 PM | J834: Uber Eats | K834: UNPAID | L834: SHEILA C. | M834: 0712895566 | N834: Ikigai Nairobi (Brookside), The Piano, Brookside Drive, Nairobi, Kenya | O834: 13.0 | P834: 5.6 | Q834: 2890 | R834: MOTORCYCLE | S834: Marty's Famous Burgers | T834: false | U834: true | V834: Nov 6, 2025, 8:37:29 PM | X834: 171.3
A835: village-market | B835: +254799956687 | C835: Kevin Auko | D835: AURO | E835: COMPLETED | F835: 00424 | G835: =IF(K835="Pick-up","PICKUPS",IF(K835="Staff drop-off","STAFF_DROPOFF",IF(K835="Replacements","REPLACEMENT",IF(K835="Central Stores Dispatch","CENTRAL STORES DISPATCH",IFNA(IFNA(VLOOKUP(F835,'Raw Platform Nov 4-6 2025'!C:C,1,FALSE),VLOOKUP(F835,'Raw Platform Nov 4-6 2025'!D:D,1,FALSE)),IFNA(VLOOKUP(F835,'Glovo Raw Nov 4-6 2025'!B:B,1,FALSE),"Not Matched")))))) | H835: =COUNTIF(F:F,F835) | I835: Nov 6, 2025, 6:31:05 PM | J835: Uber Eats | K835: PAID | L835: ryan c | M835: 0799133519 | N835: Daisy Court 4 - Fourways Junction, Nairobi, Kenya | O835: 22.0 | P835: 8.7 | Q835: 0 | R835: MOTORCYCLE | S835: KAI The Sushi Bar | T835: false | U835: true | V835: Nov 6, 2025, 7:31:52 PM | X835: 242.6
A836: village-market | B836: +254799956687 | C836: Kevin Auko | D836: AURO | E836: COMPLETED | F836: a5c44 | G836: =IF(K836="Pick-up","PICKUPS",IF(K836="Staff drop-off","STAFF_DROPOFF",IF(K836="Replacements","REPLACEMENT",IF(K836="Central Stores Dispatch","CENTRAL STORES DISPATCH",IFNA(IFNA(VLOOKUP(F836,'Raw Platform Nov 4-6 2025'!C:C,1,FALSE),VLOOKUP(F836,'Raw Platform Nov 4-6 2025'!D:D,1,FALSE)),IFNA(VLOOKUP(F836,'Glovo Raw Nov 4-6 2025'!B:B,1,FALSE),"Not Matched")))))) | H836: =COUNTIF(F:F,F836) | I836: Nov 6, 2025, 6:20:24 PM | J836: Uber Eats | K836: PAID | L836: maxence | M836: 0115293493 | N836: High View Lane, Nairobi, Kenya | O836: 19.0 | P836: 8.8 | Q836: 0 | R836: MOTORCYCLE | S836: KAI The Sushi Bar | T836: false | U836: true | V836: Nov 6, 2025, 6:02:55 PM | X836: 244.9
A837: village-market | B837: +254799956687 | C837: Kevin Auko | D837: AURO | E837: COMPLETED | F837: 8E543 | G837: =IF(K837="Pick-up","PICKUPS",IF(K837="Staff drop-off","STAFF_DROPOFF",IF(K837="Replacements","REPLACEMENT",IF(K837="Central Stores Dispatch","CENTRAL STORES DISPATCH",IFNA(IFNA(VLOOKUP(F837,'Raw Platform Nov 4-6 2025'!C:C,1,FALSE),VLOOKUP(F837,'Raw Platform Nov 4-6 2025'!D:D,1,FALSE)),IFNA(VLOOKUP(F837,'Glovo Raw Nov 4-6 2025'!B:B,1,FALSE),"Not Matched")))))) | H837: =COUNTIF(F:F,F837) | I837: Nov 5, 2025, 7:42:17 PM | J837: Uber Eats | K837: PAID | L837: ANNE C | M837: 0711106094 | N837: Kamiti Ridge Estate, Tatu City, Kenya | O837: 36.0 | P837: 17.8 | Q837: 0 | R837: MOTORCYCLE | S837: KAI The Sushi Bar | T837: false | U837: true | V837: Nov 5, 2025, 7:44:08 PM | X837: 451.9
A838: village-market | B838: +254799956687 | C838: Kevin Auko | D838: Village Market NRB | E838: COMPLETED | F838: 0550E | G838: =IF(K838="Pick-up","PICKUPS",IF(K838="Staff drop-off","STAFF_DROPOFF",IF(K838="Replacements","REPLACEMENT",IF(K838="Central Stores Dispatch","CENTRAL STORES DISPATCH",IFNA(IFNA(VLOOKUP(F838,'Raw Platform Nov 4-6 2025'!C:C,1,FALSE),VLOOKUP(F838,'Raw Platform Nov 4-6 2025'!D:D,1,FALSE)),IFNA(VLOOKUP(F838,'Glovo Raw Nov 4-6 2025'!B:B,1,FALSE),"Not Matched")))))) | H838: =COUNTIF(F:F,F838) | I838: Nov 5, 2025, 6:47:06 PM | J838: Uber Eats | K838: PAID | L838: DOREEN N | M838: 0715220400 | N838: Natasha Avenue, Kiambu, Kenya | O838: 16.0 | P838: 7.3 | Q838: 0 | R838: MOTORCYCLE | S838: Siam - Thai Kitchen | T838: false | U838: true | V838: Nov 5, 2025, 7:06:58 PM | X838: 210.4
...

Sheet Payment Summary Nov 4-6 2025
A1: Rider | B1: (unknown) | C1: AURO | D1: Kilimani NRB | E1: NSK NRB | F1: Test | G1: Village Market NRB | H1: Westlands NRB | I1: Total Earnings | J1: Deposit | K1: Welfare | L1: Grand Total
A2: Abdulaziz Juma Ebikes | B2: 0 | C2: 0 | D2: 0 | E2: 0 | F2: 0 | G2: 0 | H2: 0 | I2: =SUM(B2:H2) | J2: 50 | K2: 50 | L2: =I2-J2-K2
A3: Abraham Koech | B3: 0 | C3: 0 | D3: 0 | E3: 1202.5 | F3: 0 | G3: 0 | H3: 484 | I3: =SUM(B3:H3) | J3: 50 | K3: 50 | L3: =I3-J3-K3
A4: Allan Fedha | B4: 0 | C4: 479.5 | D4: 811.7 | E4: 0 | F4: 0 | G4: 0 | H4: 0 | I4: =SUM(B4:H4) | J4: 50 | K4: 50 | L4: =I4-J4-K4
A5: Amos Kirui | B5: 0 | C5: 210.4 | D5: 0 | E5: 0 | F5: 0 | G5: 0 | H5: 884 | I5: =SUM(B5:H5) | J5: 50 | K5: 50 | L5: =I5-J5-K5
A6: Benard Ogada | B6: 263.3 | C6: 0 | D6: 205.8 | E6: 1069.2 | F6: 0 | G6: 0 | H6: 3188.1 | I6: =SUM(B6:H6) | J6: 50 | K6: 50 | L6: =I6-J6-K6
A7: Benjamin Oliana | B7: 0 | C7: 0 | D7: 0 | E7: 1393.5 | F7: 0 | G7: 0 | H7: 4756.4 | I7: =SUM(B7:H7) | J7: 50 | K7: 50 | L7: =I7-J7-K7
A8: Benson Miyoyo | B8: 0 | C8: 0 | D8: 0 | E8: 2465.9 | F8: 0 | G8: 0 | H8: 189.7 | I8: =SUM(B8:H8) | J8: 50 | K8: 50 | L8: =I8-J8-K8
A9: Bonface mkuto Lumula | B9: 0 | C9: 309.3 | D9: 0 | E9: 0 | F9: 0 | G9: 0 | H9: 1547.6 | I9: =SUM(B9:H9) | J9: 50 | K9: 50 | L9: =I9-J9-K9
A10: Brian Ngetich | B10: 0 | C10: 554.1 | D10: 0 | E10: 215 | F10: 0 | G10: 0 | H10: 2199.3 | I10: =SUM(B10:H10) | J10: 50 | K10: 50 | L10: =I10-J10-K10
A11: Charles Njeka Ebikes | B11: 0 | C11: 0 | D11: 0 | E11: 0 | F11: 0 | G11: 0 | H11: 0 | I11: =SUM(B11:H11) | J11: 50 | K11: 50 | L11: =I11-J11-K11
A12: Chrispine Omondi | B12: 0 | C12: 0 | D12: 0 | E12: 1964.7 | F12: 0 | G12: 0 | H12: 0 | I12: =SUM(B12:H12) | J12: 50 | K12: 50 | L12: =I12-J12-K12
A13: Cyprien Nsengiyaremye | B13: 2000 | C13: 0 | D13: 0 | E13: 0 | F13: 0 | G13: 0 | H13: 0 | I13: =SUM(B13:H13) | J13: 50 | K13: 50 | L13: =I13-J13-K13
... A71: Wesley Shikanda | B71: 0 | C71: 0 | D71: 0 | E71: 1951.8 | F71: 0 | G71: 0 | H71: 0 | I71: =SUM(B71:H71) | J71: 50 | K71: 50 | L71: =I71-J71-K71
